src/FILTER/DIGITAL_INPUT_FILTER/DIG_INP_FILTER.v
////////////////////////////////////////////////////////////////////////////////////////////
//	Digitales Filter
module	DIG_INP_FILTER (
	input CLK, 
	input IN,
	output reg OUT
	);
//
parameter FILTER = 5'd25;
//
reg [4:0] ctr0;
reg [4:0] ctr1;
//
initial
	begin
	OUT <= 0;
	ctr0 <= 0;
	ctr1 <= 0;
	end
always	@(posedge CLK)
begin
	if (IN && !OUT)
		begin
		ctr0 <= 0;
		ctr1 <= ctr1 + 1;
		end
	//	
	if (!IN && OUT)
		begin
		ctr0 <= ctr0 + 1;
		ctr1 <= 0;
		end	
	//
	if (ctr0 == FILTER)
		begin
		ctr0 <= 0;
		ctr1 <= 0;
		OUT <= 0;
		end
	//
	if (ctr1 == FILTER)
		begin
		ctr0 <= 0;
		ctr1 <= 0;
		OUT <= 1;
		end
	//	
	if (((ctr0 > 0) && IN) || ((ctr1 > 0) && !IN))
		begin
		ctr0 <= 0;
		ctr1 <= 0;
		end	
end
endmodule
////////////////////////////////////////////////////////////////////////////////////////////

src/FILTER/DIGITAL_INPUT_FILTER/ICARUS_TB.v
`include "DIG_INP_FILTER.v"
// http://verilogtutorial.blogspot.ch/2012/09/verilog-timescale-system-tasks.html
`timescale 10ns/1ns
//
module ICARUS_TB;
	integer file;
	reg clk;
	reg in;
	wire out;	
	//
	initial 
		begin
			clk <= 1;
			in <= 0;
			//		
			$dumpfile("vcd\\\icarus_tb.vcd"); 
			$dumpvars(0, ICARUS_TB); 		
			//
			#4 in <= 1;
			//
			#30 in <= 0;
			#4 in <= 1;
			#5 in <= 0;
			#5 in <= 1;
			//
			#30 in <= 0;
			//
			#30 in <= 1;
			#4 in <= 0;
			#5 in <= 1;
			#5 in <= 0;
			//
			#100 $finish; 
		end 
	//
	always #1 clk <= !clk;// 50MHz
	//
	DIG_INP_FILTER dig_inp_filter(clk,
						          in,
						          out);					
	defparam dig_inp_filter.FILTER = 5'd5;
	//
endmodule
/*
cd D:\Dropbox\ABBTS_LABOR_DOZ\MOTION_CONTROL\FPGA_MODUL_MAX1000_DIT_RET_UR\FPGA_MODUL_MAX1000_DIT_RET_UR_00_02\src\BASIS\VERILOG\GLUE_LOGIC
C:\iverilog\bin\iverilog -s ICARUS_TB -o icarus_tb.o ICARUS_TB.v
C:\iverilog\bin\vvp icarus_tb.o
*/

src/FILTER/DIGITAL_INPUT_FILTER/vcd/icarus_tb.vcd
$date
	Sun May 13 07:02:31 2018
$end
$version
	Icarus Verilog
$end
$timescale
	1ns
$end
$scope module ICARUS_TB $end
$var wire 1 ! out $end
$var reg 1 " clk $end
$var reg 1 # in $end
$scope module dig_inp_filter $end
$var wire 1 " CLK $end
$var wire 1 # IN $end
$var reg 1 ! OUT $end
$var reg 5 $ ctr0 [4:0] $end
$var reg 5 % ctr1 [4:0] $end
$upscope $end
$upscope $end
$enddefinitions $end
#0
$dumpvars
b0 %
b0 $
0#
1"
0!
$end
#10
0"
#20
1"
#30
0"
#40
b1 %
1"
1#
#50
0"
#60
b10 %
1"
#70
0"
#80
b11 %
1"
#90
0"
#100
b100 %
1"
#110
0"
#120
b101 %
1"
#130
0"
#140
1!
b0 %
1"
#150
0"
#160
1"
#170
0"
#180
1"
#190
0"
#200
1"
#210
0"
#220
1"
#230
0"
#240
1"
#250
0"
#260
1"
#270
0"
#280
1"
#290
0"
#300
1"
#310
0"
#320
1"
#330
0"
#340
b1 $
1"
0#
#350
0"
#360
b10 $
1"
#370
0"
#380
b0 $
1"
1#
#390
0"
#400
1"
#410
0"
#420
1"
#430
0"
0#
#440
b1 $
1"
#450
0"
#460
b10 $
1"
#470
0"
#480
b0 $
1"
1#
#490
0"
#500
1"
#510
0"
#520
1"
#530
0"
#540
1"
#550
0"
#560
1"
#570
0"
#580
1"
#590
0"
#600
1"
#610
0"
#620
1"
#630
0"
#640
1"
#650
0"
#660
1"
#670
0"
#680
1"
#690
0"
#700
1"
#710
0"
#720
1"
#730
0"
#740
1"
#750
0"
#760
1"
#770
0"
#780
b1 $
1"
0#
#790
0"
#800
b10 $
1"
#810
0"
#820
b11 $
1"
#830
0"
#840
b100 $
1"
#850
0"
#860
b101 $
1"
#870
0"
#880
0!
b0 $
1"
#890
0"
#900
1"
#910
0"
#920
1"
#930
0"
#940
1"
#950
0"
#960
1"
#970
0"
#980
1"
#990
0"
#1000
1"
#1010
0"
#1020
1"
#1030
0"
#1040
1"
#1050
0"
#1060
1"
#1070
0"
#1080
b1 %
1"
1#
#1090
0"
#1100
b10 %
1"
#1110
0"
#1120
b0 %
1"
0#
#1130
0"
#1140
1"
#1150
0"
#1160
1"
#1170
0"
1#
#1180
b1 %
1"
#1190
0"
#1200
b10 %
1"
#1210
0"
#1220
b0 %
1"
0#
