src/ADC_DAC/DAC_MCP4921/DAC_MCP4921.v
////////////////////////////////////////////////////////////////////////////////////////////
module DAC_MCP4921 (
	input CLK,
	input LATCH,
	input [11:0] VALUE,
	output reg CS_DAC,
	output reg CLK_DAC,
	output reg SDO_DAC,
	output reg LDAC_DAC
	);
	//
	reg [15:0] ctr_clk_delay;
	reg [11:0] index;
	reg [15:0] value_temp;
	reg [4:0] state;
	//
	reg hri1; reg hri2; reg hri3; reg hri4;
	wire latch_start;
	wire clk_dac_re;
	wire clk_dac_fe;	
	//
	assign	latch_start = (hri1 && !hri2);
	assign	clk_dac_re = (hri3 && !hri4);
	assign	clk_dac_fe = (!hri3 && hri4);
	//	
	initial
	begin
		
		CS_DAC <= 1;
		CLK_DAC <= 0;
		SDO_DAC <= 0;
		LDAC_DAC <= 1;
		index <= 15;
		value_temp <= 16'b0011000000000000;// Datasheet S.18
		state <= 0;
		ctr_clk_delay <= 1;
		//
		hri1 <= 0; hri2 <= 0;
	end	
	//
	always	@(posedge CLK)
	begin
	// Impulsauswertung
	hri1 <= LATCH;
	hri2 <= hri1;
	hri3 <= CLK_DAC;
	hri4 <= hri3;
	//
	if (state == 0) 
		begin
		CS_DAC <= 1;
		index <= 15;
		value_temp <= 16'b0011000000000000;// Datasheet S.18
		ctr_clk_delay <= 1;
		//
		if(latch_start) 
			begin
			value_temp[11:0] <= VALUE[11:0];
			CS_DAC <= 0;
			state <= 1;
			end
		//
		end
	//
	if (state == 1) 
		begin
		ctr_clk_delay <= ctr_clk_delay + 1;
		if (ctr_clk_delay == 20) 
			begin
			ctr_clk_delay <= 1;
			CLK_DAC <= !CLK_DAC;
			end
		//
		SDO_DAC <= value_temp[index];
		if (clk_dac_fe && (index > 0)) index <= index - 1;
		//
		if (clk_dac_fe && (index == 0)) 
			begin
			ctr_clk_delay <= 1;
			state <= 2;
			end
		end
	//
	if (state == 2) 
		begin
		ctr_clk_delay <= ctr_clk_delay + 1;
		if (ctr_clk_delay == 20) 
			begin
			ctr_clk_delay <= 1;
			CS_DAC <= 1;
			state <= 3;
			end
		end
	//
	if (state == 3) 
		begin
		ctr_clk_delay <= ctr_clk_delay + 1;
		if (ctr_clk_delay == 20) 
			begin
			ctr_clk_delay <= 1;
			LDAC_DAC <= 0;
			state <= 4;
			end
		end
	//
	if (state == 4) 
		begin
		ctr_clk_delay <= ctr_clk_delay + 1;
		if (ctr_clk_delay == 20) 
			begin
			ctr_clk_delay <= 1;
			LDAC_DAC <= 1;
			state <= 0;
			end
		end
	//
	end
endmodule
////////////////////////////////////////////////////////////////////////////////////////////

src/ADC_DAC/DAC_MCP4921/ICARUS_TB.v
`include "DAC_MCP4921.v"
// http://verilogtutorial.blogspot.ch/2012/09/verilog-timescale-system-tasks.html
`timescale 10ns/1ns
//
module ICARUS_TB;
	//
	integer file;
	reg clk;
	reg latch;
	reg [11:0] value;
	wire cs_dac;
	wire clk_dac;
	wire sdo_dac;
	wire ldac_dac;	
	//
	initial 
	begin
		clk <= 1;
		latch <= 0;
		value <= 12'hA21;
		//
		$dumpfile("vcd\\\icarus_tb.vcd"); 
		$dumpvars(0, ICARUS_TB); 
		//
		#50 latch <= 1;
		#50 latch <= 0;
		//
		#2500 $finish; 
	end 
	//
	always #1 clk <= !clk;
	//
	DAC_MCP4921 dac_mcp4921(
					clk,
	                latch,
					value,
			        cs_dac,
			        clk_dac,
			        sdo_dac,
			        ldac_dac
					);
	//
endmodule
//
/*
cd D:\Dropbox\ABBTS_LABOR_DOZ\MOTION_CONTROL\FPGA\FPGA_MODUL_MAX1000_00_21\src\DC_MOTOR
C:\iverilog\bin\iverilog -s ICARUS_TB -o icarus_tb.o ICARUS_TB.v
C:\iverilog\bin\vvp icarus_tb.o
*/

src/ADC_DAC/DAC_MCP4921/vcd/icarus_tb.vcd
$date
	Thu Mar 29 15:41:19 2018
$end
$version
	Icarus Verilog
$end
$timescale
	1ns
$end
$scope module ICARUS_TB $end
$var wire 1 ! sdo_dac $end
$var wire 1 " ldac_dac $end
$var wire 1 # cs_dac $end
$var wire 1 $ clk_dac $end
$var reg 1 % clk $end
$var reg 1 & latch $end
$var reg 12 ' value [11:0] $end
$scope module dac_mcp4921 $end
$var wire 1 % CLK $end
$var wire 1 & LATCH $end
$var wire 12 ( VALUE [11:0] $end
$var wire 1 ) clk_dac_fe $end
$var wire 1 * clk_dac_re $end
$var wire 1 + latch_start $end
$var reg 1 $ CLK_DAC $end
$var reg 1 # CS_DAC $end
$var reg 1 " LDAC_DAC $end
$var reg 1 ! SDO_DAC $end
$var reg 16 , ctr_clk_delay [15:0] $end
$var reg 1 - hri1 $end
$var reg 1 . hri2 $end
$var reg 1 / hri3 $end
$var reg 1 0 hri4 $end
$var reg 12 1 index [11:0] $end
$var reg 5 2 state [4:0] $end
$var reg 16 3 value_temp [15:0] $end
$upscope $end
$upscope $end
$enddefinitions $end
#0
$dumpvars
b11000000000000 3
b0 2
b1111 1
x0
0/
0.
0-
b1 ,
0+
0*
x)
b101000100001 (
b101000100001 '
0&
1%
0$
1#
1"
0!
$end
#10
0%
#20
0)
00
1%
#30
0%
#40
1%
#50
0%
#60
1%
#70
0%
#80
1%
#90
0%
#100
1%
#110
0%
#120
1%
#130
0%
#140
1%
#150
0%
#160
1%
#170
0%
#180
1%
#190
0%
#200
1%
#210
0%
#220
1%
#230
0%
#240
1%
#250
0%
#260
1%
#270
0%
#280
1%
#290
0%
#300
1%
#310
0%
#320
1%
#330
0%
#340
1%
#350
0%
#360
1%
#370
0%
#380
1%
#390
0%
#400
1%
#410
0%
#420
1%
#430
0%
#440
1%
#450
0%
#460
1%
#470
0%
#480
1%
#490
0%
#500
1+
1-
1%
1&
#510
0%
#520
0+
b1 2
0#
b11101000100001 3
1.
1%
#530
0%
#540
b10 ,
1%
#550
0%
#560
b11 ,
1%
#570
0%
#580
b100 ,
1%
#590
0%
#600
b101 ,
1%
#610
0%
#620
b110 ,
1%
#630
0%
#640
b111 ,
1%
#650
0%
#660
b1000 ,
1%
#670
0%
#680
b1001 ,
1%
#690
0%
#700
b1010 ,
1%
#710
0%
#720
b1011 ,
1%
#730
0%
#740
b1100 ,
1%
#750
0%
#760
b1101 ,
1%
#770
0%
#780
b1110 ,
1%
#790
0%
#800
b1111 ,
1%
#810
0%
#820
b10000 ,
1%
#830
0%
#840
b10001 ,
1%
#850
0%
#860
b10010 ,
1%
#870
0%
#880
b10011 ,
1%
#890
0%
#900
b10100 ,
1%
#910
0%
#920
1$
b1 ,
1%
#930
0%
#940
1*
b10 ,
1/
1%
#950
0%
#960
0*
b11 ,
10
1%
#970
0%
#980
b100 ,
1%
#990
0%
#1000
b101 ,
0-
1%
0&
#1010
0%
#1020
b110 ,
0.
1%
#1030
0%
#1040
b111 ,
1%
#1050
0%
#1060
b1000 ,
1%
#1070
0%
#1080
b1001 ,
1%
#1090
0%
#1100
b1010 ,
1%
#1110
0%
#1120
b1011 ,
1%
#1130
0%
#1140
b1100 ,
1%
#1150
0%
#1160
b1101 ,
1%
#1170
0%
#1180
b1110 ,
1%
#1190
0%
#1200
b1111 ,
1%
#1210
0%
#1220
b10000 ,
1%
#1230
0%
#1240
b10001 ,
1%
#1250
0%
#1260
b10010 ,
1%
#1270
0%
#1280
b10011 ,
1%
#1290
0%
#1300
b10100 ,
1%
#1310
0%
#1320
0$
b1 ,
1%
#1330
0%
#1340
1)
b10 ,
0/
1%
#1350
0%
#1360
0)
b1110 1
b11 ,
00
1%
#1370
0%
#1380
b100 ,
1%
#1390
0%
#1400
b101 ,
1%
#1410
0%
#1420
b110 ,
1%
#1430
0%
#1440
b111 ,
1%
#1450
0%
#1460
b1000 ,
1%
#1470
0%
#1480
b1001 ,
1%
#1490
0%
#1500
b1010 ,
1%
#1510
0%
#1520
b1011 ,
1%
#1530
0%
#1540
b1100 ,
1%
#1550
0%
#1560
b1101 ,
1%
#1570
0%
#1580
b1110 ,
1%
#1590
0%
#1600
b1111 ,
1%
#1610
0%
#1620
b10000 ,
1%
#1630
0%
#1640
b10001 ,
1%
#1650
0%
#1660
b10010 ,
1%
#1670
0%
#1680
b10011 ,
1%
#1690
0%
#1700
b10100 ,
1%
#1710
0%
#1720
1$
b1 ,
1%
#1730
0%
#1740
1*
b10 ,
1/
1%
#1750
0%
#1760
0*
b11 ,
10
1%
#1770
0%
#1780
b100 ,
1%
#1790
0%
#1800
b101 ,
1%
#1810
0%
#1820
b110 ,
1%
#1830
0%
#1840
b111 ,
1%
#1850
0%
#1860
b1000 ,
1%
#1870
0%
#1880
b1001 ,
1%
#1890
0%
#1900
b1010 ,
1%
#1910
0%
#1920
b1011 ,
1%
#1930
0%
#1940
b1100 ,
1%
#1950
0%
#1960
b1101 ,
1%
#1970
0%
#1980
b1110 ,
1%
#1990
0%
#2000
b1111 ,
1%
#2010
0%
#2020
b10000 ,
1%
#2030
0%
#2040
b10001 ,
1%
#2050
0%
#2060
b10010 ,
1%
#2070
0%
#2080
b10011 ,
1%
#2090
0%
#2100
b10100 ,
1%
#2110
0%
#2120
0$
b1 ,
1%
#2130
0%
#2140
1)
b10 ,
0/
1%
#2150
0%
#2160
0)
b1101 1
b11 ,
00
1%
#2170
0%
#2180
1!
b100 ,
1%
#2190
0%
#2200
b101 ,
1%
#2210
0%
#2220
b110 ,
1%
#2230
0%
#2240
b111 ,
1%
#2250
0%
#2260
b1000 ,
1%
#2270
0%
#2280
b1001 ,
1%
#2290
0%
#2300
b1010 ,
1%
#2310
0%
#2320
b1011 ,
1%
#2330
0%
#2340
b1100 ,
1%
#2350
0%
#2360
b1101 ,
1%
#2370
0%
#2380
b1110 ,
1%
#2390
0%
#2400
b1111 ,
1%
#2410
0%
#2420
b10000 ,
1%
#2430
0%
#2440
b10001 ,
1%
#2450
0%
#2460
b10010 ,
1%
#2470
0%
#2480
b10011 ,
1%
#2490
0%
#2500
b10100 ,
1%
#2510
0%
#2520
1$
b1 ,
1%
#2530
0%
#2540
1*
b10 ,
1/
1%
#2550
0%
#2560
0*
b11 ,
10
1%
#2570
0%
#2580
b100 ,
1%
#2590
0%
#2600
b101 ,
1%
#2610
0%
#2620
b110 ,
1%
#2630
0%
#2640
b111 ,
1%
#2650
0%
#2660
b1000 ,
1%
#2670
0%
#2680
b1001 ,
1%
#2690
0%
#2700
b1010 ,
1%
#2710
0%
#2720
b1011 ,
1%
#2730
0%
#2740
b1100 ,
1%
#2750
0%
#2760
b1101 ,
1%
#2770
0%
#2780
b1110 ,
1%
#2790
0%
#2800
b1111 ,
1%
#2810
0%
#2820
b10000 ,
1%
#2830
0%
#2840
b10001 ,
1%
#2850
0%
#2860
b10010 ,
1%
#2870
0%
#2880
b10011 ,
1%
#2890
0%
#2900
b10100 ,
1%
#2910
0%
#2920
0$
b1 ,
1%
#2930
0%
#2940
1)
b10 ,
0/
1%
#2950
0%
#2960
0)
b1100 1
b11 ,
00
1%
#2970
0%
#2980
b100 ,
1%
#2990
0%
#3000
b101 ,
1%
#3010
0%
#3020
b110 ,
1%
#3030
0%
#3040
b111 ,
1%
#3050
0%
#3060
b1000 ,
1%
#3070
0%
#3080
b1001 ,
1%
#3090
0%
#3100
b1010 ,
1%
#3110
0%
#3120
b1011 ,
1%
#3130
0%
#3140
b1100 ,
1%
#3150
0%
#3160
b1101 ,
1%
#3170
0%
#3180
b1110 ,
1%
#3190
0%
#3200
b1111 ,
1%
#3210
0%
#3220
b10000 ,
1%
#3230
0%
#3240
b10001 ,
1%
#3250
0%
#3260
b10010 ,
1%
#3270
0%
#3280
b10011 ,
1%
#3290
0%
#3300
b10100 ,
1%
#3310
0%
#3320
1$
b1 ,
1%
#3330
0%
#3340
1*
b10 ,
1/
1%
#3350
0%
#3360
0*
b11 ,
10
1%
#3370
0%
#3380
b100 ,
1%
#3390
0%
#3400
b101 ,
1%
#3410
0%
#3420
b110 ,
1%
#3430
0%
#3440
b111 ,
1%
#3450
0%
#3460
b1000 ,
1%
#3470
0%
#3480
b1001 ,
1%
#3490
0%
#3500
b1010 ,
1%
#3510
0%
#3520
b1011 ,
1%
#3530
0%
#3540
b1100 ,
1%
#3550
0%
#3560
b1101 ,
1%
#3570
0%
#3580
b1110 ,
1%
#3590
0%
#3600
b1111 ,
1%
#3610
0%
#3620
b10000 ,
1%
#3630
0%
#3640
b10001 ,
1%
#3650
0%
#3660
b10010 ,
1%
#3670
0%
#3680
b10011 ,
1%
#3690
0%
#3700
b10100 ,
1%
#3710
0%
#3720
0$
b1 ,
1%
#3730
0%
#3740
1)
b10 ,
0/
1%
#3750
0%
#3760
0)
b1011 1
b11 ,
00
1%
#3770
0%
#3780
b100 ,
1%
#3790
0%
#3800
b101 ,
1%
#3810
0%
#3820
b110 ,
1%
#3830
0%
#3840
b111 ,
1%
#3850
0%
#3860
b1000 ,
1%
#3870
0%
#3880
b1001 ,
1%
#3890
0%
#3900
b1010 ,
1%
#3910
0%
#3920
b1011 ,
1%
#3930
0%
#3940
b1100 ,
1%
#3950
0%
#3960
b1101 ,
1%
#3970
0%
#3980
b1110 ,
1%
#3990
0%
#4000
b1111 ,
1%
#4010
0%
#4020
b10000 ,
1%
#4030
0%
#4040
b10001 ,
1%
#4050
0%
#4060
b10010 ,
1%
#4070
0%
#4080
b10011 ,
1%
#4090
0%
#4100
b10100 ,
1%
#4110
0%
#4120
1$
b1 ,
1%
#4130
0%
#4140
1*
b10 ,
1/
1%
#4150
0%
#4160
0*
b11 ,
10
1%
#4170
0%
#4180
b100 ,
1%
#4190
0%
#4200
b101 ,
1%
#4210
0%
#4220
b110 ,
1%
#4230
0%
#4240
b111 ,
1%
#4250
0%
#4260
b1000 ,
1%
#4270
0%
#4280
b1001 ,
1%
#4290
0%
#4300
b1010 ,
1%
#4310
0%
#4320
b1011 ,
1%
#4330
0%
#4340
b1100 ,
1%
#4350
0%
#4360
b1101 ,
1%
#4370
0%
#4380
b1110 ,
1%
#4390
0%
#4400
b1111 ,
1%
#4410
0%
#4420
b10000 ,
1%
#4430
0%
#4440
b10001 ,
1%
#4450
0%
#4460
b10010 ,
1%
#4470
0%
#4480
b10011 ,
1%
#4490
0%
#4500
b10100 ,
1%
#4510
0%
#4520
0$
b1 ,
1%
#4530
0%
#4540
1)
b10 ,
0/
1%
#4550
0%
#4560
0)
b1010 1
b11 ,
00
1%
#4570
0%
#4580
0!
b100 ,
1%
#4590
0%
#4600
b101 ,
1%
#4610
0%
#4620
b110 ,
1%
#4630
0%
#4640
b111 ,
1%
#4650
0%
#4660
b1000 ,
1%
#4670
0%
#4680
b1001 ,
1%
#4690
0%
#4700
b1010 ,
1%
#4710
0%
#4720
b1011 ,
1%
#4730
0%
#4740
b1100 ,
1%
#4750
0%
#4760
b1101 ,
1%
#4770
0%
#4780
b1110 ,
1%
#4790
0%
#4800
b1111 ,
1%
#4810
0%
#4820
b10000 ,
1%
#4830
0%
#4840
b10001 ,
1%
#4850
0%
#4860
b10010 ,
1%
#4870
0%
#4880
b10011 ,
1%
#4890
0%
#4900
b10100 ,
1%
#4910
0%
#4920
1$
b1 ,
1%
#4930
0%
#4940
1*
b10 ,
1/
1%
#4950
0%
#4960
0*
b11 ,
10
1%
#4970
0%
#4980
b100 ,
1%
#4990
0%
#5000
b101 ,
1%
#5010
0%
#5020
b110 ,
1%
#5030
0%
#5040
b111 ,
1%
#5050
0%
#5060
b1000 ,
1%
#5070
0%
#5080
b1001 ,
1%
#5090
0%
#5100
b1010 ,
1%
#5110
0%
#5120
b1011 ,
1%
#5130
0%
#5140
b1100 ,
1%
#5150
0%
#5160
b1101 ,
1%
#5170
0%
#5180
b1110 ,
1%
#5190
0%
#5200
b1111 ,
1%
#5210
0%
#5220
b10000 ,
1%
#5230
0%
#5240
b10001 ,
1%
#5250
0%
#5260
b10010 ,
1%
#5270
0%
#5280
b10011 ,
1%
#5290
0%
#5300
b10100 ,
1%
#5310
0%
#5320
0$
b1 ,
1%
#5330
0%
#5340
1)
b10 ,
0/
1%
#5350
0%
#5360
0)
b1001 1
b11 ,
00
1%
#5370
0%
#5380
1!
b100 ,
1%
#5390
0%
#5400
b101 ,
1%
#5410
0%
#5420
b110 ,
1%
#5430
0%
#5440
b111 ,
1%
#5450
0%
#5460
b1000 ,
1%
#5470
0%
#5480
b1001 ,
1%
#5490
0%
#5500
b1010 ,
1%
#5510
0%
#5520
b1011 ,
1%
#5530
0%
#5540
b1100 ,
1%
#5550
0%
#5560
b1101 ,
1%
#5570
0%
#5580
b1110 ,
1%
#5590
0%
#5600
b1111 ,
1%
#5610
0%
#5620
b10000 ,
1%
#5630
0%
#5640
b10001 ,
1%
#5650
0%
#5660
b10010 ,
1%
#5670
0%
#5680
b10011 ,
1%
#5690
0%
#5700
b10100 ,
1%
#5710
0%
#5720
1$
b1 ,
1%
#5730
0%
#5740
1*
b10 ,
1/
1%
#5750
0%
#5760
0*
b11 ,
10
1%
#5770
0%
#5780
b100 ,
1%
#5790
0%
#5800
b101 ,
1%
#5810
0%
#5820
b110 ,
1%
#5830
0%
#5840
b111 ,
1%
#5850
0%
#5860
b1000 ,
1%
#5870
0%
#5880
b1001 ,
1%
#5890
0%
#5900
b1010 ,
1%
#5910
0%
#5920
b1011 ,
1%
#5930
0%
#5940
b1100 ,
1%
#5950
0%
#5960
b1101 ,
1%
#5970
0%
#5980
b1110 ,
1%
#5990
0%
#6000
b1111 ,
1%
#6010
0%
#6020
b10000 ,
1%
#6030
0%
#6040
b10001 ,
1%
#6050
0%
#6060
b10010 ,
1%
#6070
0%
#6080
b10011 ,
1%
#6090
0%
#6100
b10100 ,
1%
#6110
0%
#6120
0$
b1 ,
1%
#6130
0%
#6140
1)
b10 ,
0/
1%
#6150
0%
#6160
0)
b1000 1
b11 ,
00
1%
#6170
0%
#6180
0!
b100 ,
1%
#6190
0%
#6200
b101 ,
1%
#6210
0%
#6220
b110 ,
1%
#6230
0%
#6240
b111 ,
1%
#6250
0%
#6260
b1000 ,
1%
#6270
0%
#6280
b1001 ,
1%
#6290
0%
#6300
b1010 ,
1%
#6310
0%
#6320
b1011 ,
1%
#6330
0%
#6340
b1100 ,
1%
#6350
0%
#6360
b1101 ,
1%
#6370
0%
#6380
b1110 ,
1%
#6390
0%
#6400
b1111 ,
1%
#6410
0%
#6420
b10000 ,
1%
#6430
0%
#6440
b10001 ,
1%
#6450
0%
#6460
b10010 ,
1%
#6470
0%
#6480
b10011 ,
1%
#6490
0%
#6500
b10100 ,
1%
#6510
0%
#6520
1$
b1 ,
1%
#6530
0%
#6540
1*
b10 ,
1/
1%
#6550
0%
#6560
0*
b11 ,
10
1%
#6570
0%
#6580
b100 ,
1%
#6590
0%
#6600
b101 ,
1%
#6610
0%
#6620
b110 ,
1%
#6630
0%
#6640
b111 ,
1%
#6650
0%
#6660
b1000 ,
1%
#6670
0%
#6680
b1001 ,
1%
#6690
0%
#6700
b1010 ,
1%
#6710
0%
#6720
b1011 ,
1%
#6730
0%
#6740
b1100 ,
1%
#6750
0%
#6760
b1101 ,
1%
#6770
0%
#6780
b1110 ,
1%
#6790
0%
#6800
b1111 ,
1%
#6810
0%
#6820
b10000 ,
1%
#6830
0%
#6840
b10001 ,
1%
#6850
0%
#6860
b10010 ,
1%
#6870
0%
#6880
b10011 ,
1%
#6890
0%
#6900
b10100 ,
1%
#6910
0%
#6920
0$
b1 ,
1%
#6930
0%
#6940
1)
b10 ,
0/
1%
#6950
0%
#6960
0)
b111 1
b11 ,
00
1%
#6970
0%
#6980
b100 ,
1%
#6990
0%
#7000
b101 ,
1%
#7010
0%
#7020
b110 ,
1%
#7030
0%
#7040
b111 ,
1%
#7050
0%
#7060
b1000 ,
1%
#7070
0%
#7080
b1001 ,
1%
#7090
0%
#7100
b1010 ,
1%
#7110
0%
#7120
b1011 ,
1%
#7130
0%
#7140
b1100 ,
1%
#7150
0%
#7160
b1101 ,
1%
#7170
0%
#7180
b1110 ,
1%
#7190
0%
#7200
b1111 ,
1%
#7210
0%
#7220
b10000 ,
1%
#7230
0%
#7240
b10001 ,
1%
#7250
0%
#7260
b10010 ,
1%
#7270
0%
#7280
b10011 ,
1%
#7290
0%
#7300
b10100 ,
1%
#7310
0%
#7320
1$
b1 ,
1%
#7330
0%
#7340
1*
b10 ,
1/
1%
#7350
0%
#7360
0*
b11 ,
10
1%
#7370
0%
#7380
b100 ,
1%
#7390
0%
#7400
b101 ,
1%
#7410
0%
#7420
b110 ,
1%
#7430
0%
#7440
b111 ,
1%
#7450
0%
#7460
b1000 ,
1%
#7470
0%
#7480
b1001 ,
1%
#7490
0%
#7500
b1010 ,
1%
#7510
0%
#7520
b1011 ,
1%
#7530
0%
#7540
b1100 ,
1%
#7550
0%
#7560
b1101 ,
1%
#7570
0%
#7580
b1110 ,
1%
#7590
0%
#7600
b1111 ,
1%
#7610
0%
#7620
b10000 ,
1%
#7630
0%
#7640
b10001 ,
1%
#7650
0%
#7660
b10010 ,
1%
#7670
0%
#7680
b10011 ,
1%
#7690
0%
#7700
b10100 ,
1%
#7710
0%
#7720
0$
b1 ,
1%
#7730
0%
#7740
1)
b10 ,
0/
1%
#7750
0%
#7760
0)
b110 1
b11 ,
00
1%
#7770
0%
#7780
b100 ,
1%
#7790
0%
#7800
b101 ,
1%
#7810
0%
#7820
b110 ,
1%
#7830
0%
#7840
b111 ,
1%
#7850
0%
#7860
b1000 ,
1%
#7870
0%
#7880
b1001 ,
1%
#7890
0%
#7900
b1010 ,
1%
#7910
0%
#7920
b1011 ,
1%
#7930
0%
#7940
b1100 ,
1%
#7950
0%
#7960
b1101 ,
1%
#7970
0%
#7980
b1110 ,
1%
#7990
0%
#8000
b1111 ,
1%
#8010
0%
#8020
b10000 ,
1%
#8030
0%
#8040
b10001 ,
1%
#8050
0%
#8060
b10010 ,
1%
#8070
0%
#8080
b10011 ,
1%
#8090
0%
#8100
b10100 ,
1%
#8110
0%
#8120
1$
b1 ,
1%
#8130
0%
#8140
1*
b10 ,
1/
1%
#8150
0%
#8160
0*
b11 ,
10
1%
#8170
0%
#8180
b100 ,
1%
#8190
0%
#8200
b101 ,
1%
#8210
0%
#8220
b110 ,
1%
#8230
0%
#8240
b111 ,
1%
#8250
0%
#8260
b1000 ,
1%
#8270
0%
#8280
b1001 ,
1%
#8290
0%
#8300
b1010 ,
1%
#8310
0%
#8320
b1011 ,
1%
#8330
0%
#8340
b1100 ,
1%
#8350
0%
#8360
b1101 ,
1%
#8370
0%
#8380
b1110 ,
1%
#8390
0%
#8400
b1111 ,
1%
#8410
0%
#8420
b10000 ,
1%
#8430
0%
#8440
b10001 ,
1%
#8450
0%
#8460
b10010 ,
1%
#8470
0%
#8480
b10011 ,
1%
#8490
0%
#8500
b10100 ,
1%
#8510
0%
#8520
0$
b1 ,
1%
#8530
0%
#8540
1)
b10 ,
0/
1%
#8550
0%
#8560
0)
b101 1
b11 ,
00
1%
#8570
0%
#8580
1!
b100 ,
1%
#8590
0%
#8600
b101 ,
1%
#8610
0%
#8620
b110 ,
1%
#8630
0%
#8640
b111 ,
1%
#8650
0%
#8660
b1000 ,
1%
#8670
0%
#8680
b1001 ,
1%
#8690
0%
#8700
b1010 ,
1%
#8710
0%
#8720
b1011 ,
1%
#8730
0%
#8740
b1100 ,
1%
#8750
0%
#8760
b1101 ,
1%
#8770
0%
#8780
b1110 ,
1%
#8790
0%
#8800
b1111 ,
1%
#8810
0%
#8820
b10000 ,
1%
#8830
0%
#8840
b10001 ,
1%
#8850
0%
#8860
b10010 ,
1%
#8870
0%
#8880
b10011 ,
1%
#8890
0%
#8900
b10100 ,
1%
#8910
0%
#8920
1$
b1 ,
1%
#8930
0%
#8940
1*
b10 ,
1/
1%
#8950
0%
#8960
0*
b11 ,
10
1%
#8970
0%
#8980
b100 ,
1%
#8990
0%
#9000
b101 ,
1%
#9010
0%
#9020
b110 ,
1%
#9030
0%
#9040
b111 ,
1%
#9050
0%
#9060
b1000 ,
1%
#9070
0%
#9080
b1001 ,
1%
#9090
0%
#9100
b1010 ,
1%
#9110
0%
#9120
b1011 ,
1%
#9130
0%
#9140
b1100 ,
1%
#9150
0%
#9160
b1101 ,
1%
#9170
0%
#9180
b1110 ,
1%
#9190
0%
#9200
b1111 ,
1%
#9210
0%
#9220
b10000 ,
1%
#9230
0%
#9240
b10001 ,
1%
#9250
0%
#9260
b10010 ,
1%
#9270
0%
#9280
b10011 ,
1%
#9290
0%
#9300
b10100 ,
1%
#9310
0%
#9320
0$
b1 ,
1%
#9330
0%
#9340
1)
b10 ,
0/
1%
#9350
0%
#9360
0)
b100 1
b11 ,
00
1%
#9370
0%
#9380
0!
b100 ,
1%
#9390
0%
#9400
b101 ,
1%
#9410
0%
#9420
b110 ,
1%
#9430
0%
#9440
b111 ,
1%
#9450
0%
#9460
b1000 ,
1%
#9470
0%
#9480
b1001 ,
1%
#9490
0%
#9500
b1010 ,
1%
#9510
0%
#9520
b1011 ,
1%
#9530
0%
#9540
b1100 ,
1%
#9550
0%
#9560
b1101 ,
1%
#9570
0%
#9580
b1110 ,
1%
#9590
0%
#9600
b1111 ,
1%
#9610
0%
#9620
b10000 ,
1%
#9630
0%
#9640
b10001 ,
1%
#9650
0%
#9660
b10010 ,
1%
#9670
0%
#9680
b10011 ,
1%
#9690
0%
#9700
b10100 ,
1%
#9710
0%
#9720
1$
b1 ,
1%
#9730
0%
#9740
1*
b10 ,
1/
1%
#9750
0%
#9760
0*
b11 ,
10
1%
#9770
0%
#9780
b100 ,
1%
#9790
0%
#9800
b101 ,
1%
#9810
0%
#9820
b110 ,
1%
#9830
0%
#9840
b111 ,
1%
#9850
0%
#9860
b1000 ,
1%
#9870
0%
#9880
b1001 ,
1%
#9890
0%
#9900
b1010 ,
1%
#9910
0%
#9920
b1011 ,
1%
#9930
0%
#9940
b1100 ,
1%
#9950
0%
#9960
b1101 ,
1%
#9970
0%
#9980
b1110 ,
1%
#9990
0%
#10000
b1111 ,
1%
#10010
0%
#10020
b10000 ,
1%
#10030
0%
#10040
b10001 ,
1%
#10050
0%
#10060
b10010 ,
1%
#10070
0%
#10080
b10011 ,
1%
#10090
0%
#10100
b10100 ,
1%
#10110
0%
#10120
0$
b1 ,
1%
#10130
0%
#10140
1)
b10 ,
0/
1%
#10150
0%
#10160
0)
b11 1
b11 ,
00
1%
#10170
0%
#10180
b100 ,
1%
#10190
0%
#10200
b101 ,
1%
#10210
0%
#10220
b110 ,
1%
#10230
0%
#10240
b111 ,
1%
#10250
0%
#10260
b1000 ,
1%
#10270
0%
#10280
b1001 ,
1%
#10290
0%
#10300
b1010 ,
1%
#10310
0%
#10320
b1011 ,
1%
#10330
0%
#10340
b1100 ,
1%
#10350
0%
#10360
b1101 ,
1%
#10370
0%
#10380
b1110 ,
1%
#10390
0%
#10400
b1111 ,
1%
#10410
0%
#10420
b10000 ,
1%
#10430
0%
#10440
b10001 ,
1%
#10450
0%
#10460
b10010 ,
1%
#10470
0%
#10480
b10011 ,
1%
#10490
0%
#10500
b10100 ,
1%
#10510
0%
#10520
1$
b1 ,
1%
#10530
0%
#10540
1*
b10 ,
1/
1%
#10550
0%
#10560
0*
b11 ,
10
1%
#10570
0%
#10580
b100 ,
1%
#10590
0%
#10600
b101 ,
1%
#10610
0%
#10620
b110 ,
1%
#10630
0%
#10640
b111 ,
1%
#10650
0%
#10660
b1000 ,
1%
#10670
0%
#10680
b1001 ,
1%
#10690
0%
#10700
b1010 ,
1%
#10710
0%
#10720
b1011 ,
1%
#10730
0%
#10740
b1100 ,
1%
#10750
0%
#10760
b1101 ,
1%
#10770
0%
#10780
b1110 ,
1%
#10790
0%
#10800
b1111 ,
1%
#10810
0%
#10820
b10000 ,
1%
#10830
0%
#10840
b10001 ,
1%
#10850
0%
#10860
b10010 ,
1%
#10870
0%
#10880
b10011 ,
1%
#10890
0%
#10900
b10100 ,
1%
#10910
0%
#10920
0$
b1 ,
1%
#10930
0%
#10940
1)
b10 ,
0/
1%
#10950
0%
#10960
0)
b10 1
b11 ,
00
1%
#10970
0%
#10980
b100 ,
1%
#10990
0%
#11000
b101 ,
1%
#11010
0%
#11020
b110 ,
1%
#11030
0%
#11040
b111 ,
1%
#11050
0%
#11060
b1000 ,
1%
#11070
0%
#11080
b1001 ,
1%
#11090
0%
#11100
b1010 ,
1%
#11110
0%
#11120
b1011 ,
1%
#11130
0%
#11140
b1100 ,
1%
#11150
0%
#11160
b1101 ,
1%
#11170
0%
#11180
b1110 ,
1%
#11190
0%
#11200
b1111 ,
1%
#11210
0%
#11220
b10000 ,
1%
#11230
0%
#11240
b10001 ,
1%
#11250
0%
#11260
b10010 ,
1%
#11270
0%
#11280
b10011 ,
1%
#11290
0%
#11300
b10100 ,
1%
#11310
0%
#11320
1$
b1 ,
1%
#11330
0%
#11340
1*
b10 ,
1/
1%
#11350
0%
#11360
0*
b11 ,
10
1%
#11370
0%
#11380
b100 ,
1%
#11390
0%
#11400
b101 ,
1%
#11410
0%
#11420
b110 ,
1%
#11430
0%
#11440
b111 ,
1%
#11450
0%
#11460
b1000 ,
1%
#11470
0%
#11480
b1001 ,
1%
#11490
0%
#11500
b1010 ,
1%
#11510
0%
#11520
b1011 ,
1%
#11530
0%
#11540
b1100 ,
1%
#11550
0%
#11560
b1101 ,
1%
#11570
0%
#11580
b1110 ,
1%
#11590
0%
#11600
b1111 ,
1%
#11610
0%
#11620
b10000 ,
1%
#11630
0%
#11640
b10001 ,
1%
#11650
0%
#11660
b10010 ,
1%
#11670
0%
#11680
b10011 ,
1%
#11690
0%
#11700
b10100 ,
1%
#11710
0%
#11720
0$
b1 ,
1%
#11730
0%
#11740
1)
b10 ,
0/
1%
#11750
0%
#11760
0)
b1 1
b11 ,
00
1%
#11770
0%
#11780
b100 ,
1%
#11790
0%
