src/QUADRATUR_ENCODER/FULL/QUADRATUR_ENCODER.v
////////////////////////////////////////////////////////////////////////////////////////////
module QUADRATUR_ENCODER(
	input CLK,
	input A,
	input B,
	input LATCH,
	input RESET,
	output reg signed [31:0] COUNTER,
	output reg signed [31:0] SPEED,
	output reg CW,
	output reg CCW
	);
	//
	reg signed [31:0] counter_temp;
	reg signed [31:0] speed_temp;
	reg hri1; reg hri2; reg hri3; reg hri4; reg hri5; reg hri6;
	//
	wire a_;
	wire b_;
	wire a_re;
	wire a_fe;
	wire b_re;
	wire b_fe;
	wire latch_re;
	//
	localparam ENC_FILTER = 5'd10;
	ENC_INP_FILTER enc_inp_filter_a(CLK, A, a_); defparam enc_inp_filter_a.FILTER = ENC_FILTER;
	ENC_INP_FILTER enc_inp_filter_b(CLK, B, b_); defparam enc_inp_filter_b.FILTER = ENC_FILTER;	
	//
	assign a_re = (hri1 && !hri2);
	assign a_fe = (!hri1 && hri2);	
	assign b_re = (hri3 && !hri4);
	assign b_fe = (!hri3 && hri4);
	assign latch_re = (hri5 && !hri6);	
	//
	initial
	begin	
		CW <= 0;
		CCW <= 0;
		COUNTER <= 0;
		SPEED <= 0;
		//
		counter_temp <= 0;
		speed_temp <= 0;
		//
		hri1 <= 0; hri2 <= 0; hri3 <= 0; hri4 <= 0; hri5 <= 0; hri6 <= 0;
	end
	//
	always @(posedge CLK)
	begin
	// Impulsauswertung
	hri1 <= a_;
	hri2 <= hri1;	
	//
	hri3 <= b_;
	hri4 <= hri3;	
	//
	hri5 <= LATCH;
	hri6 <= hri5;	
	//
	if ((a_re && !b_) || (b_re && a_) || (a_fe && b_) || (b_fe && !a_))
		begin
		counter_temp <= counter_temp + 1;
		CW <= 1;
		CCW <= 0;
		end
	//
	else if ((a_re && b_) || (b_fe && a_) || (a_fe && !b_) || (b_re && !a_))
		begin
		counter_temp <= counter_temp - 1;
		CW <= 0;
		CCW <= 1;
		end
	//
	//if (latch_re)
	//	begin
		COUNTER <= counter_temp;
	//	end
	//
	// Drehzahlerfassung mit Betrachtung des Ueberlaufes +-2^31
	if (CW && (speed_temp < 2147483640))
		begin
		speed_temp <= speed_temp + 1;
		end
	//
	if (CCW && (speed_temp > -2147483640))
		begin
		speed_temp <= speed_temp - 1;
		end
	//
	if (a_re || (speed_temp <= -50000000) || (speed_temp >= 50000000))
		begin
		SPEED <= speed_temp;
		speed_temp <= 0;
		end
	//	
	if (RESET)
		begin
		counter_temp <= 0;
		COUNTER <= 0;
		speed_temp <= 0;
		SPEED <= 0;
		end
	end
endmodule
////////////////////////////////////////////////////////////////////////////////////////////
//	Digitales Filter
module	ENC_INP_FILTER (
	input CLK, 
	input IN,
	output reg OUT
	);
//
parameter FILTER = 5'd5;
//
reg [4:0] ctr0;
reg [4:0] ctr1;
//
initial
	begin
	OUT <= 0;
	ctr0 <= 0;
	ctr1 <= 0;
	end
always	@(posedge CLK)
begin
	if (IN && !OUT)
		begin
		ctr0 <= 0;
		ctr1 <= ctr1 + 1;
		end
	//	
	if (!IN && OUT)
		begin
		ctr0 <= ctr0 + 1;
		ctr1 <= 0;
		end	
	//
	if (ctr0 == FILTER)
		begin
		ctr0 <= 0;
		ctr1 <= 0;
		OUT <= 0;
		end
	//
	if (ctr1 == FILTER)
		begin
		ctr0 <= 0;
		ctr1 <= 0;
		OUT <= 1;
		end
	//	
	if (((ctr0 > 0) && IN) || ((ctr1 > 0) && !IN))
		begin
		ctr0 <= 0;
		ctr1 <= 0;
		end	
end
endmodule
////////////////////////////////////////////////////////////////////////////////////////////

src/QUADRATUR_ENCODER/FULL/ICARUS_TB.v
`include "QUADRATUR_ENCODER.v"

// http://verilogtutorial.blogspot.ch/2012/09/verilog-timescale-system-tasks.html
`timescale 10ns/1ns
//
module ICARUS_TB;
	integer file;
	reg clk;
	reg a;
	reg b; 
	reg latch;
	reg reset;
	wire signed [31:0] counter;
	wire signed [31:0] speed;	
	wire cw;
	wire ccw;
	//
	initial 
		begin
			clk <= 1;
			a <= 0;
			b <= 0;
			latch <= 0;
			reset <= 0;
			//
			$dumpfile("vcd\\\icarus_tb.vcd"); 
			$dumpvars(0, ICARUS_TB); 
			//
			#50 a <= 1;
			#50 b <= 1;
			#50 a <= 0;
			#50 b <= 0;
			#50 a <= 1;
			#50 b <= 1;
			#50 a <= 0;
			#50 b <= 0;
			//
			#25 latch <= 1;
			#25 latch <= 0;
			//
			#50 a <= 0;
			#50 b <= 1;
			#50 a <= 1;
			#50 b <= 0;
			#50 a <= 0;
			#50 b <= 1;
			#50 a <= 1;
			#50 b <= 0;
			//
			#25 latch <= 1;
			#25 latch <= 0;
			//
			#500 $finish; 
		end 
	//
	always #1 clk <= !clk;
	//
	QUADRATUR_ENCODER quadratur_encoder(clk,
										a,
										b,
										latch,
										reset,
										counter,
										speed,
										cw,
										ccw
										);
	//
endmodule
/*
cd D:\ABBTS\LABOR\FPGA\_PLC_ADC_DAC\QUARTUS\MAX10_DC_MOTOR\src\TOOLBOX\ENCODER
C:\iverilog\bin\iverilog -s ICARUS_TB -o icarus_tb.o ICARUS_TB.v
C:\iverilog\bin\vvp icarus_tb.o
*/

src/QUADRATUR_ENCODER/FULL/vcd/icarus_tb.vcd
$date
	Mon Mar 19 05:03:01 2018
$end
$version
	Icarus Verilog
$end
$timescale
	1ns
$end
$scope module ICARUS_TB $end
$var wire 32 ! speed [31:0] $end
$var wire 1 " cw $end
$var wire 32 # counter [31:0] $end
$var wire 1 $ ccw $end
$var reg 1 % a $end
$var reg 1 & b $end
$var reg 1 ' clk $end
$var reg 1 ( latch $end
$var reg 1 ) reset $end
$scope module quadratur_encoder $end
$var wire 1 % A $end
$var wire 1 & B $end
$var wire 1 ' CLK $end
$var wire 1 ( LATCH $end
$var wire 1 ) RESET $end
$var wire 1 * a_fe $end
$var wire 1 + a_re $end
$var wire 1 , b_fe $end
$var wire 1 - b_re $end
$var wire 1 . latch_re $end
$var wire 1 / b_ $end
$var wire 1 0 a_ $end
$var reg 1 $ CCW $end
$var reg 32 1 COUNTER [31:0] $end
$var reg 1 " CW $end
$var reg 32 2 SPEED [31:0] $end
$var reg 32 3 counter_temp [31:0] $end
$var reg 1 4 hri1 $end
$var reg 1 5 hri2 $end
$var reg 1 6 hri3 $end
$var reg 1 7 hri4 $end
$var reg 1 8 hri5 $end
$var reg 1 9 hri6 $end
$var reg 32 : speed_temp [31:0] $end
$scope module enc_inp_filter_a $end
$var wire 1 ' CLK $end
$var wire 1 % IN $end
$var reg 1 0 OUT $end
$var reg 5 ; ctr0 [4:0] $end
$var reg 5 < ctr1 [4:0] $end
$upscope $end
$scope module enc_inp_filter_b $end
$var wire 1 ' CLK $end
$var wire 1 & IN $end
$var reg 1 / OUT $end
$var reg 5 = ctr0 [4:0] $end
$var reg 5 > ctr1 [4:0] $end
$upscope $end
$upscope $end
$upscope $end
$enddefinitions $end
#0
$dumpvars
b0 >
b0 =
b0 <
b0 ;
b0 :
09
08
07
06
05
04
b0 3
b0 2
b0 1
00
0/
0.
0-
0,
0+
0*
0)
0(
1'
0&
0%
0$
b0 #
0"
b0 !
$end
#10
0'
#20
1'
#30
0'
#40
1'
#50
0'
#60
1'
#70
0'
#80
1'
#90
0'
#100
1'
#110
0'
#120
1'
#130
0'
#140
1'
#150
0'
#160
1'
#170
0'
#180
1'
#190
0'
#200
1'
#210
0'
#220
1'
#230
0'
#240
1'
#250
0'
#260
1'
#270
0'
#280
1'
#290
0'
#300
1'
#310
0'
#320
1'
#330
0'
#340
1'
#350
0'
#360
1'
#370
0'
#380
1'
#390
0'
#400
1'
#410
0'
#420
1'
#430
0'
#440
1'
#450
0'
#460
1'
#470
0'
#480
1'
#490
0'
#500
b1 <
1'
1%
#510
0'
#520
b10 <
1'
#530
0'
#540
b11 <
1'
#550
0'
#560
b100 <
1'
#570
0'
#580
b101 <
1'
#590
0'
#600
b110 <
1'
#610
0'
#620
b111 <
1'
#630
0'
#640
b1000 <
1'
#650
0'
#660
b1001 <
1'
#670
0'
#680
b1010 <
1'
#690
0'
#700
10
b0 <
1'
#710
0'
#720
1+
14
1'
#730
0'
#740
0+
1"
b1 3
15
1'
#750
0'
#760
b1 :
b1 #
b1 1
1'
#770
0'
#780
b10 :
1'
#790
0'
#800
b11 :
1'
#810
0'
#820
b100 :
1'
#830
0'
#840
b101 :
1'
#850
0'
#860
b110 :
1'
#870
0'
#880
b111 :
1'
#890
0'
#900
b1000 :
1'
#910
0'
#920
b1001 :
1'
#930
0'
#940
b1010 :
1'
#950
0'
#960
b1011 :
1'
#970
0'
#980
b1100 :
1'
#990
0'
#1000
b1 >
b1101 :
1'
1&
#1010
0'
#1020
b1110 :
b10 >
1'
#1030
0'
#1040
b11 >
b1111 :
1'
#1050
0'
#1060
b10000 :
b100 >
1'
#1070
0'
#1080
b101 >
b10001 :
1'
#1090
0'
#1100
b10010 :
b110 >
1'
#1110
0'
#1120
b111 >
b10011 :
1'
#1130
0'
#1140
b10100 :
b1000 >
1'
#1150
0'
#1160
b1001 >
b10101 :
1'
#1170
0'
#1180
b10110 :
b1010 >
1'
#1190
0'
#1200
1/
b0 >
b10111 :
1'
#1210
0'
#1220
1-
b11000 :
16
1'
#1230
0'
#1240
0-
b11001 :
b10 3
17
1'
#1250
0'
#1260
b11010 :
b10 #
b10 1
1'
#1270
0'
#1280
b11011 :
1'
#1290
0'
#1300
b11100 :
1'
#1310
0'
#1320
b11101 :
1'
#1330
0'
#1340
b11110 :
1'
#1350
0'
#1360
b11111 :
1'
#1370
0'
#1380
b100000 :
1'
#1390
0'
#1400
b100001 :
1'
#1410
0'
#1420
b100010 :
1'
#1430
0'
#1440
b100011 :
1'
#1450
0'
#1460
b100100 :
1'
#1470
0'
#1480
b100101 :
1'
#1490
0'
#1500
b100110 :
b1 ;
1'
0%
#1510
0'
#1520
b10 ;
b100111 :
1'
#1530
0'
#1540
b101000 :
b11 ;
1'
#1550
0'
#1560
b100 ;
b101001 :
1'
#1570
0'
#1580
b101010 :
b101 ;
1'
#1590
0'
#1600
b110 ;
b101011 :
1'
#1610
0'
#1620
b101100 :
b111 ;
1'
#1630
0'
#1640
b1000 ;
b101101 :
1'
#1650
0'
#1660
b101110 :
b1001 ;
1'
#1670
0'
#1680
b1010 ;
b101111 :
1'
#1690
0'
#1700
b110000 :
00
b0 ;
1'
#1710
0'
#1720
1*
b110001 :
04
1'
#1730
0'
#1740
0*
b110010 :
b11 3
05
1'
#1750
0'
#1760
b110011 :
b11 #
b11 1
1'
#1770
0'
#1780
b110100 :
1'
#1790
0'
#1800
b110101 :
1'
#1810
0'
#1820
b110110 :
1'
#1830
0'
#1840
b110111 :
1'
#1850
0'
#1860
b111000 :
1'
#1870
0'
#1880
b111001 :
1'
#1890
0'
#1900
b111010 :
1'
#1910
0'
#1920
b111011 :
1'
#1930
0'
#1940
b111100 :
1'
#1950
0'
#1960
b111101 :
1'
#1970
0'
#1980
b111110 :
1'
#1990
0'
#2000
b1 =
b111111 :
1'
0&
#2010
0'
#2020
b1000000 :
b10 =
1'
#2030
0'
#2040
b11 =
b1000001 :
1'
#2050
0'
#2060
b1000010 :
b100 =
1'
#2070
0'
#2080
b101 =
b1000011 :
1'
#2090
0'
#2100
b1000100 :
b110 =
1'
#2110
0'
#2120
b111 =
b1000101 :
1'
#2130
0'
#2140
b1000110 :
b1000 =
1'
#2150
0'
#2160
b1001 =
b1000111 :
1'
#2170
0'
#2180
b1001000 :
b1010 =
1'
#2190
0'
#2200
0/
b0 =
b1001001 :
1'
#2210
0'
#2220
1,
b1001010 :
06
1'
#2230
0'
#2240
0,
b1001011 :
b100 3
07
1'
#2250
0'
#2260
b1001100 :
b100 #
b100 1
1'
#2270
0'
#2280
b1001101 :
1'
#2290
0'
#2300
b1001110 :
1'
#2310
0'
#2320
b1001111 :
1'
#2330
0'
#2340
b1010000 :
1'
#2350
0'
#2360
b1010001 :
1'
#2370
0'
#2380
b1010010 :
1'
#2390
0'
#2400
b1010011 :
1'
#2410
0'
#2420
b1010100 :
1'
#2430
0'
#2440
b1010101 :
1'
#2450
0'
#2460
b1010110 :
1'
#2470
0'
#2480
b1010111 :
1'
#2490
0'
#2500
b1011000 :
b1 <
1'
1%
#2510
0'
#2520
b10 <
b1011001 :
1'
#2530
0'
#2540
b1011010 :
b11 <
1'
#2550
0'
#2560
b100 <
b1011011 :
1'
#2570
0'
#2580
b1011100 :
b101 <
1'
#2590
0'
#2600
b110 <
b1011101 :
1'
#2610
0'
#2620
b1011110 :
b111 <
1'
#2630
0'
#2640
b1000 <
b1011111 :
1'
#2650
0'
#2660
b1100000 :
b1001 <
1'
#2670
0'
#2680
b1010 <
b1100001 :
1'
#2690
0'
#2700
b1100010 :
10
b0 <
1'
#2710
0'
#2720
1+
b1100011 :
14
1'
#2730
0'
#2740
0+
b1100011 !
b1100011 2
b0 :
b101 3
15
1'
#2750
0'
#2760
b1 :
b101 #
b101 1
1'
#2770
0'
#2780
b10 :
1'
#2790
0'
#2800
b11 :
1'
#2810
0'
#2820
b100 :
1'
#2830
0'
#2840
b101 :
1'
#2850
0'
#2860
b110 :
1'
#2870
0'
#2880
b111 :
1'
#2890
0'
#2900
b1000 :
1'
#2910
0'
#2920
b1001 :
1'
#2930
0'
#2940
b1010 :
1'
#2950
0'
#2960
b1011 :
1'
#2970
0'
#2980
b1100 :
1'
#2990
0'
#3000
b1 >
b1101 :
1'
1&
#3010
0'
#3020
b1110 :
b10 >
1'
#3030
0'
#3040
b11 >
b1111 :
1'
#3050
0'
#3060
b10000 :
b100 >
1'
#3070
0'
#3080
b101 >
b10001 :
1'
#3090
0'
#3100
b10010 :
b110 >
1'
#3110
0'
#3120
b111 >
b10011 :
1'
#3130
0'
#3140
b10100 :
b1000 >
1'
#3150
0'
#3160
b1001 >
b10101 :
1'
#3170
0'
#3180
b10110 :
b1010 >
1'
#3190
0'
#3200
1/
b0 >
b10111 :
1'
#3210
0'
#3220
1-
b11000 :
16
1'
#3230
0'
#3240
0-
b11001 :
b110 3
17
1'
#3250
0'
#3260
b11010 :
b110 #
b110 1
1'
#3270
0'
#3280
b11011 :
1'
#3290
0'
#3300
b11100 :
1'
#3310
0'
#3320
b11101 :
1'
#3330
0'
#3340
b11110 :
1'
#3350
0'
#3360
b11111 :
1'
#3370
0'
#3380
b100000 :
1'
#3390
0'
#3400
b100001 :
1'
#3410
0'
#3420
b100010 :
1'
#3430
0'
#3440
b100011 :
1'
#3450
0'
#3460
b100100 :
1'
#3470
0'
#3480
b100101 :
1'
#3490
0'
#3500
b100110 :
b1 ;
1'
0%
#3510
0'
#3520
b10 ;
b100111 :
1'
#3530
0'
#3540
b101000 :
b11 ;
1'
#3550
0'
#3560
b100 ;
b101001 :
1'
#3570
0'
#3580
b101010 :
b101 ;
1'
#3590
0'
#3600
b110 ;
b101011 :
1'
#3610
0'
#3620
b101100 :
b111 ;
1'
#3630
0'
#3640
b1000 ;
b101101 :
1'
#3650
0'
#3660
b101110 :
b1001 ;
1'
#3670
0'
#3680
b1010 ;
b101111 :
1'
#3690
0'
#3700
b110000 :
00
b0 ;
1'
#3710
0'
#3720
1*
b110001 :
04
1'
#3730
0'
#3740
0*
b110010 :
b111 3
05
1'
#3750
0'
#3760
b110011 :
b111 #
b111 1
1'
#3770
0'
#3780
b110100 :
1'
#3790
0'
#3800
b110101 :
1'
#3810
0'
#3820
b110110 :
1'
#3830
0'
#3840
b110111 :
1'
#3850
0'
#3860
b111000 :
1'
#3870
0'
#3880
b111001 :
1'
#3890
0'
#3900
b111010 :
1'
#3910
0'
#3920
b111011 :
1'
#3930
0'
#3940
b111100 :
1'
#3950
0'
#3960
b111101 :
1'
#3970
0'
#3980
b111110 :
1'
#3990
0'
#4000
b1 =
b111111 :
1'
0&
#4010
0'
#4020
b1000000 :
b10 =
1'
#4030
0'
#4040
b11 =
b1000001 :
1'
#4050
0'
#4060
b1000010 :
b100 =
1'
#4070
0'
#4080
b101 =
b1000011 :
1'
#4090
0'
#4100
b1000100 :
b110 =
1'
#4110
0'
#4120
b111 =
b1000101 :
1'
#4130
0'
#4140
b1000110 :
b1000 =
1'
#4150
0'
#4160
b1001 =
b1000111 :
1'
#4170
0'
#4180
b1001000 :
b1010 =
1'
#4190
0'
#4200
0/
b0 =
b1001001 :
1'
#4210
0'
#4220
1,
b1001010 :
06
1'
#4230
0'
#4240
0,
b1001011 :
b1000 3
07
1'
#4250
0'
1(
#4260
1.
b1001100 :
b1000 #
b1000 1
18
1'
#4270
0'
#4280
0.
b1001101 :
19
1'
#4290
0'
#4300
b1001110 :
1'
#4310
0'
#4320
b1001111 :
1'
#4330
0'
#4340
b1010000 :
1'
#4350
0'
#4360
b1010001 :
1'
#4370
0'
#4380
b1010010 :
1'
#4390
0'
#4400
b1010011 :
1'
#4410
0'
#4420
b1010100 :
1'
#4430
0'
#4440
b1010101 :
1'
#4450
0'
#4460
b1010110 :
1'
#4470
0'
#4480
b1010111 :
1'
#4490
0'
#4500
b1011000 :
08
1'
0(
#4510
0'
#4520
b1011001 :
09
1'
#4530
0'
#4540
b1011010 :
1'
#4550
0'
#4560
b1011011 :
1'
#4570
0'
#4580
b1011100 :
1'
#4590
0'
#4600
b1011101 :
1'
#4610
0'
#4620
b1011110 :
1'
#4630
0'
#4640
b1011111 :
1'
#4650
0'
#4660
b1100000 :
1'
#4670
0'
#4680
b1100001 :
1'
#4690
0'
#4700
b1100010 :
1'
#4710
0'
#4720
b1100011 :
1'
#4730
0'
#4740
b1100100 :
1'
#4750
0'
#4760
b1100101 :
1'
#4770
0'
#4780
b1100110 :
1'
#4790
0'
#4800
b1100111 :
1'
#4810
0'
#4820
b1101000 :
1'
#4830
0'
#4840
b1101001 :
1'
#4850
0'
#4860
b1101010 :
1'
#4870
0'
#4880
b1101011 :
1'
#4890
0'
#4900
b1101100 :
1'
#4910
0'
#4920
b1101101 :
1'
#4930
0'
#4940
b1101110 :
1'
#4950
0'
#4960
b1101111 :
1'
#4970
0'
#4980
b1110000 :
1'
#4990
0'
#5000
b1110001 :
1'
#5010
0'
#5020
b1110010 :
1'
#5030
0'
#5040
b1110011 :
1'
#5050
0'
#5060
b1110100 :
1'
#5070
0'
#5080
b1110101 :
1'
#5090
0'
#5100
b1110110 :
1'
#5110
0'
#5120
b1110111 :
1'
#5130
0'
#5140
b1111000 :
1'
#5150
0'
#5160
b1111001 :
1'
#5170
0'
#5180
b1111010 :
1'
#5190
0'
#5200
b1111011 :
1'
#5210
0'
#5220
b1111100 :
1'
#5230
0'
#5240
b1111101 :
1'
#5250
0'
#5260
b1111110 :
1'
#5270
0'
#5280
b1111111 :
1'
#5290
0'
#5300
b10000000 :
1'
#5310
0'
#5320
b10000001 :
1'
#5330
0'
#5340
b10000010 :
1'
#5350
0'
#5360
b10000011 :
1'
#5370
0'
#5380
b10000100 :
1'
#5390
0'
#5400
b10000101 :
1'
#5410
0'
#5420
b10000110 :
1'
#5430
0'
#5440
b10000111 :
1'
#5450
0'
#5460
b10001000 :
1'
#5470
0'
#5480
b10001001 :
1'
#5490
0'
#5500
b10001010 :
b1 >
1'
1&
#5510
0'
#5520
b10 >
b10001011 :
1'
#5530
0'
#5540
b10001100 :
b11 >
1'
#5550
0'
#5560
b100 >
b10001101 :
1'
#5570
0'
#5580
b10001110 :
b101 >
1'
#5590
0'
#5600
b110 >
b10001111 :
1'
#5610
0'
#5620
b10010000 :
b111 >
1'
#5630
0'
#5640
b1000 >
b10010001 :
1'
#5650
0'
#5660
b10010010 :
b1001 >
1'
#5670
0'
#5680
b1010 >
b10010011 :
1'
#5690
0'
#5700
b10010100 :
1/
b0 >
1'
#5710
0'
#5720
1-
b10010101 :
16
1'
#5730
0'
#5740
0-
b10010110 :
1$
0"
b111 3
17
1'
#5750
0'
#5760
b10010101 :
b111 #
b111 1
1'
#5770
0'
#5780
b10010100 :
1'
#5790
0'
#5800
b10010011 :
1'
#5810
0'
#5820
b10010010 :
1'
#5830
0'
#5840
b10010001 :
1'
#5850
0'
#5860
b10010000 :
1'
#5870
0'
#5880
b10001111 :
1'
#5890
0'
#5900
b10001110 :
1'
#5910
0'
#5920
b10001101 :
1'
#5930
0'
#5940
b10001100 :
1'
#5950
0'
#5960
b10001011 :
1'
#5970
0'
#5980
b10001010 :
1'
#5990
0'
#6000
b1 <
b10001001 :
1'
1%
#6010
0'
#6020
b10001000 :
b10 <
1'
#6030
0'
#6040
b11 <
b10000111 :
1'
#6050
0'
#6060
b10000110 :
b100 <
1'
#6070
0'
#6080
b101 <
b10000101 :
1'
#6090
0'
#6100
b10000100 :
b110 <
1'
#6110
0'
#6120
b111 <
b10000011 :
1'
#6130
0'
#6140
b10000010 :
b1000 <
1'
#6150
0'
#6160
b1001 <
b10000001 :
1'
#6170
0'
#6180
b10000000 :
b1010 <
1'
#6190
0'
#6200
10
b0 <
b1111111 :
1'
#6210
0'
#6220
1+
b1111110 :
14
1'
#6230
0'
#6240
0+
b1111110 !
b1111110 2
b0 :
b110 3
15
1'
#6250
0'
#6260
b11111111111111111111111111111111 :
b110 #
b110 1
1'
#6270
0'
#6280
b11111111111111111111111111111110 :
1'
#6290
0'
#6300
b11111111111111111111111111111101 :
1'
#6310
0'
#6320
b11111111111111111111111111111100 :
1'
#6330
0'
#6340
b11111111111111111111111111111011 :
1'
#6350
0'
#6360
b11111111111111111111111111111010 :
1'
#6370
0'
#6380
b11111111111111111111111111111001 :
1'
#6390
0'
#6400
b11111111111111111111111111111000 :
1'
#6410
0'
#6420
b11111111111111111111111111110111 :
1'
#6430
0'
#6440
b11111111111111111111111111110110 :
1'
#6450
0'
#6460
b11111111111111111111111111110101 :
1'
#6470
0'
#6480
b11111111111111111111111111110100 :
1'
#6490
0'
#6500
b11111111111111111111111111110011 :
b1 =
1'
0&
#6510
0'
#6520
b10 =
b11111111111111111111111111110010 :
1'
#6530
0'
#6540
b11111111111111111111111111110001 :
b11 =
1'
#6550
0'
#6560
b100 =
b11111111111111111111111111110000 :
1'
#6570
0'
#6580
b11111111111111111111111111101111 :
b101 =
1'
#6590
0'
#6600
b110 =
b11111111111111111111111111101110 :
1'
#6610
0'
#6620
b11111111111111111111111111101101 :
b111 =
1'
#6630
0'
#6640
b1000 =
b11111111111111111111111111101100 :
1'
#6650
0'
#6660
b11111111111111111111111111101011 :
b1001 =
1'
#6670
0'
#6680
b1010 =
b11111111111111111111111111101010 :
1'
#6690
0'
#6700
b11111111111111111111111111101001 :
0/
b0 =
1'
#6710
0'
#6720
1,
b11111111111111111111111111101000 :
06
1'
#6730
0'
#6740
0,
b11111111111111111111111111100111 :
b101 3
07
1'
#6750
0'
#6760
b11111111111111111111111111100110 :
b101 #
b101 1
1'
#6770
0'
#6780
b11111111111111111111111111100101 :
1'
#6790
0'
#6800
b11111111111111111111111111100100 :
1'
#6810
0'
#6820
b11111111111111111111111111100011 :
1'
#6830
0'
#6840
b11111111111111111111111111100010 :
1'
#6850
0'
#6860
b11111111111111111111111111100001 :
1'
#6870
0'
#6880
b11111111111111111111111111100000 :
1'
#6890
0'
#6900
b11111111111111111111111111011111 :
1'
#6910
0'
#6920
b11111111111111111111111111011110 :
1'
#6930
0'
#6940
b11111111111111111111111111011101 :
1'
#6950
0'
#6960
b11111111111111111111111111011100 :
1'
#6970
0'
#6980
b11111111111111111111111111011011 :
1'
#6990
0'
#7000
b1 ;
b11111111111111111111111111011010 :
1'
0%
#7010
0'
#7020
b11111111111111111111111111011001 :
b10 ;
1'
#7030
0'
#7040
b11 ;
b11111111111111111111111111011000 :
1'
#7050
0'
#7060
b11111111111111111111111111010111 :
b100 ;
1'
#7070
0'
#7080
b101 ;
b11111111111111111111111111010110 :
1'
#7090
0'
#7100
b11111111111111111111111111010101 :
b110 ;
1'
#7110
0'
#7120
b111 ;
b11111111111111111111111111010100 :
1'
#7130
0'
#7140
b11111111111111111111111111010011 :
b1000 ;
1'
#7150
0'
#7160
b1001 ;
b11111111111111111111111111010010 :
1'
#7170
0'
#7180
b11111111111111111111111111010001 :
b1010 ;
1'
#7190
0'
#7200
00
b0 ;
b11111111111111111111111111010000 :
1'
#7210
0'
#7220
1*
b11111111111111111111111111001111 :
04
1'
#7230
0'
#7240
0*
b11111111111111111111111111001110 :
b100 3
05
1'
#7250
0'
#7260
b11111111111111111111111111001101 :
b100 #
b100 1
1'
#7270
0'
#7280
b11111111111111111111111111001100 :
1'
#7290
0'
#7300
b11111111111111111111111111001011 :
1'
#7310
0'
#7320
b11111111111111111111111111001010 :
1'
#7330
0'
#7340
b11111111111111111111111111001001 :
1'
#7350
0'
#7360
b11111111111111111111111111001000 :
1'
#7370
0'
#7380
b11111111111111111111111111000111 :
1'
#7390
0'
#7400
b11111111111111111111111111000110 :
1'
#7410
0'
#7420
b11111111111111111111111111000101 :
1'
#7430
0'
#7440
b11111111111111111111111111000100 :
1'
#7450
0'
#7460
b11111111111111111111111111000011 :
1'
#7470
0'
#7480
b11111111111111111111111111000010 :
1'
#7490
0'
#7500
b11111111111111111111111111000001 :
b1 >
1'
1&
#7510
0'
#7520
b10 >
b11111111111111111111111111000000 :
1'
#7530
0'
#7540
b11111111111111111111111110111111 :
b11 >
1'
#7550
0'
#7560
b100 >
b11111111111111111111111110111110 :
1'
#7570
0'
#7580
b11111111111111111111111110111101 :
b101 >
1'
#7590
0'
#7600
b110 >
b11111111111111111111111110111100 :
1'
#7610
0'
#7620
b11111111111111111111111110111011 :
b111 >
1'
#7630
0'
#7640
b1000 >
b11111111111111111111111110111010 :
1'
#7650
0'
#7660
b11111111111111111111111110111001 :
b1001 >
1'
#7670
0'
#7680
b1010 >
b11111111111111111111111110111000 :
1'
#7690
0'
#7700
b11111111111111111111111110110111 :
1/
b0 >
1'
#7710
0'
#7720
1-
b11111111111111111111111110110110 :
16
1'
#7730
0'
#7740
0-
b11111111111111111111111110110101 :
b11 3
17
1'
#7750
0'
#7760
b11111111111111111111111110110100 :
b11 #
b11 1
1'
#7770
0'
#7780
b11111111111111111111111110110011 :
1'
#7790
0'
#7800
b11111111111111111111111110110010 :
1'
#7810
0'
#7820
b11111111111111111111111110110001 :
1'
#7830
0'
#7840
b11111111111111111111111110110000 :
1'
#7850
0'
#7860
b11111111111111111111111110101111 :
1'
#7870
0'
#7880
b11111111111111111111111110101110 :
1'
#7890
0'
#7900
b11111111111111111111111110101101 :
1'
#7910
0'
#7920
b11111111111111111111111110101100 :
1'
#7930
0'
#7940
b11111111111111111111111110101011 :
1'
#7950
0'
#7960
b11111111111111111111111110101010 :
1'
#7970
0'
#7980
b11111111111111111111111110101001 :
1'
#7990
0'
#8000
b1 <
b11111111111111111111111110101000 :
1'
1%
#8010
0'
#8020
b11111111111111111111111110100111 :
b10 <
1'
#8030
0'
#8040
b11 <
b11111111111111111111111110100110 :
1'
#8050
0'
#8060
b11111111111111111111111110100101 :
b100 <
1'
#8070
0'
#8080
b101 <
b11111111111111111111111110100100 :
1'
#8090
0'
#8100
b11111111111111111111111110100011 :
b110 <
1'
#8110
0'
#8120
b111 <
b11111111111111111111111110100010 :
1'
#8130
0'
#8140
b11111111111111111111111110100001 :
b1000 <
1'
#8150
0'
#8160
b1001 <
b11111111111111111111111110100000 :
1'
#8170
0'
#8180
b11111111111111111111111110011111 :
b1010 <
1'
#8190
0'
#8200
10
b0 <
b11111111111111111111111110011110 :
1'
#8210
0'
#8220
1+
b11111111111111111111111110011101 :
14
1'
#8230
0'
#8240
0+
b11111111111111111111111110011101 !
b11111111111111111111111110011101 2
b0 :
b10 3
15
1'
#8250
0'
#8260
b11111111111111111111111111111111 :
b10 #
b10 1
1'
#8270
0'
#8280
b11111111111111111111111111111110 :
1'
#8290
0'
#8300
b11111111111111111111111111111101 :
1'
#8310
0'
#8320
b11111111111111111111111111111100 :
1'
#8330
0'
#8340
b11111111111111111111111111111011 :
1'
#8350
0'
#8360
b11111111111111111111111111111010 :
1'
#8370
0'
#8380
b11111111111111111111111111111001 :
1'
#8390
0'
#8400
b11111111111111111111111111111000 :
1'
#8410
0'
#8420
b11111111111111111111111111110111 :
1'
#8430
0'
#8440
b11111111111111111111111111110110 :
1'
#8450
0'
#8460
b11111111111111111111111111110101 :
1'
#8470
0'
#8480
b11111111111111111111111111110100 :
1'
#8490
0'
#8500
b11111111111111111111111111110011 :
b1 =
1'
0&
#8510
0'
#8520
b10 =
b11111111111111111111111111110010 :
1'
#8530
0'
#8540
b11111111111111111111111111110001 :
b11 =
1'
#8550
0'
#8560
b100 =
b11111111111111111111111111110000 :
1'
#8570
0'
#8580
b11111111111111111111111111101111 :
b101 =
1'
#8590
0'
#8600
b110 =
b11111111111111111111111111101110 :
1'
#8610
0'
#8620
b11111111111111111111111111101101 :
b111 =
1'
#8630
0'
#8640
b1000 =
b11111111111111111111111111101100 :
1'
#8650
0'
#8660
b11111111111111111111111111101011 :
b1001 =
1'
#8670
0'
#8680
b1010 =
b11111111111111111111111111101010 :
1'
#8690
0'
#8700
b11111111111111111111111111101001 :
0/
b0 =
1'
#8710
0'
#8720
1,
b11111111111111111111111111101000 :
06
1'
#8730
0'
#8740
0,
b11111111111111111111111111100111 :
b1 3
07
1'
#8750
0'
1(
#8760
1.
b11111111111111111111111111100110 :
b1 #
b1 1
18
1'
#8770
0'
#8780
0.
b11111111111111111111111111100101 :
19
1'
#8790
0'
#8800
b11111111111111111111111111100100 :
1'
#8810
0'
#8820
b11111111111111111111111111100011 :
1'
#8830
0'
#8840
b11111111111111111111111111100010 :
1'
#8850
0'
#8860
b11111111111111111111111111100001 :
1'
#8870
0'
#8880
b11111111111111111111111111100000 :
1'
#8890
0'
#8900
b11111111111111111111111111011111 :
1'
#8910
0'
#8920
b11111111111111111111111111011110 :
1'
#8930
0'
