src/QUADRATUR_ENCODER/SIMPLE/QUADRATUR_ENCODER_SIMPLE.v
module QUADRATUR_ENCODER_SIMPLE(
	input CLK,
	input A,
	input B,
	input RESET,
	output reg signed [31:0] COUNTER,
	output reg CW,
	output reg CCW
	);
	//
	reg hri1; reg hri2; reg hri3; reg hri4;
	//
	wire Are;
	wire Afe;
	wire Bre;
	wire Bfe;	
	//
	//
	assign Are = (hri1 && !hri2);
	assign Afe = (!hri1 && hri2);	
	assign Bre = (hri3 && !hri4);
	assign Bfe = (!hri3 && hri4);
	//
	initial
	begin	
		CW <= 0;
		CCW <= 0;
		COUNTER <= 0;
		//
		hri1 <= 0; hri2 <= 0; hri3 <= 0; hri4 <= 0;
	end
	//
	always @(posedge CLK)
	begin
	// Impulsauswertung
	hri1 <= A;
	hri2 <= hri1;	
	//
	hri3 <= B;
	hri4 <= hri3;		
	//
	if ((Are && !B) || (Bre && A) || (Afe && B) || (Bfe && !A))
		begin
		COUNTER <= COUNTER + 1;
		CW <= 1;
		CCW <= 0;
		end
	//
	else if ((Are && B) || (Bfe && A) || (Afe && !B) || (Bre && !A))
		begin
		COUNTER <= COUNTER - 1;
		CW <= 0;
		CCW <= 1;
		end
	//	
	if (RESET)
		begin
		COUNTER <= 0;
		end
	end
endmodule

src/QUADRATUR_ENCODER/SIMPLE/ICARUS_TB.v
`include "QUADRATUR_ENCODER_SIMPLE.v"

// http://verilogtutorial.blogspot.ch/2012/09/verilog-timescale-system-tasks.html
`timescale 10ns/1ns
//
module ICARUS_TB;
	integer file;
	reg clk;
	reg a;
	reg b; 
	reg reset;
	wire signed [31:0] counter;
	wire cw;
	wire ccw;
	//
	initial 
		begin
			clk <= 1;
			a <= 0;
			b <= 0;
			reset <= 0;
			//
			$dumpfile("vcd\\\icarus_tb.vcd"); 
			$dumpvars(0, ICARUS_TB); 
			//
			#50 a <= 1;
			#50 b <= 1;
			#50 a <= 0;
			#50 b <= 0;
			#50 a <= 1;
			#50 b <= 1;
			#50 a <= 0;
			#50 b <= 0;
			//
			#50 a <= 0;
			#50 b <= 1;
			#50 a <= 1;
			#50 b <= 0;
			#50 a <= 0;
			#50 b <= 1;
			#50 a <= 1;
			#50 b <= 0;
			//
			#500 $finish; 
		end 
	//
	always #1 clk <= !clk;
	//
	QUADRATUR_ENCODER_SIMPLE quadratur_encodersimple(clk,
										a,
										b,
										reset,
										counter,
										cw,
										ccw
										);
	//
endmodule
/*
cd D:\ABBTS\LABOR\FPGA\_PLC_ADC_DAC\QUARTUS\MAX10_DC_MOTOR\src\TOOLBOX\ENCODER
C:\iverilog\bin\iverilog -s ICARUS_TB -o icarus_tb.o ICARUS_TB.v
C:\iverilog\bin\vvp icarus_tb.o
*/

src/QUADRATUR_ENCODER/SIMPLE/vcd/icarus_tb.vcd
$date
	Tue Jun 12 16:12:31 2018
$end
$version
	Icarus Verilog
$end
$timescale
	1ns
$end
$scope module ICARUS_TB $end
$var wire 1 ! cw $end
$var wire 32 " counter [31:0] $end
$var wire 1 # ccw $end
$var reg 1 $ a $end
$var reg 1 % b $end
$var reg 1 & clk $end
$var reg 1 ' reset $end
$scope module quadratur_encodersimple $end
$var wire 1 $ A $end
$var wire 1 ( Afe $end
$var wire 1 ) Are $end
$var wire 1 % B $end
$var wire 1 * Bfe $end
$var wire 1 + Bre $end
$var wire 1 & CLK $end
$var wire 1 ' RESET $end
$var reg 1 # CCW $end
$var reg 32 , COUNTER [31:0] $end
$var reg 1 ! CW $end
$var reg 1 - hri1 $end
$var reg 1 . hri2 $end
$var reg 1 / hri3 $end
$var reg 1 0 hri4 $end
$upscope $end
$upscope $end
$enddefinitions $end
#0
$dumpvars
00
0/
0.
0-
b0 ,
0+
0*
0)
0(
0'
1&
0%
0$
0#
b0 "
0!
$end
#10
0&
#20
1&
#30
0&
#40
1&
#50
0&
#60
1&
#70
0&
#80
1&
#90
0&
#100
1&
#110
0&
#120
1&
#130
0&
#140
1&
#150
0&
#160
1&
#170
0&
#180
1&
#190
0&
#200
1&
#210
0&
#220
1&
#230
0&
#240
1&
#250
0&
#260
1&
#270
0&
#280
1&
#290
0&
#300
1&
#310
0&
#320
1&
#330
0&
#340
1&
#350
0&
#360
1&
#370
0&
#380
1&
#390
0&
#400
1&
#410
0&
#420
1&
#430
0&
#440
1&
#450
0&
#460
1&
#470
0&
#480
1&
#490
0&
#500
1)
1-
1&
1$
#510
0&
#520
0)
1!
b1 "
b1 ,
1.
1&
#530
0&
#540
1&
#550
0&
#560
1&
#570
0&
#580
1&
#590
0&
#600
1&
#610
0&
#620
1&
#630
0&
#640
1&
#650
0&
#660
1&
#670
0&
#680
1&
#690
0&
#700
1&
#710
0&
#720
1&
#730
0&
#740
1&
#750
0&
#760
1&
#770
0&
#780
1&
#790
0&
#800
1&
#810
0&
#820
1&
#830
0&
#840
1&
#850
0&
#860
1&
#870
0&
#880
1&
#890
0&
#900
1&
#910
0&
#920
1&
#930
0&
#940
1&
#950
0&
#960
1&
#970
0&
#980
1&
#990
0&
#1000
1+
1/
1&
1%
#1010
0&
#1020
0+
b10 "
b10 ,
10
1&
#1030
0&
#1040
1&
#1050
0&
#1060
1&
#1070
0&
#1080
1&
#1090
0&
#1100
1&
#1110
0&
#1120
1&
#1130
0&
#1140
1&
#1150
0&
#1160
1&
#1170
0&
#1180
1&
#1190
0&
#1200
1&
#1210
0&
#1220
1&
#1230
0&
#1240
1&
#1250
0&
#1260
1&
#1270
0&
#1280
1&
#1290
0&
#1300
1&
#1310
0&
#1320
1&
#1330
0&
#1340
1&
#1350
0&
#1360
1&
#1370
0&
#1380
1&
#1390
0&
#1400
1&
#1410
0&
#1420
1&
#1430
0&
#1440
1&
#1450
0&
#1460
1&
#1470
0&
#1480
1&
#1490
0&
#1500
1(
0-
1&
0$
#1510
0&
#1520
0(
b11 "
b11 ,
0.
1&
#1530
0&
#1540
1&
#1550
0&
#1560
1&
#1570
0&
#1580
1&
#1590
0&
#1600
1&
#1610
0&
#1620
1&
#1630
0&
#1640
1&
#1650
0&
#1660
1&
#1670
0&
#1680
1&
#1690
0&
#1700
1&
#1710
0&
#1720
1&
#1730
0&
#1740
1&
#1750
0&
#1760
1&
#1770
0&
#1780
1&
#1790
0&
#1800
1&
#1810
0&
#1820
1&
#1830
0&
#1840
1&
#1850
0&
#1860
1&
#1870
0&
#1880
1&
#1890
0&
#1900
1&
#1910
0&
#1920
1&
#1930
0&
#1940
1&
#1950
0&
#1960
1&
#1970
0&
#1980
1&
#1990
0&
#2000
1*
0/
1&
0%
#2010
0&
#2020
0*
b100 "
b100 ,
00
1&
