src/BASIS/VERILOG/DIVERS/MODUL/MODULDEMO.v
module MODULDEMO(
	input CLK,
	input IN_1BIT,
	input [7:0] IN_8BIT,
	output OUT_1BIT_WIRE,
	output reg OUT_1BIT_REG,
	output reg [7:0] OUT_8BIT_REG);
	//	
	parameter VALUE_STATE_1 = 8'h11;
	//
	reg state;
	//
	assign OUT_1BIT_WIRE = IN_1BIT || OUT_8BIT_REG[0];
	//
	initial
	begin
		OUT_1BIT_REG <= 0;
		OUT_8BIT_REG <= 0;
		state <= 0;
	end
	//
	always @(posedge CLK)
	begin
	//
	state <= !state;
	//
	OUT_1BIT_REG <= IN_1BIT;
	//
	if (state == 0) 
		begin
		OUT_8BIT_REG <= VALUE_STATE_1;
		end
	//
	if (state == 1) 
		begin
		OUT_8BIT_REG <= IN_8BIT;
		end
	//
	end
endmodule

src/BASIS/VERILOG/DIVERS/MODUL/ICARUS_TB.v
`include "MODULDEMO.v"
// http://verilogtutorial.blogspot.ch/2012/09/verilog-timescale-system-tasks.html
`timescale 10ns/1ns
//
module ICARUS_TB;
	integer file;
	reg clk;
	reg in_1bit;
	reg [7:0] in_8bit;
	wire out_1bit_wire;
	wire out_1bit_reg;
	wire [7:0] out_8bit_reg;
	//
	initial 
		begin
		clk <= 1;
		in_1bit <= 0;
		in_8bit <= 0;
		//		
		$dumpfile("vcd\\\icarus_tb.vcd"); 
		$dumpvars(0, ICARUS_TB); 		
		//
		#3 begin
		   in_1bit <= 1;
		   in_8bit <= 8'hAA;
		   end
		//
		#4 begin
		   in_1bit <= 0;
		   in_8bit <= 8'hCC;
		   end
		//
		#4 in_8bit <= 8'hEE;
		//
		#10 $finish; 
		end 
	//
	always #1 clk <= !clk;// 50MHz
	//
	MODULDEMO moduldemo(clk, 
	                    in_1bit,
						in_8bit,
						out_1bit_wire,
						out_1bit_reg,
						out_8bit_reg);
	defparam moduldemo.VALUE_STATE_1 = 8'hFF;
	//
endmodule


/*
cd D:\Dropbox\ABBTS_LABOR_DOZ\MOTION_CONTROL\FPGA_MODUL_MAX1000_DIT_RET_UR\FPGA_MODUL_MAX1000_DIT_RET_UR_00_02\src\BASIS\VERILOG\GLUE_LOGIC
C:\iverilog\bin\iverilog -s ICARUS_TB -o icarus_tb.o ICARUS_TB.v
C:\iverilog\bin\vvp icarus_tb.o
*/

src/BASIS/VERILOG/DIVERS/MODUL/vcd/icarus_tb.vcd
$date
	Wed May 23 11:40:41 2018
$end
$version
	Icarus Verilog
$end
$timescale
	1ns
$end
$scope module ICARUS_TB $end
$var wire 8 ! out_8bit_reg [7:0] $end
$var wire 1 " out_1bit_wire $end
$var wire 1 # out_1bit_reg $end
$var reg 1 $ clk $end
$var reg 1 % in_1bit $end
$var reg 8 & in_8bit [7:0] $end
$scope module moduldemo $end
$var wire 1 $ CLK $end
$var wire 1 % IN_1BIT $end
$var wire 8 ' IN_8BIT [7:0] $end
$var wire 1 " OUT_1BIT_WIRE $end
$var reg 1 # OUT_1BIT_REG $end
$var reg 8 ( OUT_8BIT_REG [7:0] $end
$var reg 1 ) state $end
$upscope $end
$upscope $end
$enddefinitions $end
#0
$dumpvars
1)
b11111111 (
b0 '
b0 &
0%
1$
0#
1"
b11111111 !
$end
#10
0$
#20
0"
b0 !
b0 (
0)
1$
#30
1"
0$
b10101010 &
b10101010 '
1%
#40
b11111111 !
b11111111 (
1#
1)
1$
#50
0$
#60
b10101010 !
b10101010 (
0)
1$
#70
0"
0$
b11001100 &
b11001100 '
0%
#80
1"
b11111111 !
b11111111 (
0#
1)
1$
#90
0$
#100
0"
b11001100 !
b11001100 (
0)
1$
#110
0$
b11101110 &
b11101110 '
#120
1"
b11111111 !
b11111111 (
1)
1$
#130
0$
#140
0"
b11101110 !
b11101110 (
0)
1$
#150
0$
#160
1"
b11111111 !
b11111111 (
1)
1$
#170
0$
#180
0"
b11101110 !
b11101110 (
0)
1$
#190
0$
#200
1"
b11111111 !
b11111111 (
1)
1$
