src/BASIS/VERILOG/DIVERS/FLANKENTRIGGER/FLANKENTRIGGER.v
module FLANKENTRIGGER(
	input CLK,
	input SIGNAL,
	output RE,
	output FE,
	output reg [7:0] COUNTER);
	//	
	reg hri1; 
	reg hri2;
	//
	assign RE = (hri1 && !hri2);
	assign FE = (!hri1 && hri2);
	//
	initial
	begin
		COUNTER <= 0;
		hri1 <= 0; 
		hri2 <= 0;
	end
	//
	always @(posedge CLK)
	begin
	//
	hri1 <= SIGNAL;
	hri2 <= hri1;	
	//
	if (RE) 
		begin
		COUNTER <= COUNTER + 1;
		end
	//
	end
endmodule

src/BASIS/VERILOG/DIVERS/FLANKENTRIGGER/ICARUS_TB.v
`include "FLANKENTRIGGER.v"
// http://verilogtutorial.blogspot.ch/2012/09/verilog-timescale-system-tasks.html
`timescale 10ns/1ns
//
module ICARUS_TB;
	integer file;
	reg clk;
	reg clk_1MHz;
	reg signal;
	wire re;
	wire fe;
	wire [7:0] counter;
	//
	initial 
		begin
		clk <= 1;
		signal <= 0;
		//		
		$dumpfile("vcd\\\icarus_tb.vcd"); 
		$dumpvars(0, ICARUS_TB); 		
		//
		#10 signal <= 1;
		#10 signal <= 0;
		#10 signal <= 1;
		#10 signal <= 0;
		//
		#10 $finish; 
		end 
	//
	always #1 clk <= !clk;// 50MHz
	//
	FLANKENTRIGGER flankentrigger(clk, signal, re, fe, counter);					
	//
endmodule


/*
cd D:\Dropbox\ABBTS_LABOR_DOZ\MOTION_CONTROL\FPGA_MODUL_MAX1000_DIT_RET_UR\FPGA_MODUL_MAX1000_DIT_RET_UR_00_02\src\BASIS\VERILOG\GLUE_LOGIC
C:\iverilog\bin\iverilog -s ICARUS_TB -o icarus_tb.o ICARUS_TB.v
C:\iverilog\bin\vvp icarus_tb.o
*/

src/BASIS/VERILOG/DIVERS/FLANKENTRIGGER/vcd/icarus_tb.vcd
$date
	Wed May 23 07:28:53 2018
$end
$version
	Icarus Verilog
$end
$timescale
	1ns
$end
$scope module ICARUS_TB $end
$var wire 1 ! re $end
$var wire 1 " fe $end
$var wire 8 # counter [7:0] $end
$var reg 1 $ clk $end
$var reg 1 % signal $end
$scope module flankentrigger $end
$var wire 1 $ CLK $end
$var wire 1 " FE $end
$var wire 1 ! RE $end
$var wire 1 % SIGNAL $end
$var reg 8 & COUNTER [7:0] $end
$var reg 1 ' hri1 $end
$var reg 1 ( hri2 $end
$upscope $end
$upscope $end
$enddefinitions $end
#0
$dumpvars
0(
0'
b0 &
0%
1$
b0 #
0"
0!
$end
#10
0$
#20
1$
#30
0$
#40
1$
#50
0$
#60
1$
#70
0$
#80
1$
#90
0$
#100
1!
1'
1$
1%
#110
0$
#120
0!
b1 #
b1 &
1(
1$
#130
0$
#140
1$
#150
0$
#160
1$
#170
0$
#180
1$
#190
0$
#200
1"
0'
1$
0%
#210
0$
#220
0"
0(
1$
#230
0$
#240
1$
#250
0$
#260
1$
#270
0$
#280
1$
#290
0$
#300
1!
1'
1$
1%
#310
0$
#320
0!
b10 #
b10 &
1(
1$
#330
0$
#340
1$
#350
0$
#360
1$
#370
0$
#380
1$
#390
0$
#400
1"
0'
1$
0%
#410
0$
#420
0"
0(
1$
