src/ADC_DAC/ADC_MCP3201/ADC_MCP3201.v
module ADC_MCP3201 (
	input CLK,
	input LATCH,
	input SDI_ADC,
	output reg CS_ADC,
	output reg CLK_ADC,
	output reg [11:0] VALUE
	);
	//
	reg [15:0] ctr_clk_spi;
	reg [11:0] index;
	reg [11:0] value_temp;
	reg [4:0] state;
	reg [11:0] ctr_clk_cs;// Testvariable
	//
	reg hri1; reg hri2; reg hri3; reg hri4;
	wire latch_start;
	wire clk_adc_re;
	wire clk_adc_fe;	
	//
	assign	latch_start = (hri1 && !hri2);
	assign	clk_adc_re = (hri3 && !hri4);
	assign	clk_adc_fe = (!hri3 && hri4);
	//	
	initial
	begin
		
		CS_ADC <= 1;
		CLK_ADC <= 0;
		VALUE <= 0;
		index <= 15;
		value_temp <= 0;
		state <= 0;
		ctr_clk_spi <= 1;
		ctr_clk_cs <= 1;
		//
		hri1 <= 0; hri2 <= 0; hri3 <= 0; hri4 <= 0;
	end	
	//
	always	@(posedge CLK)
	begin
	// Impulsauswertung
	hri1 <= LATCH;
	hri2 <= hri1;
	hri3 <= CLK_ADC;
	hri4 <= hri3;
	// Testroutine
	if (CS_ADC == 0) ctr_clk_cs <= ctr_clk_cs + 1;
	else ctr_clk_cs <= 1;
	
	//
	if (state == 0) 
		begin
		CS_ADC <= 1;
		index <= 15;
		value_temp <= 0;
		ctr_clk_spi <= 1;
		//
		if(latch_start) 
			begin
			CS_ADC <= 0;
			state <= 1;
			end
		//
		end
	//
	if (state == 1) 
		begin
		ctr_clk_spi <= ctr_clk_spi + 1;
		if (ctr_clk_spi == 25) 
			begin
			ctr_clk_spi <= 1;
			CLK_ADC <= !CLK_ADC;
			end
		//
		if (clk_adc_re)
			begin
			value_temp[index - 1] <= SDI_ADC;
			end
		//
		if (clk_adc_fe) index <= index - 1;
		//
		if (index == 0) state <= 2;
		end

	if (state == 2) 
		begin
		VALUE <= value_temp[11:0];
		state <= 0;
		end
	end
endmodule

src/ADC_DAC/ADC_MCP3201/ICARUS_TB.v
`include "ADC_MCP3201.v"
// http://verilogtutorial.blogspot.ch/2012/09/verilog-timescale-system-tasks.html
`timescale 10ns/1ns
//
module ICARUS_TB;
	//
	integer file;
	reg clk;
	reg latch;
	reg sdi_adc;
	wire cs_adc;
	wire clk_adc;
	wire [11:0] value;
	//
	initial 
	begin
		clk <= 1;
		latch <= 0;
		sdi_adc <= 0;
		//
		$dumpfile("vcd\\\icarus_tb.vcd"); 
		$dumpvars(0, ICARUS_TB); 
		//
		#50   latch <= 1;
		#50   latch <= 0;
		#152  latch <= 0;
		//
		#100  sdi_adc <= 0;// B11
		#100  sdi_adc <= 0;// B10
		#100  sdi_adc <= 0;// B9
		#100  sdi_adc <= 0;// B8
		#100  sdi_adc <= 1;// B7
		#100  sdi_adc <= 0;// B6
		#100  sdi_adc <= 0;// B5
		#100  sdi_adc <= 0;// B4
		#100  sdi_adc <= 0;// B3
		#100  sdi_adc <= 0;// B2
		#100  sdi_adc <= 0;// B1
		#100  sdi_adc <= 1;// B0
		//
		#100  sdi_adc <= 0;// HI-Z
		//
		#200 $finish; 
	end 
	//
	always #1 clk <= !clk;// 50MHz
	//
	ADC_MCP3201 adc_mcp3201(
					clk,
	                latch,
			        sdi_adc,
			        cs_adc,
			        clk_adc,
			        value
					);
	//
endmodule
//
/*
cd D:\Dropbox\ABBTS_LABOR_DOZ\MOTION_CONTROL\FPGA_MODUL_MAX1000_DIT_RET_UR\FPGA_MODUL_MAX1000_DIT_RET_UR_00_02\src\ADC_DAC\ADC_MCP3201
C:\iverilog\bin\iverilog -s ICARUS_TB -o icarus_tb.o ICARUS_TB.v
C:\iverilog\bin\vvp icarus_tb.o
*/

src/ADC_DAC/ADC_MCP3201/vcd/icarus_tb.vcd
$date
	Sun May 13 14:03:16 2018
$end
$version
	Icarus Verilog
$end
$timescale
	1ns
$end
$scope module ICARUS_TB $end
$var wire 12 ! value [11:0] $end
$var wire 1 " cs_adc $end
$var wire 1 # clk_adc $end
$var reg 1 $ clk $end
$var reg 1 % latch $end
$var reg 1 & sdi_adc $end
$scope module adc_mcp3201 $end
$var wire 1 $ CLK $end
$var wire 1 % LATCH $end
$var wire 1 & SDI_ADC $end
$var wire 1 ' clk_adc_fe $end
$var wire 1 ( clk_adc_re $end
$var wire 1 ) latch_start $end
$var reg 1 # CLK_ADC $end
$var reg 1 " CS_ADC $end
$var reg 12 * VALUE [11:0] $end
$var reg 12 + ctr_clk_cs [11:0] $end
$var reg 16 , ctr_clk_spi [15:0] $end
$var reg 1 - hri1 $end
$var reg 1 . hri2 $end
$var reg 1 / hri3 $end
$var reg 1 0 hri4 $end
$var reg 12 1 index [11:0] $end
$var reg 5 2 state [4:0] $end
$var reg 12 3 value_temp [11:0] $end
$upscope $end
$upscope $end
$enddefinitions $end
#0
$dumpvars
b0 3
b0 2
b1111 1
00
0/
0.
0-
b1 ,
b1 +
b0 *
0)
0(
0'
0&
0%
1$
0#
1"
b0 !
$end
#10
0$
#20
1$
#30
0$
#40
1$
#50
0$
#60
1$
#70
0$
#80
1$
#90
0$
#100
1$
#110
0$
#120
1$
#130
0$
#140
1$
#150
0$
#160
1$
#170
0$
#180
1$
#190
0$
#200
1$
#210
0$
#220
1$
#230
0$
#240
1$
#250
0$
#260
1$
#270
0$
#280
1$
#290
0$
#300
1$
#310
0$
#320
1$
#330
0$
#340
1$
#350
0$
#360
1$
#370
0$
#380
1$
#390
0$
#400
1$
#410
0$
#420
1$
#430
0$
#440
1$
#450
0$
#460
1$
#470
0$
#480
1$
#490
0$
#500
1)
1-
1$
1%
#510
0$
#520
0)
b1 2
0"
1.
1$
#530
0$
#540
b10 ,
b10 +
1$
#550
0$
#560
b11 ,
b11 +
1$
#570
0$
#580
b100 ,
b100 +
1$
#590
0$
#600
b101 ,
b101 +
1$
#610
0$
#620
b110 ,
b110 +
1$
#630
0$
#640
b111 ,
b111 +
1$
#650
0$
#660
b1000 ,
b1000 +
1$
#670
0$
#680
b1001 ,
b1001 +
1$
#690
0$
#700
b1010 ,
b1010 +
1$
#710
0$
#720
b1011 ,
b1011 +
1$
#730
0$
#740
b1100 ,
b1100 +
1$
#750
0$
#760
b1101 ,
b1101 +
1$
#770
0$
#780
b1110 ,
b1110 +
1$
#790
0$
#800
b1111 ,
b1111 +
1$
#810
0$
#820
b10000 ,
b10000 +
1$
#830
0$
#840
b10001 ,
b10001 +
1$
#850
0$
#860
b10010 ,
b10010 +
1$
#870
0$
#880
b10011 ,
b10011 +
1$
#890
0$
#900
b10100 ,
b10100 +
1$
#910
0$
#920
b10101 ,
b10101 +
1$
#930
0$
#940
b10110 ,
b10110 +
1$
#950
0$
#960
b10111 ,
b10111 +
1$
#970
0$
#980
b11000 ,
b11000 +
1$
#990
0$
#1000
b11001 ,
b11001 +
0-
1$
0%
#1010
0$
#1020
1#
b1 ,
b11010 +
0.
1$
#1030
0$
#1040
1(
b10 ,
b11011 +
1/
1$
#1050
0$
#1060
0(
b11 ,
b11100 +
10
1$
#1070
0$
#1080
b100 ,
b11101 +
1$
#1090
0$
#1100
b101 ,
b11110 +
1$
#1110
0$
#1120
b110 ,
b11111 +
1$
#1130
0$
#1140
b111 ,
b100000 +
1$
#1150
0$
#1160
b1000 ,
b100001 +
1$
#1170
0$
#1180
b1001 ,
b100010 +
1$
#1190
0$
#1200
b1010 ,
b100011 +
1$
#1210
0$
#1220
b1011 ,
b100100 +
1$
#1230
0$
#1240
b1100 ,
b100101 +
1$
#1250
0$
#1260
b1101 ,
b100110 +
1$
#1270
0$
#1280
b1110 ,
b100111 +
1$
#1290
0$
#1300
b1111 ,
b101000 +
1$
#1310
0$
#1320
b10000 ,
b101001 +
1$
#1330
0$
#1340
b10001 ,
b101010 +
1$
#1350
0$
#1360
b10010 ,
b101011 +
1$
#1370
0$
#1380
b10011 ,
b101100 +
1$
#1390
0$
#1400
b10100 ,
b101101 +
1$
#1410
0$
#1420
b10101 ,
b101110 +
1$
#1430
0$
#1440
b10110 ,
b101111 +
1$
#1450
0$
#1460
b10111 ,
b110000 +
1$
#1470
0$
#1480
b11000 ,
b110001 +
1$
#1490
0$
#1500
b11001 ,
b110010 +
1$
#1510
0$
#1520
0#
b1 ,
b110011 +
1$
#1530
0$
#1540
1'
b10 ,
b110100 +
0/
1$
#1550
0$
#1560
0'
b1110 1
b11 ,
b110101 +
00
1$
#1570
0$
#1580
b100 ,
b110110 +
1$
#1590
0$
#1600
b101 ,
b110111 +
1$
#1610
0$
#1620
b110 ,
b111000 +
1$
#1630
0$
#1640
b111 ,
b111001 +
1$
#1650
0$
#1660
b1000 ,
b111010 +
1$
#1670
0$
#1680
b1001 ,
b111011 +
1$
#1690
0$
#1700
b1010 ,
b111100 +
1$
#1710
0$
#1720
b1011 ,
b111101 +
1$
#1730
0$
#1740
b1100 ,
b111110 +
1$
#1750
0$
#1760
b1101 ,
b111111 +
1$
#1770
0$
#1780
b1110 ,
b1000000 +
1$
#1790
0$
#1800
b1111 ,
b1000001 +
1$
#1810
0$
#1820
b10000 ,
b1000010 +
1$
#1830
0$
#1840
b10001 ,
b1000011 +
1$
#1850
0$
#1860
b10010 ,
b1000100 +
1$
#1870
0$
#1880
b10011 ,
b1000101 +
1$
#1890
0$
#1900
b10100 ,
b1000110 +
1$
#1910
0$
#1920
b10101 ,
b1000111 +
1$
#1930
0$
#1940
b10110 ,
b1001000 +
1$
#1950
0$
#1960
b10111 ,
b1001001 +
1$
#1970
0$
#1980
b11000 ,
b1001010 +
1$
#1990
0$
#2000
b11001 ,
b1001011 +
1$
#2010
0$
#2020
1#
b1 ,
b1001100 +
1$
#2030
0$
#2040
1(
b10 ,
b1001101 +
1/
1$
#2050
0$
#2060
0(
b11 ,
b1001110 +
10
1$
#2070
0$
#2080
b100 ,
b1001111 +
1$
#2090
0$
#2100
b101 ,
b1010000 +
1$
#2110
0$
#2120
b110 ,
b1010001 +
1$
#2130
0$
#2140
b111 ,
b1010010 +
1$
#2150
0$
#2160
b1000 ,
b1010011 +
1$
#2170
0$
#2180
b1001 ,
b1010100 +
1$
#2190
0$
#2200
b1010 ,
b1010101 +
1$
#2210
0$
#2220
b1011 ,
b1010110 +
1$
#2230
0$
#2240
b1100 ,
b1010111 +
1$
#2250
0$
#2260
b1101 ,
b1011000 +
1$
#2270
0$
#2280
b1110 ,
b1011001 +
1$
#2290
0$
#2300
b1111 ,
b1011010 +
1$
#2310
0$
#2320
b10000 ,
b1011011 +
1$
#2330
0$
#2340
b10001 ,
b1011100 +
1$
#2350
0$
#2360
b10010 ,
b1011101 +
1$
#2370
0$
#2380
b10011 ,
b1011110 +
1$
#2390
0$
#2400
b10100 ,
b1011111 +
1$
#2410
0$
#2420
b10101 ,
b1100000 +
1$
#2430
0$
#2440
b10110 ,
b1100001 +
1$
#2450
0$
#2460
b10111 ,
b1100010 +
1$
#2470
0$
#2480
b11000 ,
b1100011 +
1$
#2490
0$
#2500
b11001 ,
b1100100 +
1$
#2510
0$
#2520
0#
b1 ,
b1100101 +
1$
#2530
0$
#2540
1'
b10 ,
b1100110 +
0/
1$
#2550
0$
#2560
0'
b1101 1
b11 ,
b1100111 +
00
1$
#2570
0$
#2580
b100 ,
b1101000 +
1$
#2590
0$
#2600
b101 ,
b1101001 +
1$
#2610
0$
#2620
b110 ,
b1101010 +
1$
#2630
0$
#2640
b111 ,
b1101011 +
1$
#2650
0$
#2660
b1000 ,
b1101100 +
1$
#2670
0$
#2680
b1001 ,
b1101101 +
1$
#2690
0$
#2700
b1010 ,
b1101110 +
1$
#2710
0$
#2720
b1011 ,
b1101111 +
1$
#2730
0$
#2740
b1100 ,
b1110000 +
1$
#2750
0$
#2760
b1101 ,
b1110001 +
1$
#2770
0$
#2780
b1110 ,
b1110010 +
1$
#2790
0$
#2800
b1111 ,
b1110011 +
1$
#2810
0$
#2820
b10000 ,
b1110100 +
1$
#2830
0$
#2840
b10001 ,
b1110101 +
1$
#2850
0$
#2860
b10010 ,
b1110110 +
1$
#2870
0$
#2880
b10011 ,
b1110111 +
1$
#2890
0$
#2900
b10100 ,
b1111000 +
1$
#2910
0$
#2920
b10101 ,
b1111001 +
1$
#2930
0$
#2940
b10110 ,
b1111010 +
1$
#2950
0$
#2960
b10111 ,
b1111011 +
1$
#2970
0$
#2980
b11000 ,
b1111100 +
1$
#2990
0$
#3000
b11001 ,
b1111101 +
1$
#3010
0$
#3020
1#
b1 ,
b1111110 +
1$
#3030
0$
#3040
1(
b10 ,
b1111111 +
1/
1$
#3050
0$
#3060
0(
b11 ,
b10000000 +
10
1$
#3070
0$
#3080
b100 ,
b10000001 +
1$
#3090
0$
#3100
b101 ,
b10000010 +
1$
#3110
0$
#3120
b110 ,
b10000011 +
1$
#3130
0$
#3140
b111 ,
b10000100 +
1$
#3150
0$
#3160
b1000 ,
b10000101 +
1$
#3170
0$
#3180
b1001 ,
b10000110 +
1$
#3190
0$
#3200
b1010 ,
b10000111 +
1$
#3210
0$
#3220
b1011 ,
b10001000 +
1$
#3230
0$
#3240
b1100 ,
b10001001 +
1$
#3250
0$
#3260
b1101 ,
b10001010 +
1$
#3270
0$
#3280
b1110 ,
b10001011 +
1$
#3290
0$
#3300
b1111 ,
b10001100 +
1$
#3310
0$
#3320
b10000 ,
b10001101 +
1$
#3330
0$
#3340
b10001 ,
b10001110 +
1$
#3350
0$
#3360
b10010 ,
b10001111 +
1$
#3370
0$
#3380
b10011 ,
b10010000 +
1$
#3390
0$
#3400
b10100 ,
b10010001 +
1$
#3410
0$
#3420
b10101 ,
b10010010 +
1$
#3430
0$
#3440
b10110 ,
b10010011 +
1$
#3450
0$
#3460
b10111 ,
b10010100 +
1$
#3470
0$
#3480
b11000 ,
b10010101 +
1$
#3490
0$
#3500
b11001 ,
b10010110 +
1$
#3510
0$
#3520
0#
b1 ,
b10010111 +
1$
#3530
0$
#3540
1'
b10 ,
b10011000 +
0/
1$
#3550
0$
#3560
0'
b1100 1
b11 ,
b10011001 +
00
1$
#3570
0$
#3580
b100 ,
b10011010 +
1$
#3590
0$
#3600
b101 ,
b10011011 +
1$
#3610
0$
#3620
b110 ,
b10011100 +
1$
#3630
0$
#3640
b111 ,
b10011101 +
1$
#3650
0$
#3660
b1000 ,
b10011110 +
1$
#3670
0$
#3680
b1001 ,
b10011111 +
1$
#3690
0$
#3700
b1010 ,
b10100000 +
1$
#3710
0$
#3720
b1011 ,
b10100001 +
1$
#3730
0$
#3740
b1100 ,
b10100010 +
1$
#3750
0$
#3760
b1101 ,
b10100011 +
1$
#3770
0$
#3780
b1110 ,
b10100100 +
1$
#3790
0$
#3800
b1111 ,
b10100101 +
1$
#3810
0$
#3820
b10000 ,
b10100110 +
1$
#3830
0$
#3840
b10001 ,
b10100111 +
1$
#3850
0$
#3860
b10010 ,
b10101000 +
1$
#3870
0$
#3880
b10011 ,
b10101001 +
1$
#3890
0$
#3900
b10100 ,
b10101010 +
1$
#3910
0$
#3920
b10101 ,
b10101011 +
1$
#3930
0$
#3940
b10110 ,
b10101100 +
1$
#3950
0$
#3960
b10111 ,
b10101101 +
1$
#3970
0$
#3980
b11000 ,
b10101110 +
1$
#3990
0$
#4000
b11001 ,
b10101111 +
1$
#4010
0$
#4020
1#
b1 ,
b10110000 +
1$
#4030
0$
#4040
1(
b10 ,
b10110001 +
1/
1$
#4050
0$
#4060
0(
b11 ,
b10110010 +
10
1$
#4070
0$
#4080
b100 ,
b10110011 +
1$
#4090
0$
#4100
b101 ,
b10110100 +
1$
#4110
0$
#4120
b110 ,
b10110101 +
1$
#4130
0$
#4140
b111 ,
b10110110 +
1$
#4150
0$
#4160
b1000 ,
b10110111 +
1$
#4170
0$
#4180
b1001 ,
b10111000 +
1$
#4190
0$
#4200
b1010 ,
b10111001 +
1$
#4210
0$
#4220
b1011 ,
b10111010 +
1$
#4230
0$
#4240
b1100 ,
b10111011 +
1$
#4250
0$
#4260
b1101 ,
b10111100 +
1$
#4270
0$
#4280
b1110 ,
b10111101 +
1$
#4290
0$
#4300
b1111 ,
b10111110 +
1$
#4310
0$
#4320
b10000 ,
b10111111 +
1$
#4330
0$
#4340
b10001 ,
b11000000 +
1$
#4350
0$
#4360
b10010 ,
b11000001 +
1$
#4370
0$
#4380
b10011 ,
b11000010 +
1$
#4390
0$
#4400
b10100 ,
b11000011 +
1$
#4410
0$
#4420
b10101 ,
b11000100 +
1$
#4430
0$
#4440
b10110 ,
b11000101 +
1$
#4450
0$
#4460
b10111 ,
b11000110 +
1$
#4470
0$
#4480
b11000 ,
b11000111 +
1$
#4490
0$
#4500
b11001 ,
b11001000 +
1$
#4510
0$
#4520
0#
b1 ,
b11001001 +
1$
#4530
0$
#4540
1'
b10 ,
b11001010 +
0/
1$
#4550
0$
#4560
0'
b1011 1
b11 ,
b11001011 +
00
1$
#4570
0$
#4580
b100 ,
b11001100 +
1$
#4590
0$
#4600
b101 ,
b11001101 +
1$
#4610
0$
#4620
b110 ,
b11001110 +
1$
#4630
0$
#4640
b111 ,
b11001111 +
1$
#4650
0$
#4660
b1000 ,
b11010000 +
1$
#4670
0$
#4680
b1001 ,
b11010001 +
1$
#4690
0$
#4700
b1010 ,
b11010010 +
1$
#4710
0$
#4720
b1011 ,
b11010011 +
1$
#4730
0$
#4740
b1100 ,
b11010100 +
1$
#4750
0$
#4760
b1101 ,
b11010101 +
1$
#4770
0$
#4780
b1110 ,
b11010110 +
1$
#4790
0$
#4800
b1111 ,
b11010111 +
1$
#4810
0$
#4820
b10000 ,
b11011000 +
1$
#4830
0$
#4840
b10001 ,
b11011001 +
1$
#4850
0$
#4860
b10010 ,
b11011010 +
1$
#4870
0$
#4880
b10011 ,
b11011011 +
1$
#4890
0$
#4900
b10100 ,
b11011100 +
1$
#4910
0$
#4920
b10101 ,
b11011101 +
1$
#4930
0$
#4940
b10110 ,
b11011110 +
1$
#4950
0$
#4960
b10111 ,
b11011111 +
1$
#4970
0$
#4980
b11000 ,
b11100000 +
1$
#4990
0$
#5000
b11001 ,
b11100001 +
1$
#5010
0$
#5020
1#
b1 ,
b11100010 +
1$
#5030
0$
#5040
1(
b10 ,
b11100011 +
1/
1$
#5050
0$
#5060
0(
b11 ,
b11100100 +
10
1$
#5070
0$
#5080
b100 ,
b11100101 +
1$
#5090
0$
#5100
b101 ,
b11100110 +
1$
#5110
0$
#5120
b110 ,
b11100111 +
1$
#5130
0$
#5140
b111 ,
b11101000 +
1$
#5150
0$
#5160
b1000 ,
b11101001 +
1$
#5170
0$
#5180
b1001 ,
b11101010 +
1$
#5190
0$
#5200
b1010 ,
b11101011 +
1$
#5210
0$
#5220
b1011 ,
b11101100 +
1$
#5230
0$
#5240
b1100 ,
b11101101 +
1$
#5250
0$
#5260
b1101 ,
b11101110 +
1$
#5270
0$
#5280
b1110 ,
b11101111 +
1$
#5290
0$
#5300
b1111 ,
b11110000 +
1$
#5310
0$
#5320
b10000 ,
b11110001 +
1$
#5330
0$
#5340
b10001 ,
b11110010 +
1$
#5350
0$
#5360
b10010 ,
b11110011 +
1$
#5370
0$
#5380
b10011 ,
b11110100 +
1$
#5390
0$
#5400
b10100 ,
b11110101 +
1$
#5410
0$
#5420
b10101 ,
b11110110 +
1$
#5430
0$
#5440
b10110 ,
b11110111 +
1$
#5450
0$
#5460
b10111 ,
b11111000 +
1$
#5470
0$
#5480
b11000 ,
b11111001 +
1$
#5490
0$
#5500
b11001 ,
b11111010 +
1$
#5510
0$
#5520
0#
b1 ,
b11111011 +
1$
#5530
0$
#5540
1'
b10 ,
b11111100 +
0/
1$
#5550
0$
#5560
0'
b1010 1
b11 ,
b11111101 +
00
1$
#5570
0$
#5580
b100 ,
b11111110 +
1$
#5590
0$
#5600
b101 ,
b11111111 +
1$
#5610
0$
#5620
b110 ,
b100000000 +
1$
#5630
0$
#5640
b111 ,
b100000001 +
1$
#5650
0$
#5660
b1000 ,
b100000010 +
1$
#5670
0$
#5680
b1001 ,
b100000011 +
1$
#5690
0$
#5700
b1010 ,
b100000100 +
1$
#5710
0$
#5720
b1011 ,
b100000101 +
1$
#5730
0$
#5740
b1100 ,
b100000110 +
1$
#5750
0$
#5760
b1101 ,
b100000111 +
1$
#5770
0$
#5780
b1110 ,
b100001000 +
1$
#5790
0$
#5800
b1111 ,
b100001001 +
1$
#5810
0$
#5820
b10000 ,
b100001010 +
1$
#5830
0$
#5840
b10001 ,
b100001011 +
1$
#5850
0$
#5860
b10010 ,
b100001100 +
1$
#5870
0$
#5880
b10011 ,
b100001101 +
1$
#5890
0$
#5900
b10100 ,
b100001110 +
1$
#5910
0$
#5920
b10101 ,
b100001111 +
1$
#5930
0$
#5940
b10110 ,
b100010000 +
1$
#5950
0$
#5960
b10111 ,
b100010001 +
1$
#5970
0$
#5980
b11000 ,
b100010010 +
1$
#5990
0$
#6000
b11001 ,
b100010011 +
1$
#6010
0$
#6020
1#
b1 ,
b100010100 +
1$
#6030
0$
#6040
1(
b10 ,
b100010101 +
1/
1$
#6050
0$
#6060
0(
b11 ,
b100010110 +
10
1$
#6070
0$
#6080
b100 ,
b100010111 +
1$
#6090
0$
#6100
b101 ,
b100011000 +
1$
#6110
0$
#6120
b110 ,
b100011001 +
1$
#6130
0$
#6140
b111 ,
b100011010 +
1$
#6150
0$
#6160
b1000 ,
b100011011 +
1$
#6170
0$
#6180
b1001 ,
b100011100 +
1$
#6190
0$
#6200
b1010 ,
b100011101 +
1$
#6210
0$
#6220
b1011 ,
b100011110 +
1$
#6230
0$
#6240
b1100 ,
b100011111 +
1$
#6250
0$
#6260
b1101 ,
b100100000 +
1$
#6270
0$
#6280
b1110 ,
b100100001 +
1$
#6290
0$
#6300
b1111 ,
b100100010 +
1$
#6310
0$
#6320
b10000 ,
b100100011 +
1$
#6330
0$
#6340
b10001 ,
b100100100 +
1$
#6350
0$
#6360
b10010 ,
b100100101 +
1$
#6370
0$
#6380
b10011 ,
b100100110 +
1$
#6390
0$
#6400
b10100 ,
b100100111 +
1$
#6410
0$
#6420
b10101 ,
b100101000 +
1$
#6430
0$
#6440
b10110 ,
b100101001 +
1$
#6450
0$
#6460
b10111 ,
b100101010 +
1$
#6470
0$
#6480
b11000 ,
b100101011 +
1$
#6490
0$
#6500
b11001 ,
b100101100 +
1$
#6510
0$
#6520
0#
b1 ,
b100101101 +
1$
#6530
0$
#6540
1'
b10 ,
b100101110 +
0/
1$
#6550
0$
#6560
0'
b1001 1
b11 ,
b100101111 +
00
1$
#6570
0$
#6580
b100 ,
b100110000 +
1$
#6590
0$
#6600
b101 ,
b100110001 +
1$
#6610
0$
#6620
b110 ,
b100110010 +
1$
#6630
0$
#6640
b111 ,
b100110011 +
1$
#6650
0$
#6660
b1000 ,
b100110100 +
1$
#6670
0$
#6680
b1001 ,
b100110101 +
1$
#6690
0$
#6700
b1010 ,
b100110110 +
1$
#6710
0$
#6720
b1011 ,
b100110111 +
1$
#6730
0$
#6740
b1100 ,
b100111000 +
1$
#6750
0$
#6760
b1101 ,
b100111001 +
1$
#6770
0$
#6780
b1110 ,
b100111010 +
1$
#6790
0$
#6800
b1111 ,
b100111011 +
1$
#6810
0$
#6820
b10000 ,
b100111100 +
1$
#6830
0$
#6840
b10001 ,
b100111101 +
1$
#6850
0$
#6860
b10010 ,
b100111110 +
1$
#6870
0$
#6880
b10011 ,
b100111111 +
1$
#6890
0$
#6900
b10100 ,
b101000000 +
1$
#6910
0$
#6920
b10101 ,
b101000001 +
1$
#6930
0$
#6940
b10110 ,
b101000010 +
1$
#6950
0$
#6960
b10111 ,
b101000011 +
1$
#6970
0$
#6980
b11000 ,
b101000100 +
1$
#6990
0$
#7000
b11001 ,
b101000101 +
1$
#7010
0$
#7020
1#
b1 ,
b101000110 +
1$
#7030
0$
#7040
1(
b10 ,
b101000111 +
1/
1$
#7050
0$
#7060
0(
b11 ,
b101001000 +
10
1$
#7070
0$
#7080
b100 ,
b101001001 +
1$
#7090
0$
#7100
b101 ,
b101001010 +
1$
#7110
0$
#7120
b110 ,
b101001011 +
1$
#7130
0$
#7140
b111 ,
b101001100 +
1$
#7150
0$
#7160
b1000 ,
b101001101 +
1$
#7170
0$
#7180
b1001 ,
b101001110 +
1$
#7190
0$
#7200
b1010 ,
b101001111 +
1$
#7210
0$
#7220
b1011 ,
b101010000 +
1$
#7230
0$
#7240
b1100 ,
b101010001 +
1$
#7250
0$
#7260
b1101 ,
b101010010 +
1$
#7270
0$
#7280
b1110 ,
b101010011 +
1$
#7290
0$
#7300
b1111 ,
b101010100 +
1$
#7310
0$
#7320
b10000 ,
b101010101 +
1$
#7330
0$
#7340
b10001 ,
b101010110 +
1$
#7350
0$
#7360
b10010 ,
b101010111 +
1$
#7370
0$
#7380
b10011 ,
b101011000 +
1$
#7390
0$
#7400
b10100 ,
b101011001 +
1$
#7410
0$
#7420
b10101 ,
b101011010 +
1$
#7430
0$
#7440
b10110 ,
b101011011 +
1$
#7450
0$
#7460
b10111 ,
b101011100 +
1$
#7470
0$
#7480
b11000 ,
b101011101 +
1$
#7490
0$
#7500
b11001 ,
b101011110 +
1$
#7510
0$
#7520
0#
b1 ,
b101011111 +
1$
1&
#7530
0$
#7540
1'
b10 ,
b101100000 +
0/
1$
#7550
0$
#7560
0'
b1000 1
b11 ,
b101100001 +
00
1$
#7570
0$
#7580
b100 ,
b101100010 +
1$
#7590
0$
#7600
b101 ,
b101100011 +
1$
#7610
0$
#7620
b110 ,
b101100100 +
1$
#7630
0$
#7640
b111 ,
b101100101 +
1$
#7650
0$
#7660
b1000 ,
b101100110 +
1$
#7670
0$
#7680
b1001 ,
b101100111 +
1$
#7690
0$
#7700
b1010 ,
b101101000 +
1$
#7710
0$
#7720
b1011 ,
b101101001 +
1$
#7730
0$
#7740
b1100 ,
b101101010 +
1$
#7750
0$
#7760
b1101 ,
b101101011 +
1$
#7770
0$
#7780
b1110 ,
b101101100 +
1$
#7790
0$
#7800
b1111 ,
b101101101 +
1$
#7810
0$
#7820
b10000 ,
b101101110 +
1$
#7830
0$
#7840
b10001 ,
b101101111 +
1$
#7850
0$
#7860
b10010 ,
b101110000 +
1$
#7870
0$
#7880
b10011 ,
b101110001 +
1$
#7890
0$
#7900
b10100 ,
b101110010 +
1$
#7910
0$
#7920
b10101 ,
b101110011 +
1$
#7930
0$
#7940
b10110 ,
b101110100 +
1$
#7950
0$
#7960
b10111 ,
b101110101 +
1$
#7970
0$
#7980
b11000 ,
b101110110 +
1$
#7990
0$
#8000
b11001 ,
b101110111 +
1$
#8010
0$
#8020
1#
b1 ,
b101111000 +
1$
#8030
0$
#8040
1(
b10 ,
b101111001 +
1/
1$
#8050
0$
#8060
0(
b10000000 3
b11 ,
b101111010 +
10
1$
#8070
0$
#8080
b100 ,
b101111011 +
1$
#8090
0$
#8100
b101 ,
b101111100 +
1$
#8110
0$
#8120
b110 ,
b101111101 +
1$
#8130
0$
#8140
b111 ,
b101111110 +
1$
#8150
0$
#8160
b1000 ,
b101111111 +
1$
#8170
0$
#8180
b1001 ,
b110000000 +
1$
#8190
0$
#8200
b1010 ,
b110000001 +
1$
#8210
0$
#8220
b1011 ,
b110000010 +
1$
#8230
0$
#8240
b1100 ,
b110000011 +
1$
#8250
0$
#8260
b1101 ,
b110000100 +
1$
#8270
0$
#8280
b1110 ,
b110000101 +
1$
#8290
0$
#8300
b1111 ,
b110000110 +
1$
#8310
0$
#8320
b10000 ,
b110000111 +
1$
#8330
0$
#8340
b10001 ,
b110001000 +
1$
#8350
0$
#8360
b10010 ,
b110001001 +
1$
#8370
0$
#8380
b10011 ,
b110001010 +
1$
#8390
0$
#8400
b10100 ,
b110001011 +
1$
#8410
0$
#8420
b10101 ,
b110001100 +
1$
#8430
0$
#8440
b10110 ,
b110001101 +
1$
#8450
0$
#8460
b10111 ,
b110001110 +
1$
#8470
0$
#8480
b11000 ,
b110001111 +
1$
#8490
0$
#8500
b11001 ,
b110010000 +
1$
#8510
0$
#8520
0#
b1 ,
b110010001 +
1$
0&
#8530
0$
#8540
1'
b10 ,
b110010010 +
0/
1$
#8550
0$
#8560
0'
b111 1
b11 ,
b110010011 +
00
1$
#8570
0$
#8580
b100 ,
b110010100 +
1$
#8590
0$
#8600
b101 ,
b110010101 +
1$
#8610
0$
#8620
b110 ,
b110010110 +
1$
#8630
0$
#8640
b111 ,
b110010111 +
1$
#8650
0$
#8660
b1000 ,
b110011000 +
1$
#8670
0$
#8680
b1001 ,
b110011001 +
1$
#8690
0$
#8700
b1010 ,
b110011010 +
1$
#8710
0$
#8720
b1011 ,
b110011011 +
1$
#8730
0$
#8740
b1100 ,
b110011100 +
1$
#8750
0$
#8760
b1101 ,
b110011101 +
1$
#8770
0$
#8780
b1110 ,
b110011110 +
1$
#8790
0$
#8800
b1111 ,
b110011111 +
1$
#8810
0$
#8820
b10000 ,
b110100000 +
1$
#8830
0$
#8840
b10001 ,
b110100001 +
1$
#8850
0$
#8860
b10010 ,
b110100010 +
1$
#8870
0$
#8880
b10011 ,
b110100011 +
1$
#8890
0$
#8900
b10100 ,
b110100100 +
1$
#8910
0$
#8920
b10101 ,
b110100101 +
1$
#8930
0$
#8940
b10110 ,
b110100110 +
1$
#8950
0$
#8960
b10111 ,
b110100111 +
1$
#8970
0$
#8980
b11000 ,
b110101000 +
1$
#8990
0$
#9000
b11001 ,
b110101001 +
1$
#9010
0$
#9020
1#
b1 ,
b110101010 +
1$
#9030
0$
#9040
1(
b10 ,
b110101011 +
1/
1$
#9050
0$
#9060
0(
b11 ,
b110101100 +
10
1$
#9070
0$
#9080
b100 ,
b110101101 +
1$
#9090
0$
#9100
b101 ,
b110101110 +
1$
#9110
0$
#9120
b110 ,
b110101111 +
1$
#9130
0$
#9140
b111 ,
b110110000 +
1$
#9150
0$
