src/BASIS/VERILOG/TEST/TA5_FINAL.v
module TEST(
	input CLK,
	input CLK_1MHz,
	input CLK_1Hz,
	input IN8,
	input IN9,
	input IN10,
	input IN11,
	input IN12,
	input IN13,
	input IN14,
	input IN15,
	input [15:0] IN16BIT1,
	input [15:0] IN16BIT2,
	input [15:0] IN16BIT3,
	input signed [15:0] IN16BIT4,	
	//
	output reg OUT8,
	output reg OUT9,
	output reg OUT10, 
	output reg OUT11,
	output reg OUT12,
	output reg OUT13,
	output reg OUT14, 
	output reg OUT15,
	output reg [15:0] OUT16BIT1,
	output reg [15:0] OUT16BIT2,
	output reg [15:0] OUT16BIT3,
	output reg signed [15:0] OUT16BIT4);
	//
	reg [7:0] counter;
	wire IN8re; wire IN8fe;
	wire IN9re; wire IN9fe;
	reg hri1; reg hri2; reg hri3; reg hri4;
	//
	assign IN8re = (hri1 && !hri2);
	assign IN8fe = (!hri1 && hri2);
	assign IN9re = (hri3 && !hri4);
	assign IN9fe = (!hri3 && hri4);	
	//
	initial
	begin
		OUT16BIT1 <= 0;
		OUT16BIT2 <= 0;
		OUT16BIT3 <= 0;
		OUT16BIT4 <= 0;
		OUT8 <= 0; OUT9 <= 0; OUT10 <= 0; OUT11 <= 0; OUT12 <= 0; OUT13 <= 0; OUT14 <= 0; OUT15 <= 0;
		//
		counter <= 0;
		hri1 <= 0; hri2 <= 0; hri3 <= 0; hri4 <= 0;
	end
	//
	always @(posedge CLK)
	begin
		//
		// Flankenauswertung
		hri1 <= IN8;
		hri2 <= hri1;	
		hri3 <= IN9;
		hri4 <= hri3;	
		//
		if (IN8re) counter <= counter + 1;
		if (IN9re) counter <= counter - 1;
		if (IN10) counter <= 0;
		//
		OUT16BIT1[7:0] <= counter[7:0];
		//
	end
endmodule

src/BASIS/VERILOG/TEST/ICARUS_TB.v
`include "TEST.v"
// http://verilogtutorial.blogspot.ch/2012/09/verilog-timescale-system-tasks.html
`timescale 10ns/1ns
//
module ICARUS_TB;
	integer file;
	reg clk;
	reg clk_1MHz;
	reg clk_1Hz;
	reg in8;
	reg in9;
	reg in10;
	reg in11;
	reg in12;
	reg in13;
	reg in14;
	reg in15;
	reg [15:0] in16bit1;
	reg [15:0] in16bit2;
	reg [15:0] in16bit3;
	reg [15:0] in16bit4;	
	//
	wire out8;
	wire out9;
	wire out10;
	wire out11;	
	wire out12;
	wire out13;
	wire out14;
	wire out15;	
	wire [15:0] out16bit1;
	wire [15:0] out16bit2;
	wire [15:0] out16bit3;
	wire [15:0] out16bit4;		
	//
	initial 
		begin
		clk <= 1;
		clk_1MHz <= 1;
		clk_1Hz <= 1;
		in8 <= 0;
		in9 <= 0;
		in10 <= 0;
		in11 <= 0;
		in12 <= 0;
		in13 <= 0;
		in14 <= 0;
		in15 <= 0;
		in16bit1 <= 0;
		in16bit2 <= 0;
		in16bit3 <= 0;
		in16bit4 <= 0;
		//		
		$dumpfile("vcd\\\icarus_tb.vcd"); 
		$dumpvars(0, ICARUS_TB); 		
		//
		#10 in8 <= 1;
		#10 in8 <= 0;
		#10 in8 <= 1;
		#10 in8 <= 0;
		#10 in8 <= 1;
		#10 in8 <= 0;
		#10 in8 <= 1;
		#10 in8 <= 0;
		#10 in8 <= 1;
		#10 in8 <= 0;
		#10 in9 <= 1;
		#10 in9 <= 0;
		#10 in9 <= 1;
		#10 in9 <= 0;
		#10 in10 <= 1;
		#10 in10 <= 0;
		//
		#10 $finish; 
		end 
	//
	always #1        clk <= !clk;// 50MHz
	always #50       clk_1MHz <= !clk_1MHz;// 1MHz	
	always #50000000 clk_1Hz <= !clk_1Hz;// 1Hz		
	//
	TEST test(clk,
			  clk_1MHz,
			  clk_1Hz,
			  in8,
			  in9,
			  in10,
			  in11,
			  in12,
			  in13,
			  in14,
			  in15,
			  in16bit1,
			  in16bit2,
			  in16bit3,
			  in16bit4,
			  out8,
			  out9,
			  out10,
			  out11,
			  out12,
			  out13,
			  out14,
			  out15,
			  out16bit1,
			  out16bit2,
			  out16bit3,
			  out16bit4);					
	//
endmodule
/*
cd D:\Dropbox\ABBTS_LABOR_DOZ\MOTION_CONTROL\FPGA_MODUL_MAX1000_DIT_RET_UR\FPGA_MODUL_MAX1000_DIT_RET_UR_01_00\src\BASIS\VERILOG\TEST
C:\iverilog\bin\iverilog -s ICARUS_TB -o icarus_tb.o ICARUS_TB.v
C:\iverilog\bin\vvp icarus_tb.o
*/

src/BASIS/VERILOG/TEST/vcd/icarus_tb.vcd
$date
	Thu Jun 07 11:50:06 2018
$end
$version
	Icarus Verilog
$end
$timescale
	1ns
$end
$scope module ICARUS_TB $end
$var wire 1 ! out9 $end
$var wire 1 " out8 $end
$var wire 16 # out16bit4 [15:0] $end
$var wire 16 $ out16bit3 [15:0] $end
$var wire 16 % out16bit2 [15:0] $end
$var wire 16 & out16bit1 [15:0] $end
$var wire 1 ' out15 $end
$var wire 1 ( out14 $end
$var wire 1 ) out13 $end
$var wire 1 * out12 $end
$var wire 1 + out11 $end
$var wire 1 , out10 $end
$var reg 1 - clk $end
$var reg 1 . clk_1Hz $end
$var reg 1 / clk_1MHz $end
$var reg 1 0 in10 $end
$var reg 1 1 in11 $end
$var reg 1 2 in12 $end
$var reg 1 3 in13 $end
$var reg 1 4 in14 $end
$var reg 1 5 in15 $end
$var reg 16 6 in16bit1 [15:0] $end
$var reg 16 7 in16bit2 [15:0] $end
$var reg 16 8 in16bit3 [15:0] $end
$var reg 16 9 in16bit4 [15:0] $end
$var reg 1 : in8 $end
$var reg 1 ; in9 $end
$scope module test $end
$var wire 1 - CLK $end
$var wire 1 . CLK_1Hz $end
$var wire 1 / CLK_1MHz $end
$var wire 1 0 IN10 $end
$var wire 1 1 IN11 $end
$var wire 1 2 IN12 $end
$var wire 1 3 IN13 $end
$var wire 1 4 IN14 $end
$var wire 1 5 IN15 $end
$var wire 16 < IN16BIT1 [15:0] $end
$var wire 16 = IN16BIT2 [15:0] $end
$var wire 16 > IN16BIT3 [15:0] $end
$var wire 16 ? IN16BIT4 [15:0] $end
$var wire 1 : IN8 $end
$var wire 1 @ IN8fe $end
$var wire 1 A IN8re $end
$var wire 1 ; IN9 $end
$var wire 1 B IN9fe $end
$var wire 1 C IN9re $end
$var reg 1 , OUT10 $end
$var reg 1 + OUT11 $end
$var reg 1 * OUT12 $end
$var reg 1 ) OUT13 $end
$var reg 1 ( OUT14 $end
$var reg 1 ' OUT15 $end
$var reg 16 D OUT16BIT1 [15:0] $end
$var reg 16 E OUT16BIT2 [15:0] $end
$var reg 16 F OUT16BIT3 [15:0] $end
$var reg 16 G OUT16BIT4 [15:0] $end
$var reg 1 " OUT8 $end
$var reg 1 ! OUT9 $end
$var reg 8 H counter [7:0] $end
$var reg 1 I hri1 $end
$var reg 1 J hri2 $end
$var reg 1 K hri3 $end
$var reg 1 L hri4 $end
$upscope $end
$upscope $end
$enddefinitions $end
#0
$dumpvars
0L
0K
0J
0I
b0 H
b0 G
b0 F
b0 E
b0 D
0C
0B
0A
0@
b0 ?
b0 >
b0 =
b0 <
0;
0:
b0 9
b0 8
b0 7
b0 6
05
04
03
02
01
00
1/
1.
1-
0,
0+
0*
0)
0(
0'
b0 &
b0 %
b0 $
b0 #
0"
0!
$end
#10
0-
#20
1-
#30
0-
#40
1-
#50
0-
#60
1-
#70
0-
#80
1-
#90
0-
#100
1A
1I
1-
1:
#110
0-
#120
0A
b1 H
1J
1-
#130
0-
#140
b1 &
b1 D
1-
#150
0-
#160
1-
#170
0-
#180
1-
#190
0-
#200
1@
0I
1-
0:
#210
0-
#220
0@
0J
1-
#230
0-
#240
1-
#250
0-
#260
1-
#270
0-
#280
1-
#290
0-
#300
1A
1I
1-
1:
#310
0-
#320
0A
b10 H
1J
1-
#330
0-
#340
b10 &
b10 D
1-
#350
0-
#360
1-
#370
0-
#380
1-
#390
0-
#400
1@
0I
1-
0:
#410
0-
#420
0@
0J
1-
#430
0-
#440
1-
#450
0-
#460
1-
#470
0-
#480
1-
#490
0-
#500
1A
1I
1-
1:
0/
#510
0-
#520
0A
b11 H
1J
1-
#530
0-
#540
b11 &
b11 D
1-
#550
0-
#560
1-
#570
0-
#580
1-
#590
0-
#600
1@
0I
1-
0:
#610
0-
#620
0@
0J
1-
#630
0-
#640
1-
#650
0-
#660
1-
#670
0-
#680
1-
#690
0-
#700
1A
1I
1-
1:
#710
0-
#720
0A
b100 H
1J
1-
#730
0-
#740
b100 &
b100 D
1-
#750
0-
#760
1-
#770
0-
#780
1-
#790
0-
#800
1@
0I
1-
0:
#810
0-
#820
0@
0J
1-
#830
0-
#840
1-
#850
0-
#860
1-
#870
0-
#880
1-
#890
0-
#900
1A
1I
1-
1:
#910
0-
#920
0A
b101 H
1J
1-
#930
0-
#940
b101 &
b101 D
1-
#950
0-
#960
1-
#970
0-
#980
1-
#990
0-
#1000
1@
0I
1-
0:
1/
#1010
0-
#1020
0@
0J
1-
#1030
0-
#1040
1-
#1050
0-
#1060
1-
#1070
0-
#1080
1-
#1090
0-
#1100
1C
1K
1-
1;
#1110
0-
#1120
0C
b100 H
1L
1-
#1130
0-
#1140
b100 &
b100 D
1-
#1150
0-
#1160
1-
#1170
0-
#1180
1-
#1190
0-
#1200
1B
0K
1-
0;
#1210
0-
#1220
0B
0L
1-
#1230
0-
#1240
1-
#1250
0-
#1260
1-
#1270
0-
#1280
1-
#1290
0-
#1300
1C
1K
1-
1;
#1310
0-
#1320
0C
b11 H
1L
1-
#1330
0-
#1340
b11 &
b11 D
1-
#1350
0-
#1360
1-
#1370
0-
#1380
1-
#1390
0-
#1400
1B
0K
1-
0;
#1410
0-
#1420
0B
0L
1-
#1430
0-
#1440
1-
#1450
0-
#1460
1-
#1470
0-
#1480
1-
#1490
0-
#1500
b0 H
1-
10
0/
#1510
0-
#1520
b0 &
b0 D
1-
#1530
0-
#1540
1-
#1550
0-
#1560
1-
#1570
0-
#1580
1-
#1590
0-
#1600
1-
00
