src/AC_MOTOR/AC_MOTOR_TRIANGLE.v
module AC_MOTOR_TRIANGLE(
	input CLK,
	input CW_IN,
	input CCW_IN,
	//input [level_bits - 1:0] AMPLITUDE,
	output reg CW_OUT,
	output reg CCW_OUT,
	output reg LOCK,
	output reg signed [bits + level_bits:0] TRIANGLE);
	
	parameter starting_amplitude = 2;
	parameter levels = 16;
	parameter level_bits = 12;
	parameter bits = 12;

	parameter f_clk = 82000000;
	parameter f_triangle = 5000;

	parameter triangle_max =  f_clk / f_triangle / 4;
	parameter triangle_min = -f_clk / f_triangle / 4;
	parameter triangle_scaler = 2**23 / triangle_max;
	
	// reg [log2(levels) - 1:0] amplitude_int;
	reg cw_int;
	reg ccw_int;
	//reg signed [level_bits:0] amplitude_int;
	//reg signed [level_bits:0] triangle_dir;
	reg signed [1:0] triangle_dir;
	reg signed [bits + level_bits:0] triangle_int;
	// reg signed [bits + level_bits:0] triangle_max;
	// reg signed [bits + level_bits:0] triangle_min;

	initial begin
		//amplitude_int <= starting_amplitude;
		cw_int = 0;
		ccw_int = 1;
		//triangle_dir <= starting_amplitude;
		triangle_dir <= 1;
		triangle_int <= 0;
		//triangle_max <= starting_amplitude * 2048;
		//triangle_min <= -starting_amplitude * 2048;
	end

	always @(posedge CLK) begin
		if (triangle_int >= triangle_max + 1) begin
			LOCK <= 1;
			cw_int <= CW_IN;
			ccw_int <= CCW_IN;
		end else begin
			LOCK <= 0;
		end
	end

	always @(posedge CLK) begin
		if (triangle_int >= triangle_max) triangle_dir <= -1;
		if (triangle_int <= triangle_min) triangle_dir <= 1;
	end

	always @(posedge CLK) begin
		triangle_int <= triangle_int + triangle_dir;
	end

	always @(posedge CLK) begin
		TRIANGLE <= triangle_int * triangle_scaler;
		CW_OUT <= cw_int;
		CCW_OUT <= ccw_int;
	end

	// always @(posedge CLK) begin
	// 	// if (triangle_int >= triangle_max) begin
	// 	// 	// triangle_int <= triangle_max;

	// 	// end else if (triangle_int <= triangle_min) begin
	// 	// 	// triangle_int <= triangle_min;
	// 	// 	triangle_max <= amplitude_int * 2048;  //12b'011111111111';
	// 	// 	triangle_min <= -amplitude_int * 2048; //12b'100000000001';

	// 	// end

	// 	if (triangle_int >= triangle_max || triangle_int <= triangle_min) begin
	// 		cw_int <= CW_IN;
	// 		ccw_int <= CCW_IN;
	// 		triangle_max <= amplitude_int * 2048;  //12b'011111111111';
	// 		triangle_min <= -amplitude_int * 2048; //12b'100000000001';
	// 		// amplitude_int <= AMPLITUDE;
	// 		if (triangle_int >= triangle_max) begin
	// 			triangle_int <= triangle_max - amplitude_int;
	// 			triangle_dir <= -amplitude_int;
	// 		end else if (triangle_int <= triangle_min) begin
	// 			triangle_int <= triangle_min + amplitude_int;
	// 			triangle_dir <= amplitude_int;
	// 		end

	// 	end else begin
	// 		triangle_int <= triangle_int + triangle_dir;
	// 	end
	// 	TRIANGLE <= triangle_int;
	// 	CW_OUT <= cw_int;
	// 	CCW_OUT <= ccw_int;
	// end
endmodule

src/AC_MOTOR/AC_MOTOR_TRIANGLE_TB.v
`include "AC_MOTOR_TRIANGLE.v"
`timescale 10ns/1ns

module AC_MOTOR_TRIANGLE_TB;
	integer file;
	reg clk;
	reg cw_in;
	reg ccw_in;
	// reg [4:0] amplitude;
	//
	wire signed [12+12:0] triangle;
	wire cw_out;
	wire ccw_out;
	wire lock;
	//
	initial begin
		clk <= 1;
		cw_in <= 0;
		ccw_in <= 1;
		//
		// amplitude <= 1;
		//
		$dumpfile("vcd/ac_motor_triangle_tb.vcd"); 
		$dumpvars(0, AC_MOTOR_TRIANGLE_TB); 
		#25000 $finish; 
		// #1000000 $finish;
	end 
	//
	always #1 clk <= !clk;
	//
	AC_MOTOR_TRIANGLE ac_motor(
		clk,
		cw_in,
		ccw_in,
		// amplitude,
		cw_out,
		ccw_out,
		lock,
		triangle);
	//
endmodule
//

/*
cd D:\Dropbox\ABBTS_LABOR_DOZ\MOTION_CONTROL\FPGA\FPGA_MODUL_MAX1000_00_21\src\DC_MOTOR
C:\iverilog\bin\iverilog -s ICARUS_TB -o icarus_tb.o ICARUS_TB.v
C:\iverilog\bin\vvp icarus_tb.o

oder 

cd D:\Dropbox\ABBTS_LABOR_DOZ\MOTION_CONTROL\FPGA\FPGA_MODUL_MAX1000_SA_01_00\src\DC_MOTOR
D:\Dropbox\ABBTS_LABOR_DOZ\MOTION_CONTROL\FPGA\FPGA_MODUL_MAX1000_SA_01_00\icarus\iverilog\bin\iverilog -s ICARUS_TB -o icarus_tb.o ICARUS_TB.v
D:\Dropbox\ABBTS_LABOR_DOZ\MOTION_CONTROL\FPGA\FPGA_MODUL_MAX1000_SA_01_00\icarus\iverilog\bin\vvp icarus_tb.o
*/

src/AC_MOTOR/vcd/ac_motor_triangle_tb.vcd
$date
	Sun Feb  3 17:00:14 2019
$end
$version
	Icarus Verilog
$end
$timescale
	1ns
$end
$scope module AC_MOTOR_TRIANGLE_TB $end
$var wire 25 ! triangle [24:0] $end
$var wire 1 " lock $end
$var wire 1 # cw_out $end
$var wire 1 $ ccw_out $end
$var reg 1 % ccw_in $end
$var reg 1 & clk $end
$var reg 1 ' cw_in $end
$scope module ac_motor $end
$var wire 1 % CCW_IN $end
$var wire 1 & CLK $end
$var wire 1 ' CW_IN $end
$var reg 1 $ CCW_OUT $end
$var reg 1 # CW_OUT $end
$var reg 1 " LOCK $end
$var reg 25 ( TRIANGLE [24:0] $end
$var reg 1 ) ccw_int $end
$var reg 1 * cw_int $end
$var reg 2 + triangle_dir [1:0] $end
$var reg 25 , triangle_int [24:0] $end
$upscope $end
$upscope $end
$enddefinitions $end
#0
$dumpvars
b1 ,
b1 +
0*
1)
b0 (
0'
1&
1%
1$
0#
0"
b0 !
$end
#10
0&
#20
b11111111110 !
b11111111110 (
b10 ,
1&
#30
0&
#40
b111111111100 !
b111111111100 (
b11 ,
1&
#50
0&
#60
b1011111111010 !
b1011111111010 (
b100 ,
1&
#70
0&
#80
b1111111111000 !
b1111111111000 (
b101 ,
1&
#90
0&
#100
b10011111110110 !
b10011111110110 (
b110 ,
1&
#110
0&
#120
b10111111110100 !
b10111111110100 (
b111 ,
1&
#130
0&
#140
b11011111110010 !
b11011111110010 (
b1000 ,
1&
#150
0&
#160
b11111111110000 !
b11111111110000 (
b1001 ,
1&
#170
0&
#180
b100011111101110 !
b100011111101110 (
b1010 ,
1&
#190
0&
#200
b100111111101100 !
b100111111101100 (
b1011 ,
1&
#210
0&
#220
b101011111101010 !
b101011111101010 (
b1100 ,
1&
#230
0&
#240
b101111111101000 !
b101111111101000 (
b1101 ,
1&
#250
0&
#260
b110011111100110 !
b110011111100110 (
b1110 ,
1&
#270
0&
#280
b110111111100100 !
b110111111100100 (
b1111 ,
1&
#290
0&
#300
b111011111100010 !
b111011111100010 (
b10000 ,
1&
#310
0&
#320
b111111111100000 !
b111111111100000 (
b10001 ,
1&
#330
0&
#340
b1000011111011110 !
b1000011111011110 (
b10010 ,
1&
#350
0&
#360
b1000111111011100 !
b1000111111011100 (
b10011 ,
1&
#370
0&
#380
b1001011111011010 !
b1001011111011010 (
b10100 ,
1&
#390
0&
#400
b1001111111011000 !
b1001111111011000 (
b10101 ,
1&
#410
0&
#420
b1010011111010110 !
b1010011111010110 (
b10110 ,
1&
#430
0&
#440
b1010111111010100 !
b1010111111010100 (
b10111 ,
1&
#450
0&
#460
b1011011111010010 !
b1011011111010010 (
b11000 ,
1&
#470
0&
#480
b1011111111010000 !
b1011111111010000 (
b11001 ,
1&
#490
0&
#500
b1100011111001110 !
b1100011111001110 (
b11010 ,
1&
#510
0&
#520
b1100111111001100 !
b1100111111001100 (
b11011 ,
1&
#530
0&
#540
b1101011111001010 !
b1101011111001010 (
b11100 ,
1&
#550
0&
#560
b1101111111001000 !
b1101111111001000 (
b11101 ,
1&
#570
0&
#580
b1110011111000110 !
b1110011111000110 (
b11110 ,
1&
#590
0&
#600
b1110111111000100 !
b1110111111000100 (
b11111 ,
1&
#610
0&
#620
b1111011111000010 !
b1111011111000010 (
b100000 ,
1&
#630
0&
#640
b1111111111000000 !
b1111111111000000 (
b100001 ,
1&
#650
0&
#660
b10000011110111110 !
b10000011110111110 (
b100010 ,
1&
#670
0&
#680
b10000111110111100 !
b10000111110111100 (
b100011 ,
1&
#690
0&
#700
b10001011110111010 !
b10001011110111010 (
b100100 ,
1&
#710
0&
#720
b10001111110111000 !
b10001111110111000 (
b100101 ,
1&
#730
0&
#740
b10010011110110110 !
b10010011110110110 (
b100110 ,
1&
#750
0&
#760
b10010111110110100 !
b10010111110110100 (
b100111 ,
1&
#770
0&
#780
b10011011110110010 !
b10011011110110010 (
b101000 ,
1&
#790
0&
#800
b10011111110110000 !
b10011111110110000 (
b101001 ,
1&
#810
0&
#820
b10100011110101110 !
b10100011110101110 (
b101010 ,
1&
#830
0&
#840
b10100111110101100 !
b10100111110101100 (
b101011 ,
1&
#850
0&
#860
b10101011110101010 !
b10101011110101010 (
b101100 ,
1&
#870
0&
#880
b10101111110101000 !
b10101111110101000 (
b101101 ,
1&
#890
0&
#900
b10110011110100110 !
b10110011110100110 (
b101110 ,
1&
#910
0&
#920
b10110111110100100 !
b10110111110100100 (
b101111 ,
1&
#930
0&
#940
b10111011110100010 !
b10111011110100010 (
b110000 ,
1&
#950
0&
#960
b10111111110100000 !
b10111111110100000 (
b110001 ,
1&
#970
0&
#980
b11000011110011110 !
b11000011110011110 (
b110010 ,
1&
#990
0&
#1000
b11000111110011100 !
b11000111110011100 (
b110011 ,
1&
#1010
0&
#1020
b11001011110011010 !
b11001011110011010 (
b110100 ,
1&
#1030
0&
#1040
b11001111110011000 !
b11001111110011000 (
b110101 ,
1&
#1050
0&
#1060
b11010011110010110 !
b11010011110010110 (
b110110 ,
1&
#1070
0&
#1080
b11010111110010100 !
b11010111110010100 (
b110111 ,
1&
#1090
0&
#1100
b11011011110010010 !
b11011011110010010 (
b111000 ,
1&
#1110
0&
#1120
b11011111110010000 !
b11011111110010000 (
b111001 ,
1&
#1130
0&
#1140
b11100011110001110 !
b11100011110001110 (
b111010 ,
1&
#1150
0&
#1160
b11100111110001100 !
b11100111110001100 (
b111011 ,
1&
#1170
0&
#1180
b11101011110001010 !
b11101011110001010 (
b111100 ,
1&
#1190
0&
#1200
b11101111110001000 !
b11101111110001000 (
b111101 ,
1&
#1210
0&
#1220
b11110011110000110 !
b11110011110000110 (
b111110 ,
1&
#1230
0&
#1240
b11110111110000100 !
b11110111110000100 (
b111111 ,
1&
#1250
0&
#1260
b11111011110000010 !
b11111011110000010 (
b1000000 ,
1&
#1270
0&
#1280
b11111111110000000 !
b11111111110000000 (
b1000001 ,
1&
#1290
0&
#1300
b100000011101111110 !
b100000011101111110 (
b1000010 ,
1&
#1310
0&
#1320
b100000111101111100 !
b100000111101111100 (
b1000011 ,
1&
#1330
0&
#1340
b100001011101111010 !
b100001011101111010 (
b1000100 ,
1&
#1350
0&
#1360
b100001111101111000 !
b100001111101111000 (
b1000101 ,
1&
#1370
0&
#1380
b100010011101110110 !
b100010011101110110 (
b1000110 ,
1&
#1390
0&
#1400
b100010111101110100 !
b100010111101110100 (
b1000111 ,
1&
#1410
0&
#1420
b100011011101110010 !
b100011011101110010 (
b1001000 ,
1&
#1430
0&
#1440
b100011111101110000 !
b100011111101110000 (
b1001001 ,
1&
#1450
0&
#1460
b100100011101101110 !
b100100011101101110 (
b1001010 ,
1&
#1470
0&
#1480
b100100111101101100 !
b100100111101101100 (
b1001011 ,
1&
#1490
0&
#1500
b100101011101101010 !
b100101011101101010 (
b1001100 ,
1&
#1510
0&
#1520
b100101111101101000 !
b100101111101101000 (
b1001101 ,
1&
#1530
0&
#1540
b100110011101100110 !
b100110011101100110 (
b1001110 ,
1&
#1550
0&
#1560
b100110111101100100 !
b100110111101100100 (
b1001111 ,
1&
#1570
0&
#1580
b100111011101100010 !
b100111011101100010 (
b1010000 ,
1&
#1590
0&
#1600
b100111111101100000 !
b100111111101100000 (
b1010001 ,
1&
#1610
0&
#1620
b101000011101011110 !
b101000011101011110 (
b1010010 ,
1&
#1630
0&
#1640
b101000111101011100 !
b101000111101011100 (
b1010011 ,
1&
#1650
0&
#1660
b101001011101011010 !
b101001011101011010 (
b1010100 ,
1&
#1670
0&
#1680
b101001111101011000 !
b101001111101011000 (
b1010101 ,
1&
#1690
0&
#1700
b101010011101010110 !
b101010011101010110 (
b1010110 ,
1&
#1710
0&
#1720
b101010111101010100 !
b101010111101010100 (
b1010111 ,
1&
#1730
0&
#1740
b101011011101010010 !
b101011011101010010 (
b1011000 ,
1&
#1750
0&
#1760
b101011111101010000 !
b101011111101010000 (
b1011001 ,
1&
#1770
0&
#1780
b101100011101001110 !
b101100011101001110 (
b1011010 ,
1&
#1790
0&
#1800
b101100111101001100 !
b101100111101001100 (
b1011011 ,
1&
#1810
0&
#1820
b101101011101001010 !
b101101011101001010 (
b1011100 ,
1&
#1830
0&
#1840
b101101111101001000 !
b101101111101001000 (
b1011101 ,
1&
#1850
0&
#1860
b101110011101000110 !
b101110011101000110 (
b1011110 ,
1&
#1870
0&
#1880
b101110111101000100 !
b101110111101000100 (
b1011111 ,
1&
#1890
0&
#1900
b101111011101000010 !
b101111011101000010 (
b1100000 ,
1&
#1910
0&
#1920
b101111111101000000 !
b101111111101000000 (
b1100001 ,
1&
#1930
0&
#1940
b110000011100111110 !
b110000011100111110 (
b1100010 ,
1&
#1950
0&
#1960
b110000111100111100 !
b110000111100111100 (
b1100011 ,
1&
#1970
0&
#1980
b110001011100111010 !
b110001011100111010 (
b1100100 ,
1&
#1990
0&
#2000
b110001111100111000 !
b110001111100111000 (
b1100101 ,
1&
#2010
0&
#2020
b110010011100110110 !
b110010011100110110 (
b1100110 ,
1&
#2030
0&
#2040
b110010111100110100 !
b110010111100110100 (
b1100111 ,
1&
#2050
0&
#2060
b110011011100110010 !
b110011011100110010 (
b1101000 ,
1&
#2070
0&
#2080
b110011111100110000 !
b110011111100110000 (
b1101001 ,
1&
#2090
0&
#2100
b110100011100101110 !
b110100011100101110 (
b1101010 ,
1&
#2110
0&
#2120
b110100111100101100 !
b110100111100101100 (
b1101011 ,
1&
#2130
0&
#2140
b110101011100101010 !
b110101011100101010 (
b1101100 ,
1&
#2150
0&
#2160
b110101111100101000 !
b110101111100101000 (
b1101101 ,
1&
#2170
0&
#2180
b110110011100100110 !
b110110011100100110 (
b1101110 ,
1&
#2190
0&
#2200
b110110111100100100 !
b110110111100100100 (
b1101111 ,
1&
#2210
0&
#2220
b110111011100100010 !
b110111011100100010 (
b1110000 ,
1&
#2230
0&
#2240
b110111111100100000 !
b110111111100100000 (
b1110001 ,
1&
#2250
0&
#2260
b111000011100011110 !
b111000011100011110 (
b1110010 ,
1&
#2270
0&
#2280
b111000111100011100 !
b111000111100011100 (
b1110011 ,
1&
#2290
0&
#2300
b111001011100011010 !
b111001011100011010 (
b1110100 ,
1&
#2310
0&
#2320
b111001111100011000 !
b111001111100011000 (
b1110101 ,
1&
#2330
0&
#2340
b111010011100010110 !
b111010011100010110 (
b1110110 ,
1&
#2350
0&
#2360
b111010111100010100 !
b111010111100010100 (
b1110111 ,
1&
#2370
0&
#2380
b111011011100010010 !
b111011011100010010 (
b1111000 ,
1&
#2390
0&
#2400
b111011111100010000 !
b111011111100010000 (
b1111001 ,
1&
#2410
0&
#2420
b111100011100001110 !
b111100011100001110 (
b1111010 ,
1&
#2430
0&
#2440
b111100111100001100 !
b111100111100001100 (
b1111011 ,
1&
#2450
0&
#2460
b111101011100001010 !
b111101011100001010 (
b1111100 ,
1&
#2470
0&
#2480
b111101111100001000 !
b111101111100001000 (
b1111101 ,
1&
#2490
0&
#2500
b111110011100000110 !
b111110011100000110 (
b1111110 ,
1&
#2510
0&
#2520
b111110111100000100 !
b111110111100000100 (
b1111111 ,
1&
#2530
0&
#2540
b111111011100000010 !
b111111011100000010 (
b10000000 ,
1&
#2550
0&
#2560
b111111111100000000 !
b111111111100000000 (
b10000001 ,
1&
#2570
0&
#2580
b1000000011011111110 !
b1000000011011111110 (
b10000010 ,
1&
#2590
0&
#2600
b1000000111011111100 !
b1000000111011111100 (
b10000011 ,
1&
#2610
0&
#2620
b1000001011011111010 !
b1000001011011111010 (
b10000100 ,
1&
#2630
0&
#2640
b1000001111011111000 !
b1000001111011111000 (
b10000101 ,
1&
#2650
0&
#2660
b1000010011011110110 !
b1000010011011110110 (
b10000110 ,
1&
#2670
0&
#2680
b1000010111011110100 !
b1000010111011110100 (
b10000111 ,
1&
#2690
0&
#2700
b1000011011011110010 !
b1000011011011110010 (
b10001000 ,
1&
#2710
0&
#2720
b1000011111011110000 !
b1000011111011110000 (
b10001001 ,
1&
#2730
0&
#2740
b1000100011011101110 !
b1000100011011101110 (
b10001010 ,
1&
#2750
0&
#2760
b1000100111011101100 !
b1000100111011101100 (
b10001011 ,
1&
#2770
0&
#2780
b1000101011011101010 !
b1000101011011101010 (
b10001100 ,
1&
#2790
0&
#2800
b1000101111011101000 !
b1000101111011101000 (
b10001101 ,
1&
#2810
0&
#2820
b1000110011011100110 !
b1000110011011100110 (
b10001110 ,
1&
#2830
0&
#2840
b1000110111011100100 !
b1000110111011100100 (
b10001111 ,
1&
#2850
0&
#2860
b1000111011011100010 !
b1000111011011100010 (
b10010000 ,
1&
#2870
0&
#2880
b1000111111011100000 !
b1000111111011100000 (
b10010001 ,
1&
#2890
0&
#2900
b1001000011011011110 !
b1001000011011011110 (
b10010010 ,
1&
#2910
0&
#2920
b1001000111011011100 !
b1001000111011011100 (
b10010011 ,
1&
#2930
0&
#2940
b1001001011011011010 !
b1001001011011011010 (
b10010100 ,
1&
#2950
0&
#2960
b1001001111011011000 !
b1001001111011011000 (
b10010101 ,
1&
#2970
0&
#2980
b1001010011011010110 !
b1001010011011010110 (
b10010110 ,
1&
#2990
0&
#3000
b1001010111011010100 !
b1001010111011010100 (
b10010111 ,
1&
#3010
0&
#3020
b1001011011011010010 !
b1001011011011010010 (
b10011000 ,
1&
#3030
0&
#3040
b1001011111011010000 !
b1001011111011010000 (
b10011001 ,
1&
#3050
0&
#3060
b1001100011011001110 !
b1001100011011001110 (
b10011010 ,
1&
#3070
0&
#3080
b1001100111011001100 !
b1001100111011001100 (
b10011011 ,
1&
#3090
0&
#3100
b1001101011011001010 !
b1001101011011001010 (
b10011100 ,
1&
#3110
0&
#3120
b1001101111011001000 !
b1001101111011001000 (
b10011101 ,
1&
#3130
0&
#3140
b1001110011011000110 !
b1001110011011000110 (
b10011110 ,
1&
#3150
0&
#3160
b1001110111011000100 !
b1001110111011000100 (
b10011111 ,
1&
#3170
0&
#3180
b1001111011011000010 !
b1001111011011000010 (
b10100000 ,
1&
#3190
0&
#3200
b1001111111011000000 !
b1001111111011000000 (
b10100001 ,
1&
#3210
0&
#3220
b1010000011010111110 !
b1010000011010111110 (
b10100010 ,
1&
#3230
0&
#3240
b1010000111010111100 !
b1010000111010111100 (
b10100011 ,
1&
#3250
0&
#3260
b1010001011010111010 !
b1010001011010111010 (
b10100100 ,
1&
#3270
0&
#3280
b1010001111010111000 !
b1010001111010111000 (
b10100101 ,
1&
#3290
0&
#3300
b1010010011010110110 !
b1010010011010110110 (
b10100110 ,
1&
#3310
0&
#3320
b1010010111010110100 !
b1010010111010110100 (
b10100111 ,
1&
#3330
0&
#3340
b1010011011010110010 !
b1010011011010110010 (
b10101000 ,
1&
#3350
0&
#3360
b1010011111010110000 !
b1010011111010110000 (
b10101001 ,
1&
#3370
0&
#3380
b1010100011010101110 !
b1010100011010101110 (
b10101010 ,
1&
#3390
0&
#3400
b1010100111010101100 !
b1010100111010101100 (
b10101011 ,
1&
#3410
0&
#3420
b1010101011010101010 !
b1010101011010101010 (
b10101100 ,
1&
#3430
0&
#3440
b1010101111010101000 !
b1010101111010101000 (
b10101101 ,
1&
#3450
0&
#3460
b1010110011010100110 !
b1010110011010100110 (
b10101110 ,
1&
#3470
0&
#3480
b1010110111010100100 !
b1010110111010100100 (
b10101111 ,
1&
#3490
0&
#3500
b1010111011010100010 !
b1010111011010100010 (
b10110000 ,
1&
#3510
0&
#3520
b1010111111010100000 !
b1010111111010100000 (
b10110001 ,
1&
#3530
0&
#3540
b1011000011010011110 !
b1011000011010011110 (
b10110010 ,
1&
#3550
0&
#3560
b1011000111010011100 !
b1011000111010011100 (
b10110011 ,
1&
#3570
0&
#3580
b1011001011010011010 !
b1011001011010011010 (
b10110100 ,
1&
#3590
0&
#3600
b1011001111010011000 !
b1011001111010011000 (
b10110101 ,
1&
#3610
0&
#3620
b1011010011010010110 !
b1011010011010010110 (
b10110110 ,
1&
#3630
0&
#3640
b1011010111010010100 !
b1011010111010010100 (
b10110111 ,
1&
#3650
0&
#3660
b1011011011010010010 !
b1011011011010010010 (
b10111000 ,
1&
#3670
0&
#3680
b1011011111010010000 !
b1011011111010010000 (
b10111001 ,
1&
#3690
0&
#3700
b1011100011010001110 !
b1011100011010001110 (
b10111010 ,
1&
#3710
0&
#3720
b1011100111010001100 !
b1011100111010001100 (
b10111011 ,
1&
#3730
0&
#3740
b1011101011010001010 !
b1011101011010001010 (
b10111100 ,
1&
#3750
0&
#3760
b1011101111010001000 !
b1011101111010001000 (
b10111101 ,
1&
#3770
0&
#3780
b1011110011010000110 !
b1011110011010000110 (
b10111110 ,
1&
#3790
0&
#3800
b1011110111010000100 !
b1011110111010000100 (
b10111111 ,
1&
#3810
0&
#3820
b1011111011010000010 !
b1011111011010000010 (
b11000000 ,
1&
#3830
0&
#3840
b1011111111010000000 !
b1011111111010000000 (
b11000001 ,
1&
#3850
0&
#3860
b1100000011001111110 !
b1100000011001111110 (
b11000010 ,
1&
#3870
0&
#3880
b1100000111001111100 !
b1100000111001111100 (
b11000011 ,
1&
#3890
0&
#3900
b1100001011001111010 !
b1100001011001111010 (
b11000100 ,
1&
#3910
0&
#3920
b1100001111001111000 !
b1100001111001111000 (
b11000101 ,
1&
#3930
0&
#3940
b1100010011001110110 !
b1100010011001110110 (
b11000110 ,
1&
#3950
0&
#3960
b1100010111001110100 !
b1100010111001110100 (
b11000111 ,
1&
#3970
0&
#3980
b1100011011001110010 !
b1100011011001110010 (
b11001000 ,
1&
#3990
0&
#4000
b1100011111001110000 !
b1100011111001110000 (
b11001001 ,
1&
#4010
0&
#4020
b1100100011001101110 !
b1100100011001101110 (
b11001010 ,
1&
#4030
0&
#4040
b1100100111001101100 !
b1100100111001101100 (
b11001011 ,
1&
#4050
0&
#4060
b1100101011001101010 !
b1100101011001101010 (
b11001100 ,
1&
#4070
0&
#4080
b1100101111001101000 !
b1100101111001101000 (
b11001101 ,
1&
#4090
0&
#4100
b1100110011001100110 !
b1100110011001100110 (
b11001110 ,
1&
#4110
0&
#4120
b1100110111001100100 !
b1100110111001100100 (
b11001111 ,
1&
#4130
0&
#4140
b1100111011001100010 !
b1100111011001100010 (
b11010000 ,
1&
#4150
0&
#4160
b1100111111001100000 !
b1100111111001100000 (
b11010001 ,
1&
#4170
0&
#4180
b1101000011001011110 !
b1101000011001011110 (
b11010010 ,
1&
#4190
0&
#4200
b1101000111001011100 !
b1101000111001011100 (
b11010011 ,
1&
#4210
0&
#4220
b1101001011001011010 !
b1101001011001011010 (
b11010100 ,
1&
#4230
0&
#4240
b1101001111001011000 !
b1101001111001011000 (
b11010101 ,
1&
#4250
0&
#4260
b1101010011001010110 !
b1101010011001010110 (
b11010110 ,
1&
#4270
0&
#4280
b1101010111001010100 !
b1101010111001010100 (
b11010111 ,
1&
#4290
0&
#4300
b1101011011001010010 !
b1101011011001010010 (
b11011000 ,
1&
#4310
0&
#4320
b1101011111001010000 !
b1101011111001010000 (
b11011001 ,
1&
#4330
0&
#4340
b1101100011001001110 !
b1101100011001001110 (
b11011010 ,
1&
#4350
0&
#4360
b1101100111001001100 !
b1101100111001001100 (
b11011011 ,
1&
#4370
0&
#4380
b1101101011001001010 !
b1101101011001001010 (
b11011100 ,
1&
#4390
0&
#4400
b1101101111001001000 !
b1101101111001001000 (
b11011101 ,
1&
#4410
0&
#4420
b1101110011001000110 !
b1101110011001000110 (
b11011110 ,
1&
#4430
0&
#4440
b1101110111001000100 !
b1101110111001000100 (
b11011111 ,
1&
#4450
0&
#4460
b1101111011001000010 !
b1101111011001000010 (
b11100000 ,
1&
#4470
0&
#4480
b1101111111001000000 !
b1101111111001000000 (
b11100001 ,
1&
#4490
0&
#4500
b1110000011000111110 !
b1110000011000111110 (
b11100010 ,
1&
#4510
0&
#4520
b1110000111000111100 !
b1110000111000111100 (
b11100011 ,
1&
#4530
0&
#4540
b1110001011000111010 !
b1110001011000111010 (
b11100100 ,
1&
#4550
0&
#4560
b1110001111000111000 !
b1110001111000111000 (
b11100101 ,
1&
#4570
0&
#4580
b1110010011000110110 !
b1110010011000110110 (
b11100110 ,
1&
#4590
0&
#4600
b1110010111000110100 !
b1110010111000110100 (
b11100111 ,
1&
#4610
0&
#4620
b1110011011000110010 !
b1110011011000110010 (
b11101000 ,
1&
#4630
0&
#4640
b1110011111000110000 !
b1110011111000110000 (
b11101001 ,
1&
#4650
0&
#4660
b1110100011000101110 !
b1110100011000101110 (
b11101010 ,
1&
#4670
0&
#4680
b1110100111000101100 !
b1110100111000101100 (
b11101011 ,
1&
#4690
0&
#4700
b1110101011000101010 !
b1110101011000101010 (
b11101100 ,
1&
#4710
0&
#4720
b1110101111000101000 !
b1110101111000101000 (
b11101101 ,
1&
#4730
0&
#4740
b1110110011000100110 !
b1110110011000100110 (
b11101110 ,
1&
#4750
0&
#4760
b1110110111000100100 !
b1110110111000100100 (
b11101111 ,
1&
#4770
0&
#4780
b1110111011000100010 !
b1110111011000100010 (
b11110000 ,
1&
#4790
0&
#4800
b1110111111000100000 !
b1110111111000100000 (
b11110001 ,
1&
#4810
0&
#4820
b1111000011000011110 !
b1111000011000011110 (
b11110010 ,
1&
#4830
0&
#4840
b1111000111000011100 !
b1111000111000011100 (
b11110011 ,
1&
#4850
0&
#4860
b1111001011000011010 !
b1111001011000011010 (
b11110100 ,
1&
#4870
0&
#4880
b1111001111000011000 !
b1111001111000011000 (
b11110101 ,
1&
#4890
0&
#4900
b1111010011000010110 !
b1111010011000010110 (
b11110110 ,
1&
#4910
0&
#4920
b1111010111000010100 !
b1111010111000010100 (
b11110111 ,
1&
#4930
0&
#4940
b1111011011000010010 !
b1111011011000010010 (
b11111000 ,
1&
#4950
0&
#4960
b1111011111000010000 !
b1111011111000010000 (
b11111001 ,
1&
#4970
0&
#4980
b1111100011000001110 !
b1111100011000001110 (
b11111010 ,
1&
#4990
0&
#5000
b1111100111000001100 !
b1111100111000001100 (
b11111011 ,
1&
#5010
0&
#5020
b1111101011000001010 !
b1111101011000001010 (
b11111100 ,
1&
#5030
0&
#5040
b1111101111000001000 !
b1111101111000001000 (
b11111101 ,
1&
#5050
0&
#5060
b1111110011000000110 !
b1111110011000000110 (
b11111110 ,
1&
#5070
0&
#5080
b1111110111000000100 !
b1111110111000000100 (
b11111111 ,
1&
#5090
0&
#5100
b1111111011000000010 !
b1111111011000000010 (
b100000000 ,
1&
#5110
0&
#5120
b1111111111000000000 !
b1111111111000000000 (
b100000001 ,
1&
#5130
0&
#5140
b10000000010111111110 !
b10000000010111111110 (
b100000010 ,
1&
#5150
0&
#5160
b10000000110111111100 !
b10000000110111111100 (
b100000011 ,
1&
#5170
0&
#5180
b10000001010111111010 !
b10000001010111111010 (
b100000100 ,
1&
#5190
0&
#5200
b10000001110111111000 !
b10000001110111111000 (
b100000101 ,
1&
#5210
0&
#5220
b10000010010111110110 !
b10000010010111110110 (
b100000110 ,
1&
#5230
0&
#5240
b10000010110111110100 !
b10000010110111110100 (
b100000111 ,
1&
#5250
0&
#5260
b10000011010111110010 !
b10000011010111110010 (
b100001000 ,
1&
#5270
0&
#5280
b10000011110111110000 !
b10000011110111110000 (
b100001001 ,
1&
#5290
0&
#5300
b10000100010111101110 !
b10000100010111101110 (
b100001010 ,
1&
#5310
0&
#5320
b10000100110111101100 !
b10000100110111101100 (
b100001011 ,
1&
#5330
0&
#5340
b10000101010111101010 !
b10000101010111101010 (
b100001100 ,
1&
#5350
0&
#5360
b10000101110111101000 !
b10000101110111101000 (
b100001101 ,
1&
#5370
0&
#5380
b10000110010111100110 !
b10000110010111100110 (
b100001110 ,
1&
#5390
0&
#5400
b10000110110111100100 !
b10000110110111100100 (
b100001111 ,
1&
#5410
0&
#5420
b10000111010111100010 !
b10000111010111100010 (
b100010000 ,
1&
#5430
0&
#5440
b10000111110111100000 !
b10000111110111100000 (
b100010001 ,
1&
#5450
0&
#5460
b10001000010111011110 !
b10001000010111011110 (
b100010010 ,
1&
#5470
0&
#5480
b10001000110111011100 !
b10001000110111011100 (
b100010011 ,
1&
#5490
0&
#5500
b10001001010111011010 !
b10001001010111011010 (
b100010100 ,
1&
#5510
0&
#5520
b10001001110111011000 !
b10001001110111011000 (
b100010101 ,
1&
#5530
0&
#5540
b10001010010111010110 !
b10001010010111010110 (
b100010110 ,
1&
#5550
0&
#5560
b10001010110111010100 !
b10001010110111010100 (
b100010111 ,
1&
#5570
0&
#5580
b10001011010111010010 !
b10001011010111010010 (
b100011000 ,
1&
#5590
0&
#5600
b10001011110111010000 !
b10001011110111010000 (
b100011001 ,
1&
#5610
0&
#5620
b10001100010111001110 !
b10001100010111001110 (
b100011010 ,
1&
#5630
0&
#5640
b10001100110111001100 !
b10001100110111001100 (
b100011011 ,
1&
#5650
0&
#5660
b10001101010111001010 !
b10001101010111001010 (
b100011100 ,
1&
#5670
0&
#5680
b10001101110111001000 !
b10001101110111001000 (
b100011101 ,
1&
#5690
0&
#5700
b10001110010111000110 !
b10001110010111000110 (
b100011110 ,
1&
#5710
0&
