src/AC_MOTOR/AC_MOTOR.v
module AC_MOTOR(
	input CLK,
	input ENABLE,
	input CW,
	input CCW,
	//input [11:0] SINE,
	input [11:0] AMPLITUDE,
	input [11:0] FREQUENCY,
	input [11:0] ADC_CMP,
	input [11:0] ADC,
	output reg OUT1,
	output reg OUT2,
	output EN1,
	output EN2,	
	output reg ADC_LATCH);
	//
	parameter sine_samples = 64;
	parameter clock_div_max = sine_samples - 1;
	parameter bits = 12;
	parameter ctr_min = -2**(bits - 1);
	parameter ctr_max = 2**(bits - 1);
	//
	assign EN1 = ENABLE;
	assign EN2 = ENABLE;
	//
	reg [11:0] sine_index;
	reg [11:0] clock_div;
	reg [11:0] temp_frequency;
	reg [11:0] temp_amplitude;
	reg cw_temp;
	reg ccw_temp;
	reg signed [11:0] value_temp;
	reg [13:0] adc_cmp_temp;
	reg [11:0] adc_temp;
	reg en_adc;
	reg signed [bits-1:0] ctr;
	reg ctr_dir;
	reg [13:0] ctr_adc_latch;
	reg signed [bits-1:0] sine [sine_samples-1:0];
		initial begin
			sine[0] = 12'b000000000000; sine[1] = 12'b000011001011;
			sine[2] = 12'b000110010101; sine[3] = 12'b001001011011;
			sine[4] = 12'b001100011011; sine[5] = 12'b001111010011;
			sine[6] = 12'b010010000001; sine[7] = 12'b010100100100;
			sine[8] = 12'b010110111010; sine[9] = 12'b011001000001;
			sine[10] = 12'b011010111000; sine[11] = 12'b011100011110;
			sine[12] = 12'b011101110010; sine[13] = 12'b011110110011;
			sine[14] = 12'b011111100000; sine[15] = 12'b011111111010;
			sine[16] = 12'b011111111111; sine[17] = 12'b011111110000;
			sine[18] = 12'b011111001100; sine[19] = 12'b011110010101;
			sine[20] = 12'b011101001010; sine[21] = 12'b011011101101;
			sine[22] = 12'b011001111110; sine[23] = 12'b010111111111;
			sine[24] = 12'b010101110000; sine[25] = 12'b010011010100;
			sine[26] = 12'b010000101011; sine[27] = 12'b001101111000;
			sine[28] = 12'b001010111100; sine[29] = 12'b000111111001;
			sine[30] = 12'b000100110001; sine[31] = 12'b000001100110;
			sine[32] = 12'b111110011010; sine[33] = 12'b111011001111;
			sine[34] = 12'b111000000111; sine[35] = 12'b110101000100;
			sine[36] = 12'b110010001000; sine[37] = 12'b101111010101;
			sine[38] = 12'b101100101100; sine[39] = 12'b101010010000;
			sine[40] = 12'b101000000001; sine[41] = 12'b100110000010;
			sine[42] = 12'b100100010011; sine[43] = 12'b100010110110;
			sine[44] = 12'b100001101011; sine[45] = 12'b100000110100;
			sine[46] = 12'b100000010000; sine[47] = 12'b100000000001;
			sine[48] = 12'b100000000110; sine[49] = 12'b100000100000;
			sine[50] = 12'b100001001101; sine[51] = 12'b100010001110;
			sine[52] = 12'b100011100010; sine[53] = 12'b100101001000;
			sine[54] = 12'b100110111111; sine[55] = 12'b101001000110;
			sine[56] = 12'b101011011100; sine[57] = 12'b101101111111;
			sine[58] = 12'b110000101101; sine[59] = 12'b110011100101;
			sine[60] = 12'b110110100101; sine[61] = 12'b111001101011;
			sine[62] = 12'b111100110101; sine[63] = 12'b000000000000;
			clock_div <= 0;
			temp_frequency <= 2;
			temp_amplitude <= 1;
			sine_index <= 0;
			//
			OUT1 <= 0;
			OUT2 <= 0;
			ADC_LATCH <= 0;
			//
			cw_temp <= 1;
			ccw_temp <= 0;
			value_temp <= sine[0];
			adc_cmp_temp <= 0;
			adc_temp <= 0;
			en_adc <= 1;
			ctr <= 16383;
			ctr_dir <= 1;
			ctr_adc_latch <= 1;
		end
	//
	always @(posedge CLK) begin
		if (clock_div >= temp_frequency) begin
			clock_div <= 0;
			if (sine_index >= sine_samples - 1) begin
				sine_index <= 0;
				value_temp <= sine[0];
			end else begin
				sine_index <= sine_index + 1;
				value_temp <= sine[sine_index];
			end
		end else begin
			clock_div <= clock_div + 1;
		end
	
		if (ctr == ctr_max || ctr == ctr_min) begin
			cw_temp <= CW;
			ccw_temp <= CCW;
			temp_frequency <= FREQUENCY;
			temp_amplitude <= AMPLITUDE;
		end
		//
		if (ctr == ctr_max) ctr_dir <= 0;
		if (ctr == ctr_min) ctr_dir <= 1;
		//
		if (ctr_dir) ctr <= ctr + 1;
		else ctr <= ctr - 1;	
		//
		if (value_temp >= ctr) begin
			if (cw_temp && !ccw_temp) begin
				OUT1 <= 1;
				OUT2 <= 0;
				end
			//	
			if (!cw_temp && ccw_temp) begin
				OUT1 <= 0;
				OUT2 <= 1;
				end
			//
			end
		else begin
            if (cw_temp && !ccw_temp) begin
				OUT1 <= 0;
				OUT2 <= 1;
				end
			if (!cw_temp && ccw_temp) begin
				OUT1 <= 1;
				OUT2 <= 0;
				end
		end
	end
endmodule

src/AC_MOTOR/ICARUS_TB.v
`include "AC_MOTOR.v"
// http://verilogtutorial.blogspot.ch/2012/09/verilog-timescale-system-tasks.html
`timescale 10ns/1ns
//
module ICARUS_TB;
	//
	integer file;
	reg clk;
	reg enable;
	reg cw;
	reg ccw;
	reg [11:0] frequency;
	reg [11:0] amplitude;
	reg [11:0] adc_cmp;
	reg [11:0] adc;	
	wire out_1;
	wire out_2;
	wire en_1;
	wire en_2;
	wire adc_latch;
	//
	reg signed [14:0] value_in;
	wire cw_out;
	wire ccw_out;
	wire signed [11:0] value_out;
	wire signed [11:0] sin_val;
	//
	initial 
	begin
		clk <= 1;
		enable <= 1;
		cw <= 0;
		ccw <= 1;
		//
		amplitude <= 1;
		frequency <= 2;
		//
		adc_cmp <= 3000;
		adc <= 2500;
		//
		value_in <= 100;
		//
		$dumpfile("vcd/icarus_tb.vcd"); 
		$dumpvars(0, ICARUS_TB); 
		//
		// #300 value_in <= 20;
		// #300 value_in <= 30;
		// #300 value_in <= 15;
		// #300 value_in <= -15;
		// #300 value_in <= 5;
		// #300 value_in <= -150;
		// #100 value_in <= 100;
		
		
		//
		#125000 adc <= 4000;
		#10 adc <= 1000;
		//
		#25000 $finish; 
	end 
	//
	always #1 clk <= !clk;
	//
	AC_MOTOR ac_motor(
		clk,
		enable,
		cw,
		ccw,
		amplitude,
		frequency,
		adc_cmp,
		adc,
		out_1,
		out_2,
		en_1,
		en_2,
		adc_latch
		);
	//
endmodule
//

/*
cd D:\Dropbox\ABBTS_LABOR_DOZ\MOTION_CONTROL\FPGA\FPGA_MODUL_MAX1000_00_21\src\DC_MOTOR
C:\iverilog\bin\iverilog -s ICARUS_TB -o icarus_tb.o ICARUS_TB.v
C:\iverilog\bin\vvp icarus_tb.o

oder 

cd D:\Dropbox\ABBTS_LABOR_DOZ\MOTION_CONTROL\FPGA\FPGA_MODUL_MAX1000_SA_01_00\src\DC_MOTOR
D:\Dropbox\ABBTS_LABOR_DOZ\MOTION_CONTROL\FPGA\FPGA_MODUL_MAX1000_SA_01_00\icarus\iverilog\bin\iverilog -s ICARUS_TB -o icarus_tb.o ICARUS_TB.v
D:\Dropbox\ABBTS_LABOR_DOZ\MOTION_CONTROL\FPGA\FPGA_MODUL_MAX1000_SA_01_00\icarus\iverilog\bin\vvp icarus_tb.o
*/

src/AC_MOTOR/vcd/icarus_tb.vcd
$date
	Mon Nov 26 14:14:33 2018
$end
$version
	Icarus Verilog
$end
$timescale
	1ns
$end
$scope module ICARUS_TB $end
$var wire 1 ! out_2 $end
$var wire 1 " out_1 $end
$var wire 1 # en_2 $end
$var wire 1 $ en_1 $end
$var wire 1 % adc_latch $end
$var reg 12 & adc [11:0] $end
$var reg 12 ' adc_cmp [11:0] $end
$var reg 12 ( amplitude [11:0] $end
$var reg 1 ) ccw $end
$var reg 1 * clk $end
$var reg 1 + cw $end
$var reg 1 , enable $end
$var reg 12 - frequency [11:0] $end
$var reg 15 . value_in [14:0] $end
$scope module ac_motor $end
$var wire 12 / ADC [11:0] $end
$var wire 12 0 ADC_CMP [11:0] $end
$var wire 12 1 AMPLITUDE [11:0] $end
$var wire 1 ) CCW $end
$var wire 1 * CLK $end
$var wire 1 + CW $end
$var wire 1 $ EN1 $end
$var wire 1 # EN2 $end
$var wire 1 , ENABLE $end
$var wire 12 2 FREQUENCY [11:0] $end
$var reg 1 % ADC_LATCH $end
$var reg 1 " OUT1 $end
$var reg 1 ! OUT2 $end
$var reg 14 3 adc_cmp_temp [13:0] $end
$var reg 12 4 adc_temp [11:0] $end
$var reg 1 5 ccw_temp $end
$var reg 12 6 clock_div [11:0] $end
$var reg 12 7 ctr [11:0] $end
$var reg 14 8 ctr_adc_latch [13:0] $end
$var reg 1 9 ctr_dir $end
$var reg 1 : cw_temp $end
$var reg 1 ; en_adc $end
$var reg 12 < sine_index [11:0] $end
$var reg 12 = temp_amplitude [11:0] $end
$var reg 12 > temp_frequency [11:0] $end
$var reg 12 ? value_temp [11:0] $end
$upscope $end
$upscope $end
$enddefinitions $end
#0
$dumpvars
b0 ?
b10 >
b1 =
b0 <
1;
0:
19
b1 8
b0 7
b1 6
05
b0 4
b0 3
b10 2
b1 1
b101110111000 0
b100111000100 /
b1100100 .
b10 -
1,
0+
1*
1)
b1 (
b101110111000 '
b100111000100 &
0%
1$
1#
0"
0!
$end
#10
0*
#20
b1 7
b10 6
1*
#30
0*
#40
b10 7
b1 <
b0 6
1*
#50
0*
#60
b11 7
b1 6
1*
#70
0*
#80
b100 7
b10 6
1*
#90
0*
#100
b101 7
b11001011 ?
b10 <
b0 6
1*
#110
0*
#120
b110 7
b1 6
1*
#130
0*
#140
b111 7
b10 6
1*
#150
0*
#160
b1000 7
b110010101 ?
b11 <
b0 6
1*
#170
0*
#180
b1001 7
b1 6
1*
#190
0*
#200
b1010 7
b10 6
1*
#210
0*
#220
b1011 7
b1001011011 ?
b100 <
b0 6
1*
#230
0*
#240
b1100 7
b1 6
1*
#250
0*
#260
b1101 7
b10 6
1*
#270
0*
#280
b1110 7
b1100011011 ?
b101 <
b0 6
1*
#290
0*
#300
b1111 7
b1 6
1*
#310
0*
#320
b10000 7
b10 6
1*
#330
0*
#340
b10001 7
b1111010011 ?
b110 <
b0 6
1*
#350
0*
#360
b10010 7
b1 6
1*
#370
0*
#380
b10011 7
b10 6
1*
#390
0*
#400
b10100 7
b10010000001 ?
b111 <
b0 6
1*
#410
0*
#420
b10101 7
b1 6
1*
#430
0*
#440
b10110 7
b10 6
1*
#450
0*
#460
b10111 7
b10100100100 ?
b1000 <
b0 6
1*
#470
0*
#480
b11000 7
b1 6
1*
#490
0*
#500
b11001 7
b10 6
1*
#510
0*
#520
b11010 7
b10110111010 ?
b1001 <
b0 6
1*
#530
0*
#540
b11011 7
b1 6
1*
#550
0*
#560
b11100 7
b10 6
1*
#570
0*
#580
b11101 7
b11001000001 ?
b1010 <
b0 6
1*
#590
0*
#600
b11110 7
b1 6
1*
#610
0*
#620
b11111 7
b10 6
1*
#630
0*
#640
b100000 7
b11010111000 ?
b1011 <
b0 6
1*
#650
0*
#660
b100001 7
b1 6
1*
#670
0*
#680
b100010 7
b10 6
1*
#690
0*
#700
b100011 7
b11100011110 ?
b1100 <
b0 6
1*
#710
0*
#720
b100100 7
b1 6
1*
#730
0*
#740
b100101 7
b10 6
1*
#750
0*
#760
b100110 7
b11101110010 ?
b1101 <
b0 6
1*
#770
0*
#780
b100111 7
b1 6
1*
#790
0*
#800
b101000 7
b10 6
1*
#810
0*
#820
b101001 7
b11110110011 ?
b1110 <
b0 6
1*
#830
0*
#840
b101010 7
b1 6
1*
#850
0*
#860
b101011 7
b10 6
1*
#870
0*
#880
b101100 7
b11111100000 ?
b1111 <
b0 6
1*
#890
0*
#900
b101101 7
b1 6
1*
#910
0*
#920
b101110 7
b10 6
1*
#930
0*
#940
b101111 7
b11111111010 ?
b10000 <
b0 6
1*
#950
0*
#960
b110000 7
b1 6
1*
#970
0*
#980
b110001 7
b10 6
1*
#990
0*
#1000
b110010 7
b11111111111 ?
b10001 <
b0 6
1*
#1010
0*
#1020
b110011 7
b1 6
1*
#1030
0*
#1040
b110100 7
b10 6
1*
#1050
0*
#1060
b110101 7
b11111110000 ?
b10010 <
b0 6
1*
#1070
0*
#1080
b110110 7
b1 6
1*
#1090
0*
#1100
b110111 7
b10 6
1*
#1110
0*
#1120
b111000 7
b11111001100 ?
b10011 <
b0 6
1*
#1130
0*
#1140
b111001 7
b1 6
1*
#1150
0*
#1160
b111010 7
b10 6
1*
#1170
0*
#1180
b111011 7
b11110010101 ?
b10100 <
b0 6
1*
#1190
0*
#1200
b111100 7
b1 6
1*
#1210
0*
#1220
b111101 7
b10 6
1*
#1230
0*
#1240
b111110 7
b11101001010 ?
b10101 <
b0 6
1*
#1250
0*
#1260
b111111 7
b1 6
1*
#1270
0*
#1280
b1000000 7
b10 6
1*
#1290
0*
#1300
b1000001 7
b11011101101 ?
b10110 <
b0 6
1*
#1310
0*
#1320
b1000010 7
b1 6
1*
#1330
0*
#1340
b1000011 7
b10 6
1*
#1350
0*
#1360
b1000100 7
b11001111110 ?
b10111 <
b0 6
1*
#1370
0*
#1380
b1000101 7
b1 6
1*
#1390
0*
#1400
b1000110 7
b10 6
1*
#1410
0*
#1420
b1000111 7
b10111111111 ?
b11000 <
b0 6
1*
#1430
0*
#1440
b1001000 7
b1 6
1*
#1450
0*
#1460
b1001001 7
b10 6
1*
#1470
0*
#1480
b1001010 7
b10101110000 ?
b11001 <
b0 6
1*
#1490
0*
#1500
b1001011 7
b1 6
1*
#1510
0*
#1520
b1001100 7
b10 6
1*
#1530
0*
#1540
b1001101 7
b10011010100 ?
b11010 <
b0 6
1*
#1550
0*
#1560
b1001110 7
b1 6
1*
#1570
0*
#1580
b1001111 7
b10 6
1*
#1590
0*
#1600
b1010000 7
b10000101011 ?
b11011 <
b0 6
1*
#1610
0*
#1620
b1010001 7
b1 6
1*
#1630
0*
#1640
b1010010 7
b10 6
1*
#1650
0*
#1660
b1010011 7
b1101111000 ?
b11100 <
b0 6
1*
#1670
0*
#1680
b1010100 7
b1 6
1*
#1690
0*
#1700
b1010101 7
b10 6
1*
#1710
0*
#1720
b1010110 7
b1010111100 ?
b11101 <
b0 6
1*
#1730
0*
#1740
b1010111 7
b1 6
1*
#1750
0*
#1760
b1011000 7
b10 6
1*
#1770
0*
#1780
b1011001 7
b111111001 ?
b11110 <
b0 6
1*
#1790
0*
#1800
b1011010 7
b1 6
1*
#1810
0*
#1820
b1011011 7
b10 6
1*
#1830
0*
#1840
b1011100 7
b100110001 ?
b11111 <
b0 6
1*
#1850
0*
#1860
b1011101 7
b1 6
1*
#1870
0*
#1880
b1011110 7
b10 6
1*
#1890
0*
#1900
b1011111 7
b1100110 ?
b100000 <
b0 6
1*
#1910
0*
#1920
b1100000 7
b1 6
1*
#1930
0*
#1940
b1100001 7
b10 6
1*
#1950
0*
#1960
b1100010 7
b111110011010 ?
b100001 <
b0 6
1*
#1970
0*
#1980
b1100011 7
b1 6
1*
#1990
0*
#2000
b1100100 7
b10 6
1*
#2010
0*
#2020
b1100101 7
b111011001111 ?
b100010 <
b0 6
1*
#2030
0*
#2040
b1100110 7
b1 6
1*
#2050
0*
#2060
b1100111 7
b10 6
1*
#2070
0*
#2080
b1101000 7
b111000000111 ?
b100011 <
b0 6
1*
#2090
0*
#2100
b1101001 7
b1 6
1*
#2110
0*
#2120
b1101010 7
b10 6
1*
#2130
0*
#2140
b1101011 7
b110101000100 ?
b100100 <
b0 6
1*
#2150
0*
#2160
b1101100 7
b1 6
1*
#2170
0*
#2180
b1101101 7
b10 6
1*
#2190
0*
#2200
b1101110 7
b110010001000 ?
b100101 <
b0 6
1*
#2210
0*
#2220
b1101111 7
b1 6
1*
#2230
0*
#2240
b1110000 7
b10 6
1*
#2250
0*
#2260
b1110001 7
b101111010101 ?
b100110 <
b0 6
1*
#2270
0*
#2280
b1110010 7
b1 6
1*
#2290
0*
#2300
b1110011 7
b10 6
1*
#2310
0*
#2320
b1110100 7
b101100101100 ?
b100111 <
b0 6
1*
#2330
0*
#2340
b1110101 7
b1 6
1*
#2350
0*
#2360
b1110110 7
b10 6
1*
#2370
0*
#2380
b1110111 7
b101010010000 ?
b101000 <
b0 6
1*
#2390
0*
#2400
b1111000 7
b1 6
1*
#2410
0*
#2420
b1111001 7
b10 6
1*
#2430
0*
#2440
b1111010 7
b101000000001 ?
b101001 <
b0 6
1*
#2450
0*
#2460
b1111011 7
b1 6
1*
#2470
0*
#2480
b1111100 7
b10 6
1*
#2490
0*
#2500
b1111101 7
b100110000010 ?
b101010 <
b0 6
1*
#2510
0*
#2520
b1111110 7
b1 6
1*
#2530
0*
#2540
b1111111 7
b10 6
1*
#2550
0*
#2560
b10000000 7
b100100010011 ?
b101011 <
b0 6
1*
#2570
0*
#2580
b10000001 7
b1 6
1*
#2590
0*
#2600
b10000010 7
b10 6
1*
#2610
0*
#2620
b10000011 7
b100010110110 ?
b101100 <
b0 6
1*
#2630
0*
#2640
b10000100 7
b1 6
1*
#2650
0*
#2660
b10000101 7
b10 6
1*
#2670
0*
#2680
b10000110 7
b100001101011 ?
b101101 <
b0 6
1*
#2690
0*
#2700
b10000111 7
b1 6
1*
#2710
0*
#2720
b10001000 7
b10 6
1*
#2730
0*
#2740
b10001001 7
b100000110100 ?
b101110 <
b0 6
1*
#2750
0*
#2760
b10001010 7
b1 6
1*
#2770
0*
#2780
b10001011 7
b10 6
1*
#2790
0*
#2800
b10001100 7
b100000010000 ?
b101111 <
b0 6
1*
#2810
0*
#2820
b10001101 7
b1 6
1*
#2830
0*
#2840
b10001110 7
b10 6
1*
#2850
0*
#2860
b10001111 7
b100000000001 ?
b110000 <
b0 6
1*
#2870
0*
#2880
b10010000 7
b1 6
1*
#2890
0*
#2900
b10010001 7
b10 6
1*
#2910
0*
#2920
b10010010 7
b100000000110 ?
b110001 <
b0 6
1*
#2930
0*
#2940
b10010011 7
b1 6
1*
#2950
0*
#2960
b10010100 7
b10 6
1*
#2970
0*
#2980
b10010101 7
b100000100000 ?
b110010 <
b0 6
1*
#2990
0*
#3000
b10010110 7
b1 6
1*
#3010
0*
#3020
b10010111 7
b10 6
1*
#3030
0*
#3040
b10011000 7
b100001001101 ?
b110011 <
b0 6
1*
#3050
0*
#3060
b10011001 7
b1 6
1*
#3070
0*
#3080
b10011010 7
b10 6
1*
#3090
0*
#3100
b10011011 7
b100010001110 ?
b110100 <
b0 6
1*
#3110
0*
#3120
b10011100 7
b1 6
1*
#3130
0*
#3140
b10011101 7
b10 6
1*
#3150
0*
#3160
b10011110 7
b100011100010 ?
b110101 <
b0 6
1*
#3170
0*
#3180
b10011111 7
b1 6
1*
#3190
0*
#3200
b10100000 7
b10 6
1*
#3210
0*
#3220
b10100001 7
b100101001000 ?
b110110 <
b0 6
1*
#3230
0*
#3240
b10100010 7
b1 6
1*
#3250
0*
#3260
b10100011 7
b10 6
1*
#3270
0*
#3280
b10100100 7
b100110111111 ?
b110111 <
b0 6
1*
#3290
0*
#3300
b10100101 7
b1 6
1*
#3310
0*
#3320
b10100110 7
b10 6
1*
#3330
0*
#3340
b10100111 7
b101001000110 ?
b111000 <
b0 6
1*
#3350
0*
#3360
b10101000 7
b1 6
1*
#3370
0*
#3380
b10101001 7
b10 6
1*
#3390
0*
#3400
b10101010 7
b101011011100 ?
b111001 <
b0 6
1*
#3410
0*
#3420
b10101011 7
b1 6
1*
#3430
0*
#3440
b10101100 7
b10 6
1*
#3450
0*
#3460
b10101101 7
b101101111111 ?
b111010 <
b0 6
1*
#3470
0*
#3480
b10101110 7
b1 6
1*
#3490
0*
#3500
b10101111 7
b10 6
1*
#3510
0*
#3520
b10110000 7
b110000101101 ?
b111011 <
b0 6
1*
#3530
0*
#3540
b10110001 7
b1 6
1*
#3550
0*
#3560
b10110010 7
b10 6
1*
#3570
0*
#3580
b10110011 7
b110011100101 ?
b111100 <
b0 6
1*
#3590
0*
#3600
b10110100 7
b1 6
1*
#3610
0*
#3620
b10110101 7
b10 6
1*
#3630
0*
#3640
b10110110 7
b110110100101 ?
b111101 <
b0 6
1*
#3650
0*
#3660
b10110111 7
b1 6
1*
#3670
0*
#3680
b10111000 7
b10 6
1*
#3690
0*
#3700
b10111001 7
b111001101011 ?
b111110 <
b0 6
1*
#3710
0*
#3720
b10111010 7
b1 6
1*
#3730
0*
#3740
b10111011 7
b10 6
1*
#3750
0*
#3760
b10111100 7
b111100110101 ?
b111111 <
b0 6
1*
#3770
0*
#3780
b10111101 7
b1 6
1*
#3790
0*
#3800
b10111110 7
b10 6
1*
#3810
0*
#3820
b10111111 7
b0 ?
b0 <
b0 6
1*
#3830
0*
#3840
b11000000 7
b1 6
1*
#3850
0*
#3860
b11000001 7
b10 6
1*
#3870
0*
#3880
b11000010 7
b1 <
b0 6
1*
#3890
0*
#3900
b11000011 7
b1 6
1*
#3910
0*
#3920
b11000100 7
b10 6
1*
#3930
0*
#3940
b11000101 7
b11001011 ?
b10 <
b0 6
1*
#3950
0*
#3960
b11000110 7
b1 6
1*
#3970
0*
#3980
b11000111 7
b10 6
1*
#3990
0*
#4000
b11001000 7
b110010101 ?
b11 <
b0 6
1*
#4010
0*
#4020
b11001001 7
b1 6
1*
#4030
0*
#4040
b11001010 7
b10 6
1*
#4050
0*
#4060
b11001011 7
b1001011011 ?
b100 <
b0 6
1*
#4070
0*
#4080
b11001100 7
b1 6
1*
#4090
0*
#4100
b11001101 7
b10 6
1*
#4110
0*
#4120
b11001110 7
b1100011011 ?
b101 <
b0 6
1*
#4130
0*
#4140
b11001111 7
b1 6
1*
#4150
0*
#4160
b11010000 7
b10 6
1*
#4170
0*
#4180
b11010001 7
b1111010011 ?
b110 <
b0 6
1*
#4190
0*
#4200
b11010010 7
b1 6
1*
#4210
0*
#4220
b11010011 7
b10 6
1*
#4230
0*
#4240
b11010100 7
b10010000001 ?
b111 <
b0 6
1*
#4250
0*
#4260
b11010101 7
b1 6
1*
#4270
0*
#4280
b11010110 7
b10 6
1*
#4290
0*
#4300
b11010111 7
b10100100100 ?
b1000 <
b0 6
1*
#4310
0*
#4320
b11011000 7
b1 6
1*
#4330
0*
#4340
b11011001 7
b10 6
1*
#4350
0*
#4360
b11011010 7
b10110111010 ?
b1001 <
b0 6
1*
#4370
0*
#4380
b11011011 7
b1 6
1*
#4390
0*
#4400
b11011100 7
b10 6
1*
#4410
0*
#4420
b11011101 7
b11001000001 ?
b1010 <
b0 6
1*
#4430
0*
#4440
b11011110 7
b1 6
1*
#4450
0*
#4460
b11011111 7
b10 6
1*
#4470
0*
#4480
b11100000 7
b11010111000 ?
b1011 <
b0 6
1*
#4490
0*
#4500
b11100001 7
b1 6
1*
#4510
0*
#4520
b11100010 7
b10 6
1*
#4530
0*
#4540
b11100011 7
b11100011110 ?
b1100 <
b0 6
1*
#4550
0*
#4560
b11100100 7
b1 6
1*
#4570
0*
#4580
b11100101 7
b10 6
1*
#4590
0*
#4600
b11100110 7
b11101110010 ?
b1101 <
b0 6
1*
#4610
0*
#4620
b11100111 7
b1 6
1*
#4630
0*
#4640
b11101000 7
b10 6
1*
#4650
0*
#4660
b11101001 7
b11110110011 ?
b1110 <
b0 6
1*
#4670
0*
#4680
b11101010 7
b1 6
1*
#4690
0*
#4700
b11101011 7
b10 6
1*
#4710
0*
#4720
b11101100 7
b11111100000 ?
b1111 <
b0 6
1*
#4730
0*
#4740
b11101101 7
b1 6
1*
#4750
0*
#4760
b11101110 7
b10 6
1*
#4770
0*
#4780
b11101111 7
b11111111010 ?
b10000 <
b0 6
1*
#4790
0*
#4800
b11110000 7
b1 6
1*
#4810
0*
#4820
b11110001 7
b10 6
1*
#4830
0*
#4840
b11110010 7
b11111111111 ?
b10001 <
b0 6
1*
#4850
0*
#4860
b11110011 7
b1 6
1*
#4870
0*
#4880
b11110100 7
b10 6
1*
#4890
0*
#4900
b11110101 7
b11111110000 ?
b10010 <
b0 6
1*
#4910
0*
#4920
b11110110 7
b1 6
1*
#4930
0*
#4940
b11110111 7
b10 6
1*
#4950
0*
#4960
b11111000 7
b11111001100 ?
b10011 <
b0 6
1*
#4970
0*
#4980
b11111001 7
b1 6
1*
#4990
0*
#5000
b11111010 7
b10 6
1*
#5010
0*
#5020
b11111011 7
b11110010101 ?
b10100 <
b0 6
1*
#5030
0*
#5040
b11111100 7
b1 6
1*
#5050
0*
#5060
b11111101 7
b10 6
1*
#5070
0*
#5080
b11111110 7
b11101001010 ?
b10101 <
b0 6
1*
#5090
0*
#5100
b11111111 7
b1 6
1*
#5110
0*
#5120
b100000000 7
b10 6
1*
#5130
0*
#5140
b100000001 7
b11011101101 ?
b10110 <
b0 6
1*
#5150
0*
#5160
b100000010 7
b1 6
1*
#5170
0*
#5180
b100000011 7
b10 6
1*
#5190
0*
#5200
b100000100 7
b11001111110 ?
b10111 <
b0 6
1*
#5210
0*
#5220
b100000101 7
b1 6
1*
#5230
0*
#5240
b100000110 7
b10 6
1*
#5250
0*
#5260
b100000111 7
b10111111111 ?
b11000 <
b0 6
1*
#5270
0*
#5280
b100001000 7
b1 6
1*
#5290
0*
#5300
b100001001 7
b10 6
1*
#5310
0*
#5320
b100001010 7
b10101110000 ?
b11001 <
b0 6
1*
#5330
0*
#5340
b100001011 7
b1 6
1*
#5350
0*
#5360
b100001100 7
b10 6
1*
#5370
0*
#5380
b100001101 7
b10011010100 ?
b11010 <
b0 6
1*
#5390
0*
#5400
b100001110 7
b1 6
1*
#5410
0*
#5420
b100001111 7
b10 6
1*
#5430
0*
#5440
b100010000 7
b10000101011 ?
b11011 <
b0 6
1*
#5450
0*
#5460
b100010001 7
b1 6
1*
#5470
0*
#5480
b100010010 7
b10 6
1*
#5490
0*
#5500
b100010011 7
b1101111000 ?
b11100 <
b0 6
1*
#5510
0*
#5520
b100010100 7
b1 6
1*
#5530
0*
#5540
b100010101 7
b10 6
1*
#5550
0*
#5560
b100010110 7
b1010111100 ?
b11101 <
b0 6
1*
#5570
0*
#5580
b100010111 7
b1 6
1*
#5590
0*
#5600
b100011000 7
b10 6
1*
#5610
0*
#5620
b100011001 7
b111111001 ?
b11110 <
b0 6
1*
#5630
0*
#5640
b100011010 7
b1 6
1*
#5650
0*
#5660
b100011011 7
b10 6
1*
#5670
0*
#5680
b100011100 7
b100110001 ?
b11111 <
b0 6
1*
#5690
0*
#5700
b100011101 7
b1 6
1*
#5710
0*
#5720
b100011110 7
b10 6
1*
#5730
0*
#5740
b100011111 7
b1100110 ?
b100000 <
b0 6
1*
#5750
0*
#5760
b100100000 7
b1 6
1*
#5770
0*
#5780
b100100001 7
b10 6
1*
#5790
0*
#5800
b100100010 7
b111110011010 ?
b100001 <
b0 6
1*
#5810
0*
#5820
b100100011 7
b1 6
1*
#5830
0*
#5840
b100100100 7
b10 6
1*
#5850
0*
#5860
b100100101 7
b111011001111 ?
b100010 <
b0 6
1*
#5870
0*
#5880
b100100110 7
b1 6
1*
#5890
0*
#5900
b100100111 7
b10 6
1*
#5910
0*
#5920
b100101000 7
b111000000111 ?
b100011 <
b0 6
1*
#5930
0*
#5940
b100101001 7
b1 6
1*
#5950
0*
#5960
b100101010 7
b10 6
1*
#5970
0*
#5980
b100101011 7
b110101000100 ?
b100100 <
b0 6
1*
#5990
0*
#6000
b100101100 7
b1 6
1*
#6010
0*
#6020
b100101101 7
b10 6
1*
#6030
0*
#6040
b100101110 7
b110010001000 ?
b100101 <
b0 6
1*
#6050
0*
#6060
b100101111 7
b1 6
1*
#6070
0*
#6080
b100110000 7
b10 6
1*
#6090
0*
#6100
b100110001 7
b101111010101 ?
b100110 <
b0 6
1*
#6110
0*
#6120
b100110010 7
b1 6
1*
#6130
0*
#6140
b100110011 7
b10 6
1*
#6150
0*
#6160
b100110100 7
b101100101100 ?
b100111 <
b0 6
1*
#6170
0*
#6180
b100110101 7
b1 6
1*
#6190
0*
#6200
b100110110 7
b10 6
1*
#6210
0*
#6220
b100110111 7
b101010010000 ?
b101000 <
b0 6
1*
#6230
0*
#6240
b100111000 7
b1 6
1*
#6250
0*
#6260
b100111001 7
b10 6
1*
#6270
0*
#6280
b100111010 7
b101000000001 ?
b101001 <
b0 6
1*
#6290
0*
#6300
b100111011 7
b1 6
1*
#6310
0*
#6320
b100111100 7
b10 6
1*
#6330
0*
#6340
b100111101 7
b100110000010 ?
b101010 <
b0 6
1*
#6350
0*
#6360
b100111110 7
b1 6
1*
#6370
0*
#6380
b100111111 7
b10 6
1*
#6390
0*
#6400
b101000000 7
b100100010011 ?
b101011 <
b0 6
1*
#6410
0*
#6420
b101000001 7
b1 6
1*
#6430
0*
#6440
b101000010 7
b10 6
1*
#6450
0*
#6460
b101000011 7
b100010110110 ?
b101100 <
b0 6
1*
#6470
0*
#6480
b101000100 7
b1 6
1*
#6490
0*
#6500
b101000101 7
b10 6
1*
#6510
0*
#6520
b101000110 7
b100001101011 ?
b101101 <
b0 6
1*
#6530
0*
#6540
b101000111 7
b1 6
1*
#6550
0*
#6560
b101001000 7
b10 6
1*
#6570
0*
#6580
b101001001 7
b100000110100 ?
b101110 <
b0 6
1*
#6590
0*
#6600
b101001010 7
b1 6
1*
#6610
0*
#6620
b101001011 7
b10 6
1*
#6630
0*
#6640
b101001100 7
b100000010000 ?
b101111 <
b0 6
1*
#6650
0*
#6660
b101001101 7
b1 6
1*
#6670
0*
#6680
b101001110 7
b10 6
1*
#6690
0*
#6700
b101001111 7
b100000000001 ?
b110000 <
b0 6
1*
#6710
0*
#6720
b101010000 7
b1 6
1*
#6730
0*
#6740
b101010001 7
b10 6
1*
#6750
0*
#6760
b101010010 7
b100000000110 ?
b110001 <
b0 6
1*
#6770
0*
#6780
b101010011 7
b1 6
1*
#6790
0*
#6800
b101010100 7
b10 6
1*
#6810
0*
#6820
b101010101 7
b100000100000 ?
b110010 <
b0 6
1*
#6830
0*
#6840
b101010110 7
b1 6
1*
#6850
0*
#6860
b101010111 7
b10 6
1*
#6870
0*
