src/APP_IO_EXPANDER/CLIENT_MCP23S17/CLIENT_MCP23S17.v
// SPI Treiber für die IO-Expander MCP23S17
// \_toolchain\datasheets\MCP23S17.pdf
module CLIENT_MCP23S17(
	input CLK,
	input SPI_MISO,
	input [15:0] IO16_D,
	output wire SPI_CS,
	output wire SPI_CLK,
	output wire SPI_MOSI,
	output reg [15:0] IO16_SW
	);
	//
	// Registerdefinition MCP23S17
	localparam IODIRA    = 8'h00; //Data Direction Register for PORTA   
	localparam IODIRB    = 8'h01; //Data Direction Register for PORTB
	localparam IPOLA     = 8'h02; //Input Polarity Register for PORTA
	localparam IPOLB     = 8'h03; //Input Polarity Register for PORTB
	localparam GPINTENA  = 8'h04; //Interrupt-on-change enable Register for PORTA
	localparam GPINTENB  = 8'h05; //Interrupt-on-change enable Register for PORTB
	localparam DEFVALA   = 8'h06; //Default Value Register for PORTA   
	localparam DEFVALB   = 8'h07; //Default Value Register for PORTB     
	localparam INTCONA   = 8'h08; //Interrupt-on-change control Register for PORTA 
	localparam INTCONB   = 8'h09; //Interrupt-on-change control Register for PORTB     
	localparam IOCON     = 8'h0A; //Configuration register for device                     
	localparam GPPUA     = 8'h0C; //100kOhm pullup resistor register for PORTA (sets pin to input when set)   
	localparam GPPUB     = 8'h0D; //100kOhm pullup resistor register for PORTB (sets pin to input when set)     
	localparam INTFA     = 8'h0E; //Interrupt flag Register for PORTA       
	localparam INTFB     = 8'h0F; //Interrupt flag Register for PORTB   
	localparam INTCAPA   = 8'h10; //Interrupt captured value Register for PORTA 
	localparam INTCAPB   = 8'h11; //Interrupt captured value Register for PORTB   
	localparam GPIOA     = 8'h12; //General purpose I/O Register for PORTA 
	localparam GPIOB     = 8'h13; //General purpose I/O Register for PORTB
	localparam OLATA     = 8'h14; //Output latch Register for PORTA
	localparam OLATB     = 8'h15; //Output latch Register for PORTB  	
	//
	// Read Write U1 und U2
	localparam R_U1 = 8'h4B;// 0x4B Adresse 5
	localparam W_U1 = 8'h4A;// 0x4A Adresse 5
	localparam R_U2 = 8'h4D;// 0x4D Adresse 6
	localparam W_U2 = 8'h4C;// 0x4C Adresse 6 
	//
	//localparam INIT = 3'd0;
	//
	reg [4:0] state;
	reg start;
	wire [23:0] data_in;
	reg [23:0] data_out;
	reg [15:0] counter;
	wire done;
	reg hri1; reg hri2; reg hri3; reg hri4; reg hri5; reg hri6;
	wire done_re; wire done_fe;
	//
	assign done_re = (hri1 && !hri2);
	assign done_fe = (!hri1 && hri2);
	//
	SPI_INP_FILTER_CLIENT spi_inp_filter_miso(CLK, SPI_MISO, spi_miso_filter); 
	defparam spi_inp_filter_miso.FILTER = 5'd2;
	SHIFTER_24_BIT shifter_24_bit(CLK, start, spi_miso_filter, data_out, done, SPI_CS, SPI_CLK, SPI_MOSI, data_in); 
	defparam shifter_24_bit.CLK_COUNTER = 5'd50;// 500kHz
	//
	initial
	begin
		//
		counter <= 0;
		state <= 0;
		data_out <= 0;
		start <= 0;
		hri1 <= 0; hri2 <= 0; hri3 <= 0; hri4 <= 0; hri5 <= 0; hri6 <= 0;
	end
	//
	
	//
	always @(posedge CLK)
	begin
	//
	hri1 <= done;
	hri2 <= hri1;
	//
	if (state == 0)
		begin
		start <= 0;
		state <= state + 1;
		end
	//
	if (state == 1)
		begin
		counter <= counter + 1;
		if (counter > 1000)
			begin
			counter <= 0;
			state <= state + 1;
			end
		end
	//
	if (state == 2) /* sequential operation mode disabled, address mode enabled */
	begin
		data_out[23:16] <= 8'h40; data_out[15:08] <= IOCON;	data_out[07:00] <= 8'h28;
		start <= 1;
		if (done_re) state <= state + 1;
	end
	//
	if (state == 3) begin start <= 0; state <= state + 1; end
	//
	if (state == 4) /* sequential operation mode disabled, address mode enabled */
	begin
		data_out[23:16] <= W_U1; data_out[15:08] <= IOCON;	data_out[07:00] <= 8'h28;
		start <= 1;
		if (done_re) state <= state + 1;
	end
	//
	if (state == 5) begin start <= 0; state <= state + 1; end
	//
	if (state == 6) /* sequential operation mode disabled, address mode enabled */
	begin
		data_out[23:16] <= W_U2; data_out[15:08] <= IOCON;	data_out[07:00] <= 8'h28;
		start <= 1;
		if (done_re) state <= state + 1;
	end
	//
	if (state == 7) begin start <= 0; state <= state + 1; end
	//
	if (state == 8) /* 1 = GPIO register bit will reflect the opposite logic state of the input pin. 0 = GPIO register bit will reflect the same logic state of the input pin. */
	begin
		data_out[23:16] <= W_U1; data_out[15:08] <= IPOLA;	data_out[07:00] <= 8'hFF;
		start <= 1;
		if (done_re) state <= state + 1;
	end
	//
	if (state == 9) begin start <= 0; state <= state + 1; end
	//
	if (state == 10) /* 1 = GPIO register bit will reflect the opposite logic state of the input pin. 0 = GPIO register bit will reflect the same logic state of the input pin. */
	begin
		data_out[23:16] <= W_U2; data_out[15:08] <= IPOLA;	data_out[07:00] <= 8'hFF;
		start <= 1;
		if (done_re) state <= state + 1;
	end
	//
	if (state == 11) begin start <= 0; state <= state + 1; end
	//
	if (state == 12) /* direction PORT A, 0 = OUTPUT, 1 = INPUT */
	begin
		data_out[23:16] <= W_U1; data_out[15:08] <= IODIRA;	data_out[07:00] <= 8'hFF;
		start <= 1;
		if (done_re) state <= state + 1;
	end
	//
	if (state == 13) begin start <= 0; state <= state + 1; end
	//
	if (state == 14) /* direction PORT B, 0 = OUTPUT, 1 = INPUT */
	begin
		data_out[23:16] <= W_U1; data_out[15:08] <= IODIRB;	data_out[07:00] <= 8'h00;
		start <= 1;
		if (done_re) state <= state + 1;
	end
	//
	if (state == 15) begin start <= 0; state <= state + 1; end
	//
	if (state == 16) /* direction PORT A, 0 = OUTPUT, 1 = INPUT */
	begin
		data_out[23:16] <= W_U2; data_out[15:08] <= IODIRA;	data_out[07:00] <= 8'hFF;
		start <= 1;
		if (done_re) state <= state + 1;
	end
	//
	if (state == 17) begin start <= 0; state <= state + 1; end
	//
	if (state == 18) /* direction PORT B, 0 = OUTPUT, 1 = INPUT */
	begin
		data_out[23:16] <= W_U2; data_out[15:08] <= IODIRB;	data_out[07:00] <= 8'h00;
		start <= 1;
		if (done_re) state <= state + 1;
	end
	//
	////////////////////////////////////////////////	
	if (state == 19) begin start <= 0; state <= state + 1; end
	//
	if (state == 20) /* read INPUTS */
	begin
		data_out[23:16] <= R_U1; data_out[15:08] <= GPIOA;	data_out[07:00] <= 8'hFF;
		IO16_SW[7:0] <= data_in[07:00];
		start <= 1;
		if (done_re) state <= state + 1;
	end
	//
	if (state == 21) begin start <= 0; state <= state + 1; end
	//
	if (state == 22) /* write OUTPUTS */
	begin
		data_out[23:16] <= W_U1; data_out[15:08] <= GPIOB;	data_out[07:00] <= IO16_D[7:0];
		start <= 1;
		if (done_re) state <= state + 1;
	end
	////////////////////////////////////////////////	
	if (state == 23) begin start <= 0; state <= state + 1; end
	//
	if (state == 24) /* read INPUTS */
	begin
		data_out[23:16] <= R_U2; data_out[15:08] <= GPIOA;	data_out[07:00] <= 8'hFF;
		IO16_SW[15:8] <= data_in[07:00];
		start <= 1;
		if (done_re) state <= state + 1;
	end
	//	
	if (state == 25) begin start <= 0; state <= state + 1; end
	//
	if (state == 26) /* write OUTPUTS */
	begin
		data_out[23:16] <= W_U2; data_out[15:08] <= GPIOB;	data_out[07:00] <= IO16_D[15:8];
		start <= 1;
		if (done_re) state <= 19;
	end
	////////////////////////////////////////////////		
	end
endmodule
////////////////////////////////////////////////////////////////////////////////////////////
//	24-BIT-Shifter
module SHIFTER_24_BIT(
	input CLK,
	input START,
	input IO_IN,
	input [23:0] DATA_OUT,
	output reg DONE,
	output reg CS,
	output reg CLK_OUT,
	output reg IO_OUT,
	output reg [23:0] DATA_IN
	);
	//
	parameter CLK_COUNTER = 5'd25;// 1MHz
	//
	reg [7:0] state;
	reg	[15:0]counter;
	reg	[15:0]counter_cs;
	reg enable;
	reg [7:0] clk_counter;
	reg [7:0] in_counter;
	reg [7:0] out_counter;	
	reg hri1; reg hri2; reg hri3; reg hri4;
	wire start_re; wire start_fe;
	wire clk_out_re; wire clk_out_fe;
	//
	assign start_re = (hri1 && !hri2);
	assign start_fe = (!hri1 && hri2);
	assign clk_out_re = (hri3 && !hri4);
	assign clk_out_fe = (!hri3 && hri4);	
	//
	initial
	begin
		DONE <= 0;
		CS <= 1;
		CLK_OUT <= 0;
		IO_OUT <= 0;
		DATA_IN <= 0;
		//
		state <= 0;
		counter <= 0;
		enable <= 0;
		clk_counter <= 0;
		in_counter <= 23;
		out_counter <= 23;
		counter_cs <= 0;
		hri1 <= 0; hri2 <= 0; hri3 <= 0; hri4 <= 0;
	end
	//
	always @(posedge CLK)
	begin
	//
	hri1 <= START;
	hri2 <= hri1;
	hri3 <= CLK_OUT;
	hri4 <= hri3;	
	//
	if (state == 0)
		begin
		counter_cs <= 0;
		clk_counter <= 0;
		in_counter <= 23;
		out_counter <= 23;
		if (start_re) 
			begin
			CS <= 0;
			DONE <= 0;
			state <= state + 1;		
			end
		//
		end
	//
	if (state == 1)
		begin
		counter_cs <= counter_cs + 1;
		if (counter_cs > 100) 
			begin
			counter_cs <= 0;
			enable <= 1;
			state <= state + 1;		
			end
		//
		end
	//
	if (state == 2)
		begin
		if (clk_counter == 48) 
			begin
			enable <= 0;
			state <= state + 1;		
			end
		//
		end
	//
	if (state == 3)
		begin
		counter_cs <= counter_cs + 1;
		if (counter_cs > 100) 
			begin
			counter_cs <= 0;
			CS <= 1;
			state <= state + 1;		
			end
		//
		end
	//
	if (state == 4)
		begin
		counter_cs <= counter_cs + 1;
		if (counter_cs > 100) 
			begin
			counter_cs <= 0;
			DONE <= 1;
			state <= 0;		
			end
		//
		end
	//
	////////////////////////////////////////////
	if (clk_out_re)
		begin
		DATA_IN[in_counter] <= IO_IN;
		if (in_counter > 0) in_counter <= in_counter - 1;
		end
	////////////////////////////////////////////
	IO_OUT <= DATA_OUT[out_counter];
	if (clk_out_fe)
		begin
		if (out_counter > 0) out_counter <= out_counter - 1;
		end
	////////////////////////////////////////////
	// Clockgenerator
	if (enable) 
		begin
		counter <= counter + 1;
		if(enable && (counter == CLK_COUNTER)) 
			begin
			counter <= 1;
			CLK_OUT <= !CLK_OUT;
			clk_counter <= clk_counter + 1;
			end	
		end
	else counter <= 1;
	//
	end
endmodule

////////////////////////////////////////////////////////////////////////////////////////////
//	Digitales Filter der Eingangssignale
module	SPI_INP_FILTER_CLIENT (
	input CLK, 
	input IN,
	output reg OUT
	);
//
parameter FILTER = 5'd10;
//
reg [4:0] ctr0;
reg [4:0] ctr1;
//
initial
	begin
	OUT <= 0;
	ctr0 <= 0;
	ctr1 <= 0;
	end
always	@(posedge CLK)
begin
	if (IN && !OUT)
		begin
		ctr0 <= 0;
		ctr1 <= ctr1 + 1;
		end
	//	
	if (!IN && OUT)
		begin
		ctr0 <= ctr0 + 1;
		ctr1 <= 0;
		end	
	//
	if (ctr0 == FILTER)
		begin
		ctr0 <= 0;
		ctr1 <= 0;
		OUT <= 0;
		end
	//
	if (ctr1 == FILTER)
		begin
		ctr0 <= 0;
		ctr1 <= 0;
		OUT <= 1;
		end
	//	
	if (((ctr0 > 0) && IN) || ((ctr1 > 0) && !IN))
		begin
		ctr0 <= 0;
		ctr1 <= 0;
		end	
end
endmodule
////////////////////////////////////////////////////////////////////////////////////////////
/*
ToDo: 
- FSM mit case
- Erweiterung PCB Tresor
- Beachtung der Warnungen bezüglich Datenbreite
- Signalfilter für die Eingangssignale der Tasten
*/

src/APP_IO_EXPANDER/CLIENT_MCP23S17/ICARUS_TB.v
`include "CLIENT_MCP23S17.v"
// http://verilogtutorial.blogspot.ch/2012/09/verilog-timescale-system-tasks.html
`timescale 10ns/1ns
//
module ICARUS_TB;
	integer file;
	reg clk;
	reg spi_miso;
	reg [15:0] led;
	wire spi_cs;
	wire spi_clk;
	wire spi_mosi;
	wire [15:0] sw;
	//
	initial 
	begin
		clk <= 1;
		spi_miso <= 0;
		led <= 0;
		//		
		$dumpfile("vcd\\\icarus_tb.vcd"); 
		$dumpvars(0, ICARUS_TB); 		
		//
		#100 spi_miso <= 1;
		#120 spi_miso <= 0;
		#100000 $finish; 
	end 
	//
	always #1        clk <= !clk;// 50MHz
	//
	CLIENT_MCP23S17 client_mcp23s17(clk,
								    spi_miso,
								    led,
								    spi_cs,
								    spi_clk,
								    spi_mosi,
								    sw);		
	//
endmodule
/*
cd D:\Dropbox\ABBTS_LABOR_DOZ\MOTION_CONTROL\FPGA_MODUL_MAX1000_DIT_RET_UR\FPGA_MODUL_MAX1000_DIT_RET_UR_01_00\src\APP_TIMER
C:\iverilog\bin\iverilog -s ICARUS_TB -o icarus_tb.o ICARUS_TB.v
C:\iverilog\bin\vvp icarus_tb.o
*/

src/APP_IO_EXPANDER/CLIENT_MCP23S17/vcd/icarus_tb.vcd
$date
	Wed May 30 09:32:57 2018
$end
$version
	Icarus Verilog
$end
$timescale
	1ns
$end
$scope module ICARUS_TB $end
$var wire 16 ! sw [15:0] $end
$var wire 1 " spi_mosi $end
$var wire 1 # spi_cs $end
$var wire 1 $ spi_clk $end
$var reg 1 % clk $end
$var reg 16 & led [15:0] $end
$var reg 1 ' spi_miso $end
$scope module client_mcp23s17 $end
$var wire 1 % CLK $end
$var wire 16 ( IO16_D [15:0] $end
$var wire 1 ' SPI_MISO $end
$var wire 1 ) done_fe $end
$var wire 1 * done_re $end
$var wire 1 + spi_miso_filter $end
$var wire 1 , done $end
$var wire 24 - data_in [23:0] $end
$var wire 1 " SPI_MOSI $end
$var wire 1 # SPI_CS $end
$var wire 1 $ SPI_CLK $end
$var reg 16 . IO16_SW [15:0] $end
$var reg 16 / counter [15:0] $end
$var reg 24 0 data_out [23:0] $end
$var reg 1 1 hri1 $end
$var reg 1 2 hri2 $end
$var reg 1 3 hri3 $end
$var reg 1 4 hri4 $end
$var reg 1 5 hri5 $end
$var reg 1 6 hri6 $end
$var reg 1 7 start $end
$var reg 5 8 state [4:0] $end
$scope module shifter_24_bit $end
$var wire 1 % CLK $end
$var wire 24 9 DATA_OUT [23:0] $end
$var wire 1 7 START $end
$var wire 1 : clk_out_fe $end
$var wire 1 ; clk_out_re $end
$var wire 1 < start_fe $end
$var wire 1 = start_re $end
$var wire 1 + IO_IN $end
$var reg 1 $ CLK_OUT $end
$var reg 1 # CS $end
$var reg 24 > DATA_IN [23:0] $end
$var reg 1 , DONE $end
$var reg 1 " IO_OUT $end
$var reg 8 ? clk_counter [7:0] $end
$var reg 16 @ counter [15:0] $end
$var reg 16 A counter_cs [15:0] $end
$var reg 1 B enable $end
$var reg 1 C hri1 $end
$var reg 1 D hri2 $end
$var reg 1 E hri3 $end
$var reg 1 F hri4 $end
$var reg 8 G in_counter [7:0] $end
$var reg 8 H out_counter [7:0] $end
$var reg 8 I state [7:0] $end
$upscope $end
$scope module spi_inp_filter_miso $end
$var wire 1 % CLK $end
$var wire 1 ' IN $end
$var reg 1 + OUT $end
$var reg 5 J ctr0 [4:0] $end
$var reg 5 K ctr1 [4:0] $end
$upscope $end
$upscope $end
$upscope $end
$enddefinitions $end
#0
$dumpvars
b0 K
b0 J
b0 I
b10111 H
b10111 G
0F
0E
0D
0C
0B
b0 A
b1 @
b0 ?
b0 >
0=
0<
0;
0:
b0 9
b1 8
07
06
05
04
03
02
01
b0 0
b0 /
bx .
b0 -
0,
0+
0*
0)
b0 (
0'
b0 &
1%
0$
1#
0"
bx !
$end
#10
0%
#20
b1 /
1%
#30
0%
#40
b10 /
1%
#50
0%
#60
b11 /
1%
#70
0%
#80
b100 /
1%
#90
0%
#100
b101 /
1%
#110
0%
#120
b110 /
1%
#130
0%
#140
b111 /
1%
#150
0%
#160
b1000 /
1%
#170
0%
#180
b1001 /
1%
#190
0%
#200
b1010 /
1%
#210
0%
#220
b1011 /
1%
#230
0%
#240
b1100 /
1%
#250
0%
#260
b1101 /
1%
#270
0%
#280
b1110 /
1%
#290
0%
#300
b1111 /
1%
#310
0%
#320
b10000 /
1%
#330
0%
#340
b10001 /
1%
#350
0%
#360
b10010 /
1%
#370
0%
#380
b10011 /
1%
#390
0%
#400
b10100 /
1%
#410
0%
#420
b10101 /
1%
#430
0%
#440
b10110 /
1%
#450
0%
#460
b10111 /
1%
#470
0%
#480
b11000 /
1%
#490
0%
#500
b11001 /
1%
#510
0%
#520
b11010 /
1%
#530
0%
#540
b11011 /
1%
#550
0%
#560
b11100 /
1%
#570
0%
#580
b11101 /
1%
#590
0%
#600
b11110 /
1%
#610
0%
#620
b11111 /
1%
#630
0%
#640
b100000 /
1%
#650
0%
#660
b100001 /
1%
#670
0%
#680
b100010 /
1%
#690
0%
#700
b100011 /
1%
#710
0%
#720
b100100 /
1%
#730
0%
#740
b100101 /
1%
#750
0%
#760
b100110 /
1%
#770
0%
#780
b100111 /
1%
#790
0%
#800
b101000 /
1%
#810
0%
#820
b101001 /
1%
#830
0%
#840
b101010 /
1%
#850
0%
#860
b101011 /
1%
#870
0%
#880
b101100 /
1%
#890
0%
#900
b101101 /
1%
#910
0%
#920
b101110 /
1%
#930
0%
#940
b101111 /
1%
#950
0%
#960
b110000 /
1%
#970
0%
#980
b110001 /
1%
#990
0%
#1000
b1 K
b110010 /
1%
1'
#1010
0%
#1020
b110011 /
b10 K
1%
#1030
0%
#1040
1+
b0 K
b110100 /
1%
#1050
0%
#1060
b110101 /
1%
#1070
0%
#1080
b110110 /
1%
#1090
0%
#1100
b110111 /
1%
#1110
0%
#1120
b111000 /
1%
#1130
0%
#1140
b111001 /
1%
#1150
0%
#1160
b111010 /
1%
#1170
0%
#1180
b111011 /
1%
#1190
0%
#1200
b111100 /
1%
#1210
0%
#1220
b111101 /
1%
#1230
0%
#1240
b111110 /
1%
#1250
0%
#1260
b111111 /
1%
#1270
0%
#1280
b1000000 /
1%
#1290
0%
#1300
b1000001 /
1%
#1310
0%
#1320
b1000010 /
1%
#1330
0%
#1340
b1000011 /
1%
#1350
0%
#1360
b1000100 /
1%
#1370
0%
#1380
b1000101 /
1%
#1390
0%
#1400
b1000110 /
1%
#1410
0%
#1420
b1000111 /
1%
#1430
0%
#1440
b1001000 /
1%
#1450
0%
#1460
b1001001 /
1%
#1470
0%
#1480
b1001010 /
1%
#1490
0%
#1500
b1001011 /
1%
#1510
0%
#1520
b1001100 /
1%
#1530
0%
#1540
b1001101 /
1%
#1550
0%
#1560
b1001110 /
1%
#1570
0%
#1580
b1001111 /
1%
#1590
0%
#1600
b1010000 /
1%
#1610
0%
#1620
b1010001 /
1%
#1630
0%
#1640
b1010010 /
1%
#1650
0%
#1660
b1010011 /
1%
#1670
0%
#1680
b1010100 /
1%
#1690
0%
#1700
b1010101 /
1%
#1710
0%
#1720
b1010110 /
1%
#1730
0%
#1740
b1010111 /
1%
#1750
0%
#1760
b1011000 /
1%
#1770
0%
#1780
b1011001 /
1%
#1790
0%
#1800
b1011010 /
1%
#1810
0%
#1820
b1011011 /
1%
#1830
0%
#1840
b1011100 /
1%
#1850
0%
#1860
b1011101 /
1%
#1870
0%
#1880
b1011110 /
1%
#1890
0%
#1900
b1011111 /
1%
#1910
0%
#1920
b1100000 /
1%
#1930
0%
#1940
b1100001 /
1%
#1950
0%
#1960
b1100010 /
1%
#1970
0%
#1980
b1100011 /
1%
#1990
0%
#2000
b1100100 /
1%
#2010
0%
#2020
b1100101 /
1%
#2030
0%
#2040
b1100110 /
1%
#2050
0%
#2060
b1100111 /
1%
#2070
0%
#2080
b1101000 /
1%
#2090
0%
#2100
b1101001 /
1%
#2110
0%
#2120
b1101010 /
1%
#2130
0%
#2140
b1101011 /
1%
#2150
0%
#2160
b1101100 /
1%
#2170
0%
#2180
b1101101 /
1%
#2190
0%
#2200
b1 J
b1101110 /
1%
0'
#2210
0%
#2220
b1101111 /
b10 J
1%
#2230
0%
#2240
0+
b0 J
b1110000 /
1%
#2250
0%
#2260
b1110001 /
1%
#2270
0%
#2280
b1110010 /
1%
#2290
0%
#2300
b1110011 /
1%
#2310
0%
#2320
b1110100 /
1%
#2330
0%
#2340
b1110101 /
1%
#2350
0%
#2360
b1110110 /
1%
#2370
0%
#2380
b1110111 /
1%
#2390
0%
#2400
b1111000 /
1%
#2410
0%
#2420
b1111001 /
1%
#2430
0%
#2440
b1111010 /
1%
#2450
0%
#2460
b1111011 /
1%
#2470
0%
#2480
b1111100 /
1%
#2490
0%
#2500
b1111101 /
1%
#2510
0%
#2520
b1111110 /
1%
#2530
0%
#2540
b1111111 /
1%
#2550
0%
#2560
b10000000 /
1%
#2570
0%
#2580
b10000001 /
1%
#2590
0%
#2600
b10000010 /
1%
#2610
0%
#2620
b10000011 /
1%
#2630
0%
#2640
b10000100 /
1%
#2650
0%
#2660
b10000101 /
1%
#2670
0%
#2680
b10000110 /
1%
#2690
0%
#2700
b10000111 /
1%
#2710
0%
#2720
b10001000 /
1%
#2730
0%
#2740
b10001001 /
1%
#2750
0%
#2760
b10001010 /
1%
#2770
0%
#2780
b10001011 /
1%
#2790
0%
#2800
b10001100 /
1%
#2810
0%
#2820
b10001101 /
1%
#2830
0%
#2840
b10001110 /
1%
#2850
0%
#2860
b10001111 /
1%
#2870
0%
#2880
b10010000 /
1%
#2890
0%
#2900
b10010001 /
1%
#2910
0%
#2920
b10010010 /
1%
#2930
0%
#2940
b10010011 /
1%
#2950
0%
#2960
b10010100 /
1%
#2970
0%
#2980
b10010101 /
1%
#2990
0%
#3000
b10010110 /
1%
#3010
0%
#3020
b10010111 /
1%
#3030
0%
#3040
b10011000 /
1%
#3050
0%
#3060
b10011001 /
1%
#3070
0%
#3080
b10011010 /
1%
#3090
0%
#3100
b10011011 /
1%
#3110
0%
#3120
b10011100 /
1%
#3130
0%
#3140
b10011101 /
1%
#3150
0%
#3160
b10011110 /
1%
#3170
0%
#3180
b10011111 /
1%
#3190
0%
#3200
b10100000 /
1%
#3210
0%
#3220
b10100001 /
1%
#3230
0%
#3240
b10100010 /
1%
#3250
0%
#3260
b10100011 /
1%
#3270
0%
#3280
b10100100 /
1%
#3290
0%
#3300
b10100101 /
1%
#3310
0%
#3320
b10100110 /
1%
#3330
0%
#3340
b10100111 /
1%
#3350
0%
#3360
b10101000 /
1%
#3370
0%
#3380
b10101001 /
1%
#3390
0%
#3400
b10101010 /
1%
#3410
0%
#3420
b10101011 /
1%
#3430
0%
#3440
b10101100 /
1%
#3450
0%
#3460
b10101101 /
1%
#3470
0%
#3480
b10101110 /
1%
#3490
0%
#3500
b10101111 /
1%
#3510
0%
#3520
b10110000 /
1%
#3530
0%
#3540
b10110001 /
1%
#3550
0%
#3560
b10110010 /
1%
#3570
0%
#3580
b10110011 /
1%
#3590
0%
#3600
b10110100 /
1%
#3610
0%
#3620
b10110101 /
1%
#3630
0%
#3640
b10110110 /
1%
#3650
0%
#3660
b10110111 /
1%
#3670
0%
#3680
b10111000 /
1%
#3690
0%
#3700
b10111001 /
1%
#3710
0%
#3720
b10111010 /
1%
#3730
0%
#3740
b10111011 /
1%
#3750
0%
#3760
b10111100 /
1%
#3770
0%
#3780
b10111101 /
1%
#3790
0%
#3800
b10111110 /
1%
#3810
0%
#3820
b10111111 /
1%
#3830
0%
#3840
b11000000 /
1%
#3850
0%
#3860
b11000001 /
1%
#3870
0%
#3880
b11000010 /
1%
#3890
0%
#3900
b11000011 /
1%
#3910
0%
#3920
b11000100 /
1%
#3930
0%
#3940
b11000101 /
1%
#3950
0%
#3960
b11000110 /
1%
#3970
0%
#3980
b11000111 /
1%
#3990
0%
#4000
b11001000 /
1%
#4010
0%
#4020
b11001001 /
1%
#4030
0%
#4040
b11001010 /
1%
#4050
0%
#4060
b11001011 /
1%
#4070
0%
#4080
b11001100 /
1%
#4090
0%
#4100
b11001101 /
1%
#4110
0%
#4120
b11001110 /
1%
#4130
0%
#4140
b11001111 /
1%
#4150
0%
#4160
b11010000 /
1%
#4170
0%
#4180
b11010001 /
1%
#4190
0%
#4200
b11010010 /
1%
#4210
0%
#4220
b11010011 /
1%
#4230
0%
#4240
b11010100 /
1%
#4250
0%
#4260
b11010101 /
1%
#4270
0%
#4280
b11010110 /
1%
#4290
0%
#4300
b11010111 /
1%
#4310
0%
#4320
b11011000 /
1%
#4330
0%
#4340
b11011001 /
1%
#4350
0%
#4360
b11011010 /
1%
#4370
0%
#4380
b11011011 /
1%
#4390
0%
#4400
b11011100 /
1%
#4410
0%
#4420
b11011101 /
1%
#4430
0%
#4440
b11011110 /
1%
#4450
0%
#4460
b11011111 /
1%
#4470
0%
#4480
b11100000 /
1%
#4490
0%
#4500
b11100001 /
1%
#4510
0%
#4520
b11100010 /
1%
#4530
0%
#4540
b11100011 /
1%
#4550
0%
#4560
b11100100 /
1%
#4570
0%
#4580
b11100101 /
1%
#4590
0%
#4600
b11100110 /
1%
#4610
0%
#4620
b11100111 /
1%
#4630
0%
#4640
b11101000 /
1%
#4650
0%
#4660
b11101001 /
1%
#4670
0%
#4680
b11101010 /
1%
#4690
0%
#4700
b11101011 /
1%
#4710
0%
#4720
b11101100 /
1%
#4730
0%
#4740
b11101101 /
1%
#4750
0%
#4760
b11101110 /
1%
#4770
0%
#4780
b11101111 /
1%
#4790
0%
#4800
b11110000 /
1%
#4810
0%
#4820
b11110001 /
1%
#4830
0%
#4840
b11110010 /
1%
#4850
0%
#4860
b11110011 /
1%
#4870
0%
#4880
b11110100 /
1%
#4890
0%
#4900
b11110101 /
1%
#4910
0%
#4920
b11110110 /
1%
#4930
0%
#4940
b11110111 /
1%
#4950
0%
#4960
b11111000 /
1%
#4970
0%
#4980
b11111001 /
1%
#4990
0%
#5000
b11111010 /
1%
#5010
0%
#5020
b11111011 /
1%
#5030
0%
#5040
b11111100 /
1%
#5050
0%
#5060
b11111101 /
1%
#5070
0%
#5080
b11111110 /
1%
#5090
0%
#5100
b11111111 /
1%
#5110
0%
#5120
b100000000 /
1%
#5130
0%
#5140
b100000001 /
1%
#5150
0%
#5160
b100000010 /
1%
#5170
0%
#5180
b100000011 /
1%
#5190
0%
#5200
b100000100 /
1%
#5210
0%
#5220
b100000101 /
1%
#5230
0%
#5240
b100000110 /
1%
#5250
0%
#5260
b100000111 /
1%
#5270
0%
#5280
b100001000 /
1%
#5290
0%
#5300
b100001001 /
1%
#5310
0%
#5320
b100001010 /
1%
#5330
0%
#5340
b100001011 /
1%
#5350
0%
#5360
b100001100 /
1%
#5370
0%
#5380
b100001101 /
1%
#5390
0%
#5400
b100001110 /
1%
#5410
0%
#5420
b100001111 /
1%
#5430
0%
#5440
b100010000 /
1%
#5450
0%
#5460
b100010001 /
1%
#5470
0%
#5480
b100010010 /
1%
#5490
0%
#5500
b100010011 /
1%
#5510
0%
#5520
b100010100 /
1%
#5530
0%
#5540
b100010101 /
1%
#5550
0%
#5560
b100010110 /
1%
#5570
0%
#5580
b100010111 /
1%
#5590
0%
#5600
b100011000 /
1%
#5610
0%
#5620
b100011001 /
1%
#5630
0%
#5640
b100011010 /
1%
#5650
0%
#5660
b100011011 /
1%
#5670
0%
#5680
b100011100 /
1%
#5690
0%
#5700
b100011101 /
1%
#5710
0%
#5720
b100011110 /
1%
#5730
0%
#5740
b100011111 /
1%
#5750
0%
#5760
b100100000 /
1%
#5770
0%
#5780
b100100001 /
1%
#5790
0%
#5800
b100100010 /
1%
#5810
0%
#5820
b100100011 /
1%
#5830
0%
#5840
b100100100 /
1%
#5850
0%
#5860
b100100101 /
1%
#5870
0%
#5880
b100100110 /
1%
#5890
0%
#5900
b100100111 /
1%
#5910
0%
#5920
b100101000 /
1%
#5930
0%
#5940
b100101001 /
1%
#5950
0%
#5960
b100101010 /
1%
#5970
0%
#5980
b100101011 /
1%
#5990
0%
#6000
b100101100 /
1%
#6010
0%
#6020
b100101101 /
1%
#6030
0%
#6040
b100101110 /
1%
#6050
0%
#6060
b100101111 /
1%
#6070
0%
#6080
b100110000 /
1%
#6090
0%
#6100
b100110001 /
1%
#6110
0%
#6120
b100110010 /
1%
#6130
0%
#6140
b100110011 /
1%
#6150
0%
#6160
b100110100 /
1%
#6170
0%
#6180
b100110101 /
1%
#6190
0%
#6200
b100110110 /
1%
#6210
0%
#6220
b100110111 /
1%
#6230
0%
#6240
b100111000 /
1%
#6250
0%
#6260
b100111001 /
1%
#6270
0%
#6280
b100111010 /
1%
#6290
0%
#6300
b100111011 /
1%
#6310
0%
#6320
b100111100 /
1%
#6330
0%
#6340
b100111101 /
1%
#6350
0%
#6360
b100111110 /
1%
#6370
0%
#6380
b100111111 /
1%
#6390
0%
#6400
b101000000 /
1%
#6410
0%
#6420
b101000001 /
1%
#6430
0%
#6440
b101000010 /
1%
#6450
0%
#6460
b101000011 /
1%
#6470
0%
#6480
b101000100 /
1%
#6490
0%
#6500
b101000101 /
1%
#6510
0%
#6520
b101000110 /
1%
#6530
0%
#6540
b101000111 /
1%
#6550
0%
#6560
b101001000 /
1%
#6570
0%
#6580
b101001001 /
1%
#6590
0%
#6600
b101001010 /
1%
#6610
0%
#6620
b101001011 /
1%
#6630
0%
#6640
b101001100 /
1%
#6650
0%
#6660
b101001101 /
1%
#6670
0%
#6680
b101001110 /
1%
#6690
0%
#6700
b101001111 /
1%
#6710
0%
#6720
b101010000 /
1%
#6730
0%
#6740
b101010001 /
1%
#6750
0%
#6760
b101010010 /
1%
#6770
0%
#6780
b101010011 /
1%
#6790
0%
#6800
b101010100 /
1%
#6810
0%
#6820
b101010101 /
1%
#6830
0%
#6840
b101010110 /
1%
#6850
0%
#6860
b101010111 /
1%
#6870
0%
#6880
b101011000 /
1%
#6890
0%
#6900
b101011001 /
1%
#6910
0%
#6920
b101011010 /
1%
#6930
0%
#6940
b101011011 /
1%
#6950
0%
#6960
b101011100 /
1%
#6970
0%
#6980
b101011101 /
1%
#6990
0%
#7000
b101011110 /
1%
#7010
0%
#7020
b101011111 /
1%
#7030
0%
